Workbook
Name Affectation_de_classe: Rules!$C$2:$C$50
Name Assegnazione_della_classe: Rules!$D$2:$D$50
Name Assegnazione_della_proprieta: Rules!$H$2:$H$50
Name Attribution_de_propriete: Rules!$G$2:$G$50
Name DataType: Rules!$I$2:$I$50
Name FAIR_Prinzipien: Rules!$M$2:$M$50
Name IFC_Data_Type: Rules!$J$2:$J$50
Name ISG___Informationssicherheitsgesetz: Rules!$L$2:$L$50
Name Klassen_Zuordnung: Rules!$B$2:$B$50
Name Klassifikation: Rules!$B$2:$B$50
Name LifecycleStatus: Rules!$N$2:$N$50
Name Markmals_Klassifikation: Rules!$F$2:$F$50
Name Merkmals_Zuordnung: Rules!$F$2:$F$50
Name Objekt_Einordnung: Rules!$A$2:$A$50
Name Property_Classification: Rules!$E$2:$E$50
Name Status: Rules!$K$2:$K$50

Sheet Impressum
B1: Data Dictionary - Flächenmanagement
B3: Dokumenteninformationen
C4: Status | D4: Entwurf
C5: Version | D5: 0.5.0
C6: Letzte Änderung | D6: 46272
C7: Autor | D7: Bauen digital Schweiz / buildingSMART Switzerland
B9: Trägerschaft
B11: Mit freundlicher Unterstützung von
C12: B+S AG | D12: MEGA
C13: Basler & Hofmann AG | D13: Mensch und Maschine Schweiz AG
C14: Bauenschweiz | D14: open BIM Verband
C15: Baumschlager Eberle Zürich AG | D15: Penzel Valier AG
C16: Buildup AG | D16: POM+
C17: CADMEC AG | D17: Roundtable Gebäudetechnik
C18: CRB | D18: Schindler Aufzüge AG
C19: Fachgruppe für Untertagbau (FGU) | D19: Schweizerische Bundesbahnen (SBB AG)
C20: FHNW | D20: Schweizerische Eidgenossenschaft – Bundesamt für Rüstung (armasuisse)
C21: Frutiger AG | D21: Schweizerische Eidgenossenschaft – Bundesamt für Strassen (ASTRA)
C22: HKG | D22: Schweizerischer Ingenieur- und Architektenverein (SIA)
C23: IBG Engineering AG | D23: Siemens AG
... C31: Marti Tunnel AG | D31: Walo AG
B33: Abgrenzung | D33: Fokus auf Austauschformat IFC 4.3.2.0 (IFC4X3_ADD2)
D34: Andere Formate (z. B. CityGML, gbXML, LandXML) sind kein Bestandteil
D35: Strukturvorlage ist eine methodische Grundlage, kein vollständiges Data Dictionaries
D36: Vollständige Data Dictionariess müssen in Datenbanken realsiert werden
D37: Die Handlungsempfehlung ist keine Implementierungsrichtlinie für Softwareentwicklung
D38: Die Strukturvorlage ist ein Best Practice Beispiel und kann jederzeit an neue Anforderungen angepasst werden. Es wird davon abgeraten, auf der Basis der Strukturvorlage Applikationen oder Tools zu entwickeln.
D39: Keine spezifischen Referenzen/Anbindungen an externe Data Dictionaries
B41: Copyright | D41: Dieses Dokument ist als Creative Commons Attribution-NonCommercial-ShareAlike 4.0 International Lizenz als Namensnennung – nichtkommerziell Weitergabe – unter gleichen Bedingungen lizenziert
D42: Weitere Informationen unter:
D43: Creative Commons
B45: Einschränkung und Handhabung | D45: Dieses Dokument erhebt keinen Anspruch auf Vollständigkeit. Es ist auch keine aus rechtlicher Sicht allgemeingültige Empfehlung oder Leitlinie, sondern soll alle Beteiligten in der Bau- und Immobilienbranche dabei unterstützen, die Abhängigkeit der einzelnen notwendigen Steuerungsinstrumente untereinander zu verstehen und richtig zuzuordnen.
B47: Herausgeber | D47: Bauen digital Schweiz / buildingSMART Switzerland
D48: info@bauen-digital.ch

Sheet Anleitung
A1: Anleitung Strukturvorlage Data Dictionaries
B3: Inhaltsverzeichnis
B5: 1 | C5: Handhabung
B6: 2 | C6: Governance
B7: 3 | C7: Header (Kopfzeile)
B8: 4 | C8: Classes (Objekte)
B9: 5 | C9: Properties (Merkmale)
B10: 6 | C10: Values (Werte)
B11: 7 | C11: Documents (Dokument) | G11: Data Template (Datenvorlage)
B12: 8 | C12: GroupOfProperties (Merkmalsgruppen)
B14: Hinweise zur Handhabung
B16: Farbcode zum ausfüllen der Strukturvorlage
B17: D | C17: Kein Farbcode: | H17: Diese Spalten müssen ausgefüllt werden.
H18: Bei sprachabhängigen Texten muss mind. EN und eine Landessprache ausgefüllt werden
C19: Grüner Farbcode: | H19: Dropdownliste: Automatische Übersetzung von EN in DE, FR, IT. Basiert auf der Übersetzung im Reiter "Rules"
C20: Grauer Farbcode: | H20: Zusätzliche Sprachen; falls erforderlich
C21: Blauer Farbcode: | H21: Diese Spalte ist system-generated, d.h. ist im Excl nicht auszufüllen, sondern wird vom Zielsystem (Datenbank) generiert
C22: Roter Farbcode: | H22: Wird automatisch durch das Validierungskript ausgefüllt
C24: A | D24: B | E24: C | F24: D | G24: E
B25: Hinweise zur Handhabung | C25: Erforderlich für Excel | D25: Sprachen | E25: Referenziert / System generiert | F25: Rules | G25: Erforderlich für Validierung
B26: A | C26: Erforderlich für Objektkatalog / Merkmalskatalog / Wertekatalog
C27: Definiert die Mindestanforderungen an einen Katalog. Unterscheidung zwischen yes = erforderlich / optional = bei Bedarf ergänzen / no = nicht notwendig
B28: B | C28: Sprachen
C29: Angabe zur Sprache: mehrsprachig = muss in der für den Katalog führenden Sprache enthalten sein
C30: EN, DE, FR, IT = gibt Sprache zwingend vor / neutral = nicht von Sprache abhängig
B31: C | C31: Regelt die Eingabe der Spalten
C32: Darf nicht vom Ersteller manuell ausgefüllt werden, sondern wird auf eine Quelle referenziert, resp. von eine Datenbank automatisch generiert
C33: referenced = Referenz auf anderen Katalog / system-generated = vom Zielsystem generiert
B34: D | C34: Vordefinierte Regeln
C35: Verweist auf die Dropdownliste in diesem Template
B36: E | C36: Erforderlich für eine automatische Validierung zur technischen Qualitätssicherung
C37: Gibt die Valdierungsregeln an, nach welchen die Spalteninhalte geprüft werden
A39: 2 | B39: Governance
B41: Vorgabe einer minimalen Governance für die verschiedenen Kataloge
B42: Optional können aller Regeln der SN EN ISO 23386 ergänzt werden
B44: A | C44: B | D44: C | E44: D | F44: E | G44: F | H44: G
B45: Governance | C45: Status | D45: Versionsdatum | E45: Herkunft (PROV) | F45: Regeln zur Festlegung von Merkmalen | G45: Regeln zur Festlegung von Merkmalsgruppen | H45: Management-Regeln für die Erstellung und Pflege
B46: B | C46: Vorgeschriebener Status des Merkmals während seines Lebenszyklus gemäss Liste (Enumeration)
B47: C | C47: Datum der Version. Format nach ISO 8601 = YYYY-MM-DDThh:mm:ssTDZ (T = festes Trennzeichen zwischen Datum und Uhrzeit / TDZ = Zeitzonenbezeichnung. Z = UTC, Abweichung zu UTC angeben)
C48: Beispiel: CET Zeit: 15:30 = UTC+2h > Korrekte Angabe: 2026-06-18T15:30+02:00
B49: D | C49: EN: PROV = Provenance, DE = Herkunft, Entstehungsgeschichte oder Nachweis der Datenherkunft
B50: E | C50: Um eindeutig, maschinenlesbar und für den Menschen verständlich zu sein, müssen Merkmale als Liste von Attributen festgelegt werden. Einige Attribute sind zwingend erforderlich und andere sind freigestellt.
C51: Hinweis: Entspricht PA002 bis PA040 - Attribute eines Merkmals
C52: Anwendung: Die Regeln zur Festlegung von Merkmalen müssen erst für über Datenbanken publizierte Data Dictionaries angewandt werden
B53: F | C53: Um eindeutig, maschinenlesbar und für den Menschen verständlich zu sein, müssen Merkmalsgruppen als Liste von Attributen festgelegt werden. Einige Attribute sind zwingend erforderlich und andere sind freigestellt.
C54: Hinweis: Entspricht GA001 bis GA02 - Attribute eines Merkmalsgruppe
C55: Anwendung: Die Regeln zur Festlegung von Merkmalsgruppen müssen erst für über Datenbanken publizierte Data Dictionaries angewandt werden
B56: G | C56: Verbindliche Regeln zur Erstellung, Pflege und Versionierung von Merkmalen und Merkmalsgruppen sowie zur koordinierten Abstimmung und Freigabe zwischen Akteuren zur Sicherstellung von Qualität, Konsistenz und Interoperabilität.
C57: Um eindeutig, maschinenlesbar und für den Menschen verständlich zu sein, müssen Merkmale als Liste von Attributen festgelegt werden. Einige Attribute sind zwingend erforderlich und andere sind freigestellt.
C58: Hinweis: Entspricht RA001 bis RA008 - Attribute einer Anfrage
C59: Anwendung: Die Management-Regeln für die Erstellung und Pflege müssen erst für über Datenbanken publizierte Data Dictionaries angewandt werden
A61: 3 | B61: Header (Kopfzeile)
B62: 1 | C62: Metadaten zur Erstellung eines Data Dictionaries
B63: 1.1 | C63: OrganizationCode = Kurzzeichen der Organisation
B64: 1.2 | C64: DictionaryCode = Systemgenerierter Code
B65: 1.3 | C65: DictionaryName (DE, FR, IT) = Name des Data Dictionary – mind. 1 Landessprache erforderlich
B66: 1.4 | C66: DictionaryName (EN) = Name des Data Dictionary in Englisch erforderlich
B67: 1.5 | C67: DictionaryVersion = Versionsnummer
B68: 1.6 | C68: DictionaryUri = Systemgeneriert
B69: 1.7 | C69: LifecycleStatus gemäss Dropdown Liste Ausfüllen
A71: 4 | B71: Classes (Objekte)
C73: B | D73: C | E73: D | F73: E | G73: F | H73: G | I73: H | J73: I | N73: J | R73: K | V73: L | W73: M | X73: N | Y73: O | Z73: P | AA73: Q | AB73: R | AC73: S | AD73: T | AE73: U | AF73: V | AG73: W
B74: Structural categorisation | C74: Domain/Domäne/Domaine/Dominio | D74: System/System/Système/Sistema | E74: Category/Kategorie/Catégorie/Categoria | F74: Classes | G74: GUID/URI | H74: Class-ID | I74: Class-Code | J74: Class-Assignment | K74: Klassen-Zuordnung (DE) | L74: Affectation de classe (FR) | M74: Assegnazione della classe (IT) | N74: Designation (EN) | O74: Bezeichnung (DE) | P74: Désignation (FR) | Q74: Designazione (IT) | R74: Description (EN) | S74: Beschreibung (DE) | T74: Description (FR) | U74: Descrizione (IT) | V74: IFC 4.3.2.0 (IFC4X3_ADD2) | W74: IFC_URI | X74: IfcObject Entity | Y74: IfcTypeObject Entity | Z74: PredefinedType | AA74: ObjectType | AB74: Governance | AC74: Status | AD74: Version date | AE74: Provenance (PROV) | AF74: RelatedDocuments | AG74: RelatedDocumentName (EN)
A76: 4.1 | B76: Structural categorisation (Strukturelle Einordnung)
C78: B | D78: C | E78: D
B79: Structural categorisation | C79: Domain/Domäne/Domaine/Dominio | D79: System/System/Système/Sistema | E79: Category/Kategorie/Catégorie/Categoria
B80: B | C80: Fachlicher Gesamtbereich, oberste Gliederung nach Disziplin Biespiele: Architektur, Tragwerk, HVAC, Verkehrswegebau, Bahntechnik, Werkleitungen
B81: C | C81: Funktionale Einheit innerhalb einer Domäne. Bündelt Objekte zu einer technischen Gesamtanlage oder Konstruktion.
C82: Beispiele: Lufttechnische Anlage, Fahrbahnkonstruktion, Oberbau Geleise, Abwasserentsorgung
B83: D | C83: Gliedert Objekte nach technischer Funktion, Material oder Bauart. Beispiele: Verteilnetz Lüftung, Belagsschichten, Schwellen, Kanalisation
A85: 4.2 | B85: Classes (Objekte)
B87: E | C87: F | D87: G | E87: H | F87: I | J87: J | N87: K
B88: Objekte | C88: GUID/URI | D88: Class-ID | E88: Class-Code | F88: Class-Assignment | G88: Klassen-Zuordnung (DE) | H88: Affectation de classe (FR) | I88: Assegnazione della classe (IT) | J88: Designation (EN) | K88: Bezeichnung (DE) | L88: Désignation (FR) | M88: Designazione (IT) | N88: Description (EN) | O88: Beschreibung (DE) | P88: Description (FR) | Q88: Descrizione (IT)
B89: F | C89: System generierte URI / benutzerdefinierte Backend-Referenz = Global eindeutige, persistente Identifikatoren zur interoperablen Referenzierung von Ressourcen. Mehrfach verwendete Objekte müssen die gleiche GUID/URI besitzen
B90: G | C90: Systemgeneriert Code, bezeiht sich auf „Designation“ (EN)
B91: H | C91: Stabiler, systeminterner Code zur eindeutigen, sprachneutralen Identifikation des Objekts. Mehrfach verwendete Objekte müssen die gleiche Class-Code besitzen
B92: I | C92: Einheitliche Einordnung von Objekten entlang einer strukturierten Gliederung (räumlich, logisch, kontextuell) als fachliche Abstraktion über den gesamten Lebenszyklus.
C93: Hinweis: Dropdown-Liste in Englisch auswählen, DE, FR, IT werden automatisch übersetzt
B94: J | C94: Eindeutiger, fachlicher Name eines Objekts zur Identifikation und Einordnung. EN = zwingend & mind. eine weitere Sprache (DE, FR, IT)
B95: K | C95: Kurzbeschreibung oder Definition zur fachlichen Erläuterung eines Objekts. EN = zwingend & mind. eine weitere Sprache (DE, FR, IT)
A97: 4.3 | B97: IFC 4.3.2.0 (IFC4X3_ADD2)
B99: L | C99: M | D99: N | E99: O | F99: P | G99: Q
B100: IFC 4.3.2.0 (IFC4X3_ADD2) | C100: GUID/URI | D100: IfcObject Entity | E100: IfcTypeObject Entity | F100: PredefinedType | G100: ObjectType
B101: M | C101: URI aus buildingSMART Data Dictionary (bSDD)
B102: N | C102: Ein IfcObject ist die Verallgemeinerung jedes semantisch behandelten Objekts oder Prozesses. Objekte sind Dinge, wie sie erscheinen – d. h. Instanzen.
C103: Beispiele: physisch greifbare Elemente wie Wände, Träger oder Verkleidungen, physisch vorhandene Elemente wie Räume oder konzeptionelle Elemente wie Raster oder virtuelle Begrenzungen.
C104: Der Begriff steht auch für Prozesse wie Arbeitsaufgaben, für Steuerungselemente wie Kostenpositionen oder für Akteure wie Personen, die am Entwurfsprozess beteiligt sind.
B105: O | C105: Der Objekttyp definiert die spezifischen Informationen zu einem Typ, die allen Instanzen dieses Typs gemeinsam sind.
B106: P | C106: Enumerierter Attributwert im IFC-Schema zur normierten Klassifizierung eines Objekttyps gemäss vordefinierter Auswahlliste.
B107: Q | C107: Freitext-Attribut zur zusätzlichen, projektspezifischen Typisierung eines Objekts, wenn keine passende Klassifizierung über PredefinedType existiert.
A109: 4.4 | B109: RelatedDocuments (zugehörige Dokumente)
B111: V | C111: W
B112: RelatedDocuments | C112: RelatedDocumentName (EN)
B113: W | C113: Referenz auf „DocumentName (EN)“ im Reiter "Documents"
A115: 5 | B115: Properties (Merkmale)
B117: A | C117: B | D117: C | E117: D | F117: E | J117: F | N117: G | R117: H | S117: I | T117: J | U117: K | V117: L | W117: M | X117: N
B118: Properties (Merkmale) | C118: GUID/URI | D118: Property-ID | E118: Property-Code | F118: Property-Assignment | G118: Merkmals-Zuordnung (DE) | H118: Attribution de propriété (FR) | I118: Assegnazione della proprietà (IT) | J118: Designation (EN) | K118: Bezeichnung (DE) | L118: Désignation (FR) | M118: Designazione (IT) | N118: Description (EN) | O118: Beschreibung (DE) | P118: Description (FR) | Q118: Descrizione (IT) | R118: DataType (Base Type) | S118: DataType (IFC) | T118: EnumerationDesignation (EN) | U118: IFC 4.3.2.0 (IFC4X3_ADD2) | V118: IFC_URI | W118: IfcPropertySet (Pset) / IfcQuantitySet (Qto) | X118: Units/Einheit/Unité/Unità
A120: 5.1 | B120: Properties (Merkmale)
B122: A | C122: B | D122: C | E122: D | F122: E | J122: F | N122: G | O122: H | P122: I | Q122: J | R122: K | S122: L | T122: M
B123: Properties (Merkmale) | C123: GUID/URI | D123: Property-ID | E123: Property-Code | F123: Property-Assignment | G123: Merkmals-Zuordnung (DE) | H123: Attribution de propriété (FR) | I123: Assegnazione della proprietà (IT) | J123: Designation (EN) | K123: Bezeichnung (DE) | L123: Désignation (FR) | M123: Designazione (IT) | N123: Description (EN) | O123: Beschreibung (DE) | P123: Description (FR) | Q123: Descrizione (IT) | R123: DataType (Base Type) | S123: DataType (IFC) | T123: EnumerationDesignation (EN)
...

Sheet Header
A1: Data Dictionary — Core Metadata
A2: Field | B2: Value | C2: Requirement | D2: Notes / Maps to
A3: IDENTIFICATION
A4: OrganizationCode | B4: IFMA | C4: user defined name (small or capital letters), max 7 chars | D4: Short org code — lowercase, max 7 chars, appears in all derived IRIs
A5: DictionaryCode | B5: data_dictionary_area_management | C5: SYSTEM-GENERATED | D5: Generated from DictionaryName (EN)
A6: DictionaryName (EN) | B6: Data Dictionary Area Management | C6: REQUIRED | D6: Required authoring title in English — source for DictionaryCode generation
A7: DictionaryName (DE) | B7: Data Dictionary Flächenmanagement | C7: OPTIONAL | D7: Core authoring title in German — minimal DCAT
A8: DictionaryName (FR) | B8: Data Dictionary Gestion des zones | C8: OPTIONAL | D8: Optional multilingual title support
A9: DictionaryName (IT) | B9: Data Dictionary Gestione dell'area | C9: DictionaryName (IT) | D9: Optional multilingual title support
A10: DictionaryVersion | B10: 0.5.0 | C10: REQUIRED | D10: Semantic versioning: MAJOR.MINOR.PATCH
A11: DictionaryUri | B11: https://example.com/BdCH/data_dictionary_area_management | C11: SYSTEM-GENERATED | D11: Derived from OrganizationCode and DictionaryCode; canonical base pattern https://example.com/<OrganizationCode>/<DictionaryCode>
C12: Guide | D12: Private organisations may keep only this tab and delete Dictionary_public.
A13: GOVERNANCE
A14: LifecycleStatus | B14: Candidate | C14: REQUIRED | D14: Governance state used to derive i14y registration status
A16: LEGEND
A17: REQUIRED: | B17: Must be filled before validation/export
A18: OPTIONAL: | B18: Fill if available

Sheet Classes
A1: Filter | B1: Hinweise zur Handhabung | C1: Structural categorisation | D1: Domain/Domäne/Domaine/Dominio | E1: System/System/Système/Sistema | F1: Category/Kategorie/Catégorie/Categoria | G1: Classes | H1: GUID/URI | I1: Class-ID | J1: Class-Code | K1: Class-Assignment | L1: Klassen-Zuordnung (DE) | M1: Affectation de classe (FR) | N1: Assegnazione della classe (IT) | O1: Designation (EN) | P1: Bezeichnung (DE) | Q1: Désignation (FR) | R1: Designazione (IT) | S1: Description (EN) | T1: Beschreibung (DE) | U1: Description (FR) | V1: Descrizione (IT) | W1: IFC 4.3.2.0 (IFC4X3_ADD2) | X1: IFC_URI | Y1: IfcObject Entity | Z1: IfcTypeObject Entity | AA1: PredefinedType | AB1: ObjectType | AC1: Governance | AD1: Status | AE1: Version date | AF1: Provenance (PROV) | AG1: RelatedDocuments | AH1: RelatedDocumentName (EN) | AJ1: User Defined (not part of HE Data Dictionary / not validated by Validator)
B2: Erforderlich für Excel | D2: optional | E2: optional | F2: optional | H2: no | I2: no | J2: yes | K2: yes | O2: yes | P2: yes | Q2: optional | R2: optional | S2: ja | T2: ja | U2: optional | V2: optional | X2: yes | Y2: yes | Z2: yes | AA2: yes | AB2: yes | AD2: yes | AE2: yes | AF2: yes | AH2: optional
B3: Sprachen | D3: multilingual | E3: multilingual | F3: multilingual | H3: neutral | I3: neutral | J3: neutral | K3: multilingual | L3: DE | M3: FR | N3: IT | O3: EN | P3: DE | Q3: FR | R3: IT | S3: EN | T3: DE | U3: FR | V3: IT | X3: multilingual | Y3: multilingual | Z3: multilingual | AA3: multilingual | AB3: multilingual | AD3: EN | AE3: neutral | AF3: EN | AH3: EN
B4: Referenziert / System generiert | H4: referenced | I4: system-generated | L4: system-generated | M4: system-generated | N4: system-generated | X4: referenced | Y4: referenced | Z4: referenced | AA4: referenced | AB4: referenced | AD4: referenced | AE4: referenced | AF4: referenced | AH4: referenced
B5: Dropdown Liste | K5: Rules.Class-Assignment | L5: Rules.Klassen-Zuordnung | M5: Rules.Affectation de classe | N5: Rules.Assegnazione della classe | AD5: Rules.Status
B6: Validierung | D6: user defined | E6: user defined | F6: user defined | H6: not validated. Info: If available system-generated URI / user defined backend reference | I6: system-generated from Designation (EN) | J6: user defined | K6: must match Rules.Class-Assignment | L6: system-generated from Class-Assignment via Rules | M6: system-generated from Class-Assignment via Rules | N6: system-generated from Class-Assignment via Rules | O6: user defined | P6: user defined | Q6: user defined | R6: user defined | S6: user defined | T6: user defined | U6: user defined | V6: user defined | X6: validated against identifiers from https://search.bsdd.buildingsmart.org/uri/buildingsmart/ifc/4.3 | Y6: validated against IFC 4.3 entity identifiers | Z6: validated against IFC 4.3 entity identifiers | AA6: validated against IFC predefined types when applicable | AB6: validated against IFC 4.3 entity identifiers | AD6: must match Rules.Status | AE6: date format 2026-06-18T15:30+02:00 | AF6: user defined | AH6: must match a DocumentName (EN) entry from Documents.DocumentName (EN)
J7: IFMA_C_31010000 | K7: Spatial structure | L7: Logische Zonen & Gruppen | M7: =IFERROR(INDEX(Rules!$C:$C,MATCH(K7,Rules!$A:$A,0)),"") -> Structure spatiale | N7: =IFERROR(INDEX(Rules!$D:$D,MATCH(K7,Rules!$A:$A,0)),"") -> Struttura spaziale | O7: Elevation | P7: Geschossebene | S7: The physical floor level or storey level of a building. | T7: Die physische Geschossebene bzw. Etage eines Gebäudes. | X7: https://identifier.buildingsmart.org/uri/buildingsmart/ifc/4.3/class/IfcBuildingStorey | Y7: IfcBuildingStorey | Z7: IfcBuildingStorey | AD7: Preview | AE7: 2026-07-09T10:30+02:00 | AF7: IFMA | AH7: Document type catalogue
J8: IFMA_C_31010001 | K8: Spatial structure | L8: =IFERROR(INDEX(Rules!$B:$B,MATCH(K8,Rules!$A:$A,0)),"") -> Räumliche Struktur | M8: =IFERROR(INDEX(Rules!$C:$C,MATCH(K8,Rules!$A:$A,0)),"") -> Structure spatiale | N8: =IFERROR(INDEX(Rules!$D:$D,MATCH(K8,Rules!$A:$A,0)),"") -> Struttura spaziale | O8: Site area | P8: Grundstückfläche | S8: Site area (plot area according to SIA 416) | T8: Parzellenfläche (Grundstückfläche gemäss SIA 416) | X8: https://identifier.buildingsmart.org/uri/buildingsmart/ifc/4.3/class/IfcSite | Y8: IfcSite | Z8: IfcSite | AD8: Preview | AE8: 2026-07-09T10:30+02:00 | AF8: IFMA | AH8: Document type catalogue
J9: IFMA_C_31010002 | K9: Spatial structure | L9: =IFERROR(INDEX(Rules!$B:$B,MATCH(K9,Rules!$A:$A,0)),"") -> Räumliche Struktur | M9: =IFERROR(INDEX(Rules!$C:$C,MATCH(K9,Rules!$A:$A,0)),"") -> Structure spatiale | N9: =IFERROR(INDEX(Rules!$D:$D,MATCH(K9,Rules!$A:$A,0)),"") -> Struttura spaziale | O9: Surrounding area | P9: Umgebungsfläche | S9: Surrounding area according to SIA 416 | T9: Umgebungsfläche gemäss SIA 416 | X9: https://identifier.buildingsmart.org/uri/buildingsmart/ifc/4.3/class/IfcSpace | Y9: IfcSpace | Z9: IfcSpace | AA9: USERDEFINED | AB9: SITE_AREA | AD9: Preview | AE9: 2026-07-09T10:30+02:00 | AF9: IFMA | AH9: Document type catalogue
J10: IFMA_C_31010003 | K10: Spatial structure | L10: =IFERROR(INDEX(Rules!$B:$B,MATCH(K10,Rules!$A:$A,0)),"") -> Räumliche Struktur | M10: =IFERROR(INDEX(Rules!$C:$C,MATCH(K10,Rules!$A:$A,0)),"") -> Structure spatiale | N10: =IFERROR(INDEX(Rules!$D:$D,MATCH(K10,Rules!$A:$A,0)),"") -> Struttura spaziale | O10: Gross floor area | P10: Geschossvolumen | S10: Volumetric representation of gross floor areas and storey volumes according to SIA 416 | T10: Volumetrische Darstellung der Geschossflächen (brutto) und Geschossvolumen gemäss SIA 416 | X10: https://identifier.buildingsmart.org/uri/buildingsmart/ifc/4.3/class/IfcSpace | Y10: IfcSpace | Z10: IfcSpace | AA10: USERDEFINED | AB10: SURROUNDING_AREA | AD10: Preview | AE10: 2026-07-09T10:30+02:00 | AF10: IFMA | AH10: Document type catalogue
J11: IFMA_C_31010004 | K11: Spatial structure | L11: =IFERROR(INDEX(Rules!$B:$B,MATCH(K11,Rules!$A:$A,0)),"") -> Räumliche Struktur | M11: =IFERROR(INDEX(Rules!$C:$C,MATCH(K11,Rules!$A:$A,0)),"") -> Structure spatiale | N11: =IFERROR(INDEX(Rules!$D:$D,MATCH(K11,Rules!$A:$A,0)),"") -> Struttura spaziale | O11: Room | P11: Nettogeschossfläche | S11: Internal spaces (net floor areas according to SIA 416) | T11: Innenräume (Nettogeschossflächen gemäss SIA 416) | X11: https://identifier.buildingsmart.org/uri/buildingsmart/ifc/4.3/class/IfcSpaceGFA | Y11: IfcSpace | Z11: IfcSpace | AA11: GFA | AD11: Preview | AE11: 2026-07-09T10:30+02:00 | AF11: IFMA | AH11: Document type catalogue
J12: IFMA_C_31010005 | K12: Spatial structure | L12: =IFERROR(INDEX(Rules!$B:$B,MATCH(K12,Rules!$A:$A,0)),"") -> Räumliche Struktur | M12: =IFERROR(INDEX(Rules!$C:$C,MATCH(K12,Rules!$A:$A,0)),"") -> Structure spatiale | N12: =IFERROR(INDEX(Rules!$D:$D,MATCH(K12,Rules!$A:$A,0)),"") -> Struttura spaziale | O12: External room | P12: Aussen-Nettogeschossfläche | S12: External spaces (external net floor areas according to SIA 416) | T12: Aussenräume (Aussen-Nettogeschossflächen gemäss SIA 416) | X12: https://identifier.buildingsmart.org/uri/buildingsmart/ifc/4.3/class/IfcSpace | Y12: IfcSpace | Z12: IfcSpace | AA12: USERDEFINED | AB12: ROOM | AD12: Preview | AE12: 2026-07-09T10:30+02:00 | AF12: IFMA | AH12: Document type catalogue
J13: IFMA_C_31010006 | K13: Spatial structure | L13: =IFERROR(INDEX(Rules!$B:$B,MATCH(K13,Rules!$A:$A,0)),"") -> Räumliche Struktur | M13: =IFERROR(INDEX(Rules!$C:$C,MATCH(K13,Rules!$A:$A,0)),"") -> Structure spatiale | N13: =IFERROR(INDEX(Rules!$D:$D,MATCH(K13,Rules!$A:$A,0)),"") -> Struttura spaziale | O13: Parking space | P13: Stellplatz | S13: Parking spaces such as car parking spaces, moped parking, bicycle parking, fire service access/parking bays | T13: Stellplätze wie z.B. Autoparkplatz, Mofa-Parkplatz, Velostellplatz, Feuerwehrstellplatz | X13: https://identifier.buildingsmart.org/uri/buildingsmart/ifc/4.3/class/IfcSpace | Y13: IfcSpace | Z13: IfcSpace | AA13: USERDEFINED | AB13: EXTERNAL_ROOM | AD13: Preview | AE13: 2026-07-09T10:30+02:00 | AF13: IFMA | AH13: Document type catalogue
J14: IFMA_C_31010007 | K14: Spatial structure | L14: =IFERROR(INDEX(Rules!$B:$B,MATCH(K14,Rules!$A:$A,0)),"") -> Räumliche Struktur | M14: =IFERROR(INDEX(Rules!$C:$C,MATCH(K14,Rules!$A:$A,0)),"") -> Structure spatiale | N14: =IFERROR(INDEX(Rules!$D:$D,MATCH(K14,Rules!$A:$A,0)),"") -> Struttura spaziale | O14: Rentable area | P14: Vermietbare Fläche | S14: Representation of lettable area where this differs from net floor areas | T14: Darstellung der vermietbaren Fläche, insofern diese von den Nettoraumflächen differiert | X14: https://identifier.buildingsmart.org/uri/buildingsmart/ifc/4.3/class/IfcSpacePARKING | Y14: IfcSpace | Z14: IfcSpace | AA14: PARKING | AD14: Preview | AE14: 2026-07-09T10:30+02:00 | AF14: IFMA | AH14: Document type catalogue
M16: =IFERROR(INDEX(Rules!$C:$C,MATCH(K16,Rules!$A:$A,0)),"") | N16: =IFERROR(INDEX(Rules!$D:$D,MATCH(K16,Rules!$A:$A,0)),"")
L17: =IFERROR(INDEX(Rules!$B:$B,MATCH(K17,Rules!$A:$A,0)),"") | M17: =IFERROR(INDEX(Rules!$C:$C,MATCH(K17,Rules!$A:$A,0)),"") | N17: =IFERROR(INDEX(Rules!$D:$D,MATCH(K17,Rules!$A:$A,0)),"")
L18: =IFERROR(INDEX(Rules!$B:$B,MATCH(K18,Rules!$A:$A,0)),"") | M18: =IFERROR(INDEX(Rules!$C:$C,MATCH(K18,Rules!$A:$A,0)),"") | N18: =IFERROR(INDEX(Rules!$D:$D,MATCH(K18,Rules!$A:$A,0)),"")
L19: =IFERROR(INDEX(Rules!$B:$B,MATCH(K19,Rules!$A:$A,0)),"") | M19: =IFERROR(INDEX(Rules!$C:$C,MATCH(K19,Rules!$A:$A,0)),"") | N19: =IFERROR(INDEX(Rules!$D:$D,MATCH(K19,Rules!$A:$A,0)),"")
L20: =IFERROR(INDEX(Rules!$B:$B,MATCH(K20,Rules!$A:$A,0)),"") | M20: =IFERROR(INDEX(Rules!$C:$C,MATCH(K20,Rules!$A:$A,0)),"") | N20: =IFERROR(INDEX(Rules!$D:$D,MATCH(K20,Rules!$A:$A,0)),"")
L21: =IFERROR(INDEX(Rules!$B:$B,MATCH(K21,Rules!$A:$A,0)),"") | M21: =IFERROR(INDEX(Rules!$C:$C,MATCH(K21,Rules!$A:$A,0)),"") | N21: =IFERROR(INDEX(Rules!$D:$D,MATCH(K21,Rules!$A:$A,0)),"")
L22: =IFERROR(INDEX(Rules!$B:$B,MATCH(K22,Rules!$A:$A,0)),"") | M22: =IFERROR(INDEX(Rules!$C:$C,MATCH(K22,Rules!$A:$A,0)),"") | N22: =IFERROR(INDEX(Rules!$D:$D,MATCH(K22,Rules!$A:$A,0)),"")
L23: =IFERROR(INDEX(Rules!$B:$B,MATCH(K23,Rules!$A:$A,0)),"") | M23: =IFERROR(INDEX(Rules!$C:$C,MATCH(K23,Rules!$A:$A,0)),"") | N23: =IFERROR(INDEX(Rules!$D:$D,MATCH(K23,Rules!$A:$A,0)),"")
L24: =IFERROR(INDEX(Rules!$B:$B,MATCH(K24,Rules!$A:$A,0)),"") | M24: =IFERROR(INDEX(Rules!$C:$C,MATCH(K24,Rules!$A:$A,0)),"") | N24: =IFERROR(INDEX(Rules!$D:$D,MATCH(K24,Rules!$A:$A,0)),"")

Sheet Properties
A1: Filter | B1: Hinweise zur Handhabung | C1: Properties | D1: GUID/URI | E1: Property-ID | F1: Property-Code | G1: Property-Assignment | H1: Merkmals-Zuordnung (DE) | I1: Attribution de propriété (FR) | J1: Assegnazione della proprietà (IT) | K1: Designation (EN) | L1: Bezeichnung (DE) | M1: Désignation (FR) | N1: Designazione (IT) | O1: Description (EN) | P1: Beschreibung (DE) | Q1: Description (FR) | R1: Descrizione (IT) | S1: DataType (Base Type) | T1: DataType (IFC) | U1: EnumerationDesignation (EN) | V1: IFC 4.3.2.0 (IFC4X3_ADD2) | W1: IFC_URI | X1: IfcPropertySet (Pset) IfcQuantitySet (Qto) | Y1: Units/Einheit/Unité/Unità | Z1: Governance | AA1: Status | AB1: Version date | AC1: Provenance (PROV) | AE1: User Defined (not part of HE Data Dictionary / not validated by Validator)
B2: Erforderlich für Excel | D2: no | E2: no | F2: yes | G2: yes | K2: yes | L2: yes | M2: optional | N2: optional | O2: yes | P2: yes | Q2: optional | R2: optional | S2: yes | T2: yes | U2: yes | W2: yes | X2: yes | Y2: yes | AA2: yes | AB2: yes | AC2: yes
B3: Sprachen | D3: neutral | E3: neutral | F3: neutral | G3: neutral | H3: DE | I3: FR | J3: IT | K3: EN | L3: DE | M3: FR | N3: IT | O3: EN | P3: DE | Q3: FR | R3: IT | S3: neutral | T3: neutral | U3: EN | W3: neutral | X3: EN | Y3: neutral | AA3: EN | AB3: neutral | AC3: EN
B4: Referenziert / System generiert | D4: referenced | E4: system-generated | H4: system-generated | I4: system-generated | J4: system-generated | S4: referenced | T4: referenced | U4: referenced | W4: referenced | X4: referenced | AA4: referenced | AB4: referenced | AC4: referenced
B5: Dropdown Liste | G5: Rules.Property-Assignment | H5: Rules.Merkmals-Zuordnung | I5: Rules.Attribution de propriété | J5: Rules.Assegnazione della proprietà | S5: Rules.DataType | T5: Rules.IFC Data Type | AA5: Rules.Status
B6: Validierung | D6: not validated. Info: If available system-generated URI / user defined backend reference | E6: system-generated from Designation (EN) | F6: user defined | G6: must match Rules.Property-Assignment | H6: system-generated from Property-Assignment via Rules | I6: system-generated from Property-Assignment via Rules | J6: system-generated from Property-Assignment via Rules | K6: user defined | L6: user defined | M6: user defined | N6: user defined | O6: user defined | P6: user defined | Q6: user defined | R6: user defined | S6: must match Rules.DataType | T6: must match Rules.IFC Data Type | U6: must match a Designation (EN) entry from Values.Designation (EN) | W6: validated against identifiers from https://search.bsdd.buildingsmart.org/uri/buildingsmart/ifc/4.3 | X6: validated against IFC 4.3 property/quantity set identifiers when IFC_URI is present | Y6: user defined | AA6: must match Rules.Status | AB6: date format 2026-06-18T15:30+02:00 | AC6: user defined
F7: IFMA_P_31020002 | G7: Identification and classification | H7: =IFERROR(INDEX(Rules!$F:$F,MATCH(G7,Rules!$E:$E,0)),"") -> Identifikation und Klassifikation | I7: =IFERROR(INDEX(Rules!$G:$G,MATCH(G7,Rules!$E:$E,0)),"") -> Identification et classification | J7: =IFERROR(INDEX(Rules!$H:$H,MATCH(G7,Rules!$E:$E,0)),"") -> Identificazione e classificazione | K7: Name | L7: ID | O7: Unique room number or floor number according to numbering scheme | P7: Eindeutige Raumnummer bzw. Geschossnummer gemäss Nummerierungskonzept | S7: STRING | T7: IfcLabel | AA7: Preview | AB7: 2026-07-09T10:30+02:00 | AC7: IFMA
F8: IFMA_P_31020003 | G8: Identification and classification | H8: =IFERROR(INDEX(Rules!$F:$F,MATCH(G8,Rules!$E:$E,0)),"") -> Identifikation und Klassifikation | I8: =IFERROR(INDEX(Rules!$G:$G,MATCH(G8,Rules!$E:$E,0)),"") -> Identification et classification | J8: =IFERROR(INDEX(Rules!$H:$H,MATCH(G8,Rules!$E:$E,0)),"") -> Identificazione e classificazione | K8: LongName | L8: Raumbezeichnung | O8: Designation | P8: Bezeichnung | S8: STRING | T8: IfcLabel | AA8: Preview | AB8: 2026-07-09T10:30+02:00 | AC8: IFMA
F9: IFMA_P_31020004 | G9: Identification and classification | H9: =IFERROR(INDEX(Rules!$F:$F,MATCH(G9,Rules!$E:$E,0)),"") -> Identifikation und Klassifikation | I9: =IFERROR(INDEX(Rules!$G:$G,MATCH(G9,Rules!$E:$E,0)),"") -> Identification et classification | J9: =IFERROR(INDEX(Rules!$H:$H,MATCH(G9,Rules!$E:$E,0)),"") -> Identificazione e classificazione | K9: SIA_416_2003 | L9: SIA 416:2003 Flächenart | O9: Classification according to SIA 416 / 2003 | P9: Klassifizierung gemäss SIA 416 / 2003 | S9: STRING | T9: IfcLabel | U9: Area type SIA 416 code | AA9: Preview | AB9: 2026-07-09T10:30+02:00 | AC9: IFMA
F10: IFMA_P_31020007 | G10: Identification and classification | H10: =IFERROR(INDEX(Rules!$F:$F,MATCH(G10,Rules!$E:$E,0)),"") -> Identifikation und Klassifikation | I10: =IFERROR(INDEX(Rules!$G:$G,MATCH(G10,Rules!$E:$E,0)),"") -> Identification et classification | J10: =IFERROR(INDEX(Rules!$H:$H,MATCH(G10,Rules!$E:$E,0)),"") -> Identificazione e classificazione | K10: SIA_380_2015 | L10: SIA 380:2015 Raumbezeichnung | O10: Classification according to SIA 380 / 2015 | P10: Klassifizierung gemäss SIA 380 / 2015 | S10: STRING | T10: IfcLabel | U10: Room designation SIA 380 label | AA10: Preview | AB10: 2026-07-09T10:30+02:00 | AC10: IFMA
F11: IFMA_P_31020008 | G11: Identification and classification | H11: =IFERROR(INDEX(Rules!$F:$F,MATCH(G11,Rules!$E:$E,0)),"") -> Identifikation und Klassifikation | I11: =IFERROR(INDEX(Rules!$G:$G,MATCH(G11,Rules!$E:$E,0)),"") -> Identification et classification | J11: =IFERROR(INDEX(Rules!$H:$H,MATCH(G11,Rules!$E:$E,0)),"") -> Identificazione e classificazione | K11: SIA_2024_2021 | L11: SIA 2024:2001 Raumnutzung | O11: Classification according to SIA 2024 / 2021 | P11: Klassifizierung gemäss SIA 2024 / 2021 | S11: STRING | T11: IfcLabel | U11: Room usage SIA 2024 code | AA11: Preview | AB11: 2026-07-09T10:30+02:00 | AC11: IFMA
F12: IFMA_P_31020010 | G12: Identification and classification | H12: =IFERROR(INDEX(Rules!$F:$F,MATCH(G12,Rules!$E:$E,0)),"") -> Identifikation und Klassifikation | I12: =IFERROR(INDEX(Rules!$G:$G,MATCH(G12,Rules!$E:$E,0)),"") -> Identification et classification | J12: =IFERROR(INDEX(Rules!$H:$H,MATCH(G12,Rules!$E:$E,0)),"") -> Identificazione e classificazione | K12: SIA_d0615_2000 | L12: SIA d0165:2000 Nutzungsart | O12: Classification according to SIA D 0165 / 2000 | P12: Klassifizierung gemäss SIA D 0165 / 2000 | S12: STRING | T12: IfcLabel | U12: Area type d0165 code | AA12: Preview | AB12: 2026-07-09T10:30+02:00 | AC12: IFMA
F13: IFMA_P_31020012 | G13: Operating conditions and limits | H13: =IFERROR(INDEX(Rules!$F:$F,MATCH(G13,Rules!$E:$E,0)),"") -> Betriebsbedingungen und Grenzwerte | I13: =IFERROR(INDEX(Rules!$G:$G,MATCH(G13,Rules!$E:$E,0)),"") -> Conditions de fonctionnement et limites | J13: =IFERROR(INDEX(Rules!$H:$H,MATCH(G13,Rules!$E:$E,0)),"") -> Condizioni operative e limiti | K13: ProgramUse | L13: Raumnutzung | O13: Room usage according to room programme | P13: Raumnutzung gemäss Raumprogramm | S13: STRING | T13: IfcLabel | U13: Program use | AA13: Preview | AB13: 2026-07-09T10:30+02:00 | AC13: IFMA
F14: IFMA_P_31020013 | G14: Operating conditions and limits | H14: =IFERROR(INDEX(Rules!$F:$F,MATCH(G14,Rules!$E:$E,0)),"") -> Betriebsbedingungen und Grenzwerte | I14: =IFERROR(INDEX(Rules!$G:$G,MATCH(G14,Rules!$E:$E,0)),"") -> Conditions de fonctionnement et limites | J14: =IFERROR(INDEX(Rules!$H:$H,MATCH(G14,Rules!$E:$E,0)),"") -> Condizioni operative e limiti | K14: RoomType | L14: Raumtyp | O14: Room type (functional type) according to room catalogue (room data sheets) | P14: Raumtyp (Funktionstyp) gemäss Raumkatalog (Raumdatenblätter) | S14: STRING | T14: IfcLabel | U14: Room type | AA14: Preview | AB14: 2026-07-09T10:30+02:00 | AC14: IFMA
F15: IFMA_P_31020014 | G15: Identification and classification | H15: =IFERROR(INDEX(Rules!$F:$F,MATCH(G15,Rules!$E:$E,0)),"") -> Identifikation und Klassifikation | I15: =IFERROR(INDEX(Rules!$G:$G,MATCH(G15,Rules!$E:$E,0)),"") -> Identification et classification | J15: =IFERROR(INDEX(Rules!$H:$H,MATCH(G15,Rules!$E:$E,0)),"") -> Identificazione e classificazione | K15: UnitType | L15: Einheitstyp | O15: Unit type, in particular dwelling type (e.g. 3.5-room flat) | P15: Einheitstyp, insb. Wohnungstyp z.B. 3,5-Zi | S15: STRING | T15: IfcLabel | U15: Unit type | AA15: Preview | AB15: 2026-07-09T10:30+02:00 | AC15: IFMA
F16: IFMA_P_31020015 | G16: Identification and classification | H16: =IFERROR(INDEX(Rules!$F:$F,MATCH(G16,Rules!$E:$E,0)),"") -> Identifikation und Klassifikation | I16: =IFERROR(INDEX(Rules!$G:$G,MATCH(G16,Rules!$E:$E,0)),"") -> Identification et classification | J16: =IFERROR(INDEX(Rules!$H:$H,MATCH(G16,Rules!$E:$E,0)),"") -> Identificazione e classificazione | K16: Unit_ID | L16: Einheitsnummer | O16: Unique unit number (ID) according to numbering scheme for sale or rental units (e.g. apartment number) | P16: Eindeutige Einheitsnummer (ID) gemäss Nummerierungskonzept für Verkaufs- bzw. Mieteinheiten, z.B. Wohnungsnummer | S16: STRING | T16: IfcLabel | U16: Unit ID | AA16: Preview | AB16: 2026-07-09T10:30+02:00 | AC16: IFMA
F17: IFMA_P_31020016 | G17: Identification and classification | H17: =IFERROR(INDEX(Rules!$F:$F,MATCH(G17,Rules!$E:$E,0)),"") -> Identifikation und Klassifikation | I17: =IFERROR(INDEX(Rules!$G:$G,MATCH(G17,Rules!$E:$E,0)),"") -> Identification et classification | J17: =IFERROR(INDEX(Rules!$H:$H,MATCH(G17,Rules!$E:$E,0)),"") -> Identificazione e classificazione | K17: RoomNumberFM | L17: Raumnummer_Betrieb | O17: Operational room number | P17: Raumnummer Betrieb | S17: STRING | T17: IfcLabel | U17: Operational room number | AA17: Preview | AB17: 2026-07-09T10:30+02:00 | AC17: IFMA
F18: IFMA_P_31020017 | G18: Identification and classification | H18: =IFERROR(INDEX(Rules!$F:$F,MATCH(G18,Rules!$E:$E,0)),"") -> Identifikation und Klassifikation | I18: =IFERROR(INDEX(Rules!$G:$G,MATCH(G18,Rules!$E:$E,0)),"") -> Identification et classification | J18: =IFERROR(INDEX(Rules!$H:$H,MATCH(G18,Rules!$E:$E,0)),"") -> Identificazione e classificazione | K18: RoomSignalLabel | L18: Raumbeschriftung | O18: Room labelled | P18: Raum beschriftet | S18: STRING | T18: IfcLabel | U18: Room signal label | AA18: Preview | AB18: 2026-07-09T10:30+02:00 | AC18: IFMA
F19: IFMA_P_31020018 | G19: Operating conditions and limits | H19: =IFERROR(INDEX(Rules!$F:$F,MATCH(G19,Rules!$E:$E,0)),"") -> Betriebsbedingungen und Grenzwerte | I19: =IFERROR(INDEX(Rules!$G:$G,MATCH(G19,Rules!$E:$E,0)),"") -> Conditions de fonctionnement et limites | J19: =IFERROR(INDEX(Rules!$H:$H,MATCH(G19,Rules!$E:$E,0)),"") -> Condizioni operative e limiti | K19: CleaningGroup | L19: Reinigungsgruppe | O19: Cleaning group | P19: Reinigungsgruppe | S19: STRING | T19: IfcLabel | U19: Cleaning group | AA19: Preview | AB19: 2026-07-09T10:30+02:00 | AC19: IFMA
F20: IFMA_P_31020019 | G20: Physical characteristics | H20: =IFERROR(INDEX(Rules!$F:$F,MATCH(G20,Rules!$E:$E,0)),"") -> Physikalische Eigenschaften | I20: =IFERROR(INDEX(Rules!$G:$G,MATCH(G20,Rules!$E:$E,0)),"") -> Caractéristiques physiques | J20: =IFERROR(INDEX(Rules!$H:$H,MATCH(G20,Rules!$E:$E,0)),"") -> Caratteristiche fisiche | K20: AreaLoad | L20: Flächenlast | O20: Area load | P20: Flächenlast | S20: REAL | T20: IfcPlanarForceMeasure | U20: Area load | AA20: Preview | AB20: 2026-07-09T10:30+02:00 | AC20: IFMA
... F29: IFMA_P_31020028 | G29: Operating conditions and limits | H29: =IFERROR(INDEX(Rules!$F:$F,MATCH(G29,Rules!$E:$E,0)),"") -> Betriebsbedingungen und Grenzwerte | I29: =IFERROR(INDEX(Rules!$G:$G,MATCH(G29,Rules!$E:$E,0)),"") -> Conditions de fonctionnement et limites | J29: =IFERROR(INDEX(Rules!$H:$H,MATCH(G29,Rules!$E:$E,0)),"") -> Condizioni operative e limiti | K29: IsRentable | L29: Vermietbarkeit | O29: Letting suitability | P29: Vermietbarkeit | S29: BOOLEAN | T29: IfcBoolean | U29: Rentable | AA29: Preview | AB29: 2026-07-09T10:30+02:00 | AC29: IFMA
D30: https://identifier.buildingsmart.org/uri/buildingsmart/ifc/4.3/prop/IsExternal | F30: IFMA_P_31020029 | G30: Identification and classification | H30: =IFERROR(INDEX(Rules!$F:$F,MATCH(G30,Rules!$E:$E,0)),"") -> Identifikation und Klassifikation | I30: =IFERROR(INDEX(Rules!$G:$G,MATCH(G30,Rules!$E:$E,0)),"") -> Identification et classification | J30: =IFERROR(INDEX(Rules!$H:$H,MATCH(G30,Rules!$E:$E,0)),"") -> Identificazione e classificazione | K30: IsExternal | L30: Aussenraum | O30: Indicates whether the element is intended for outdoor use (TRUE) or not (FALSE). If set to (TRUE), the element is an external element that forms the outer boundary of a building. | P30: Angabe, ob das Element für die Verwendung im Aussenbereich vorgesehen ist (TRUE) oder nicht (FALSE). Bei (TRUE) handelt es sich um ein Aussenelement, das ein Gebäude nach außen abschliesst. | S30: BOOLEAN | T30: IfcBoolean | U30: External space | W30: https://identifier.buildingsmart.org/uri/buildingsmart/ifc/4.3/prop/IsExternal | X30: Pset_SpaceCommon | AA30: Preview | AB30: 2026-07-09T10:30+02:00 | AC30: IFMA
D31: https://identifier.buildingsmart.org/uri/buildingsmart/ifc/4.3/prop/OccupancyType | F31: IFMA_P_31020030 | G31: Operating conditions and limits | H31: =IFERROR(INDEX(Rules!$F:$F,MATCH(G31,Rules!$E:$E,0)),"") -> Betriebsbedingungen und Grenzwerte | I31: =IFERROR(INDEX(Rules!$G:$G,MATCH(G31,Rules!$E:$E,0)),"") -> Conditions de fonctionnement et limites | J31: =IFERROR(INDEX(Rules!$H:$H,MATCH(G31,Rules!$E:$E,0)),"") -> Condizioni operative e limiti | K31: OccupancyType | L31: Nutzungsart | O31: Occupancy type for this object.; It is defined according to the presiding national building code. | P31: Nutzungsart dieses Objekts; sie wird gemäss den geltenden nationalen Bauvorschriften definiert. | S31: STRING | T31: IfcLabel | U31: Occupancy type | W31: https://identifier.buildingsmart.org/uri/buildingsmart/ifc/4.3/prop/OccupancyType | X31: Pset_SpaceOccupancyRequirements | AA31: Preview | AB31: 2026-07-09T10:30+02:00 | AC31: IFMA
F32: IFMA_P_31020031 | G32: Geometric characteristics | H32: =IFERROR(INDEX(Rules!$F:$F,MATCH(G32,Rules!$E:$E,0)),"") -> Geometrische Eigenschaften | I32: =IFERROR(INDEX(Rules!$G:$G,MATCH(G32,Rules!$E:$E,0)),"") -> Caractéristiques géométriques | J32: =IFERROR(INDEX(Rules!$H:$H,MATCH(G32,Rules!$E:$E,0)),"") -> Caratteristiche geometriche | K32: MinimumHeadroom | L32: Raumnutzhöhe | O32: Effective clear height | P32: Lichte Höhe | S32: REAL | T32: IfcLengthMeasure | U32: Headroom | X32: Pset_SpaceOccupancyRequirements | AA32: Preview | AB32: 2026-07-09T10:30+02:00 | AC32: IFMA
D33: https://identifier.buildingsmart.org/uri/buildingsmart/ifc/4.3/prop/OccupancyNumberPeak | F33: IFMA_P_31020032 | G33: Operating conditions and limits | H33: =IFERROR(INDEX(Rules!$F:$F,MATCH(G33,Rules!$E:$E,0)),"") -> Betriebsbedingungen und Grenzwerte | I33: =IFERROR(INDEX(Rules!$G:$G,MATCH(G33,Rules!$E:$E,0)),"") -> Conditions de fonctionnement et limites | J33: =IFERROR(INDEX(Rules!$H:$H,MATCH(G33,Rules!$E:$E,0)),"") -> Condizioni operative e limiti | K33: OccupancyNumberPeak | L33: Personenbelegung geplant | O33: Maximal number of people required for the activity assigned to this space in peak time. | P33: Maximale Anzahl Personen für die zugewiesene Nutzung dieses Raums in Spitzenzeiten. | S33: INTEGER | T33: IfcInteger | U33: Planned occupancy | W33: https://identifier.buildingsmart.org/uri/buildingsmart/ifc/4.3/prop/OccupancyNumberPeak | X33: Pset_SpaceOccupancyRequirements | AA33: Preview | AB33: 2026-07-09T10:30+02:00 | AC33: IFMA
D34: https://identifier.buildingsmart.org/uri/buildingsmart/ifc/4.3/prop/OccupancyNumber | F34: IFMA_P_31020033 | G34: Operating conditions and limits | H34: =IFERROR(INDEX(Rules!$F:$F,MATCH(G34,Rules!$E:$E,0)),"") -> Betriebsbedingungen und Grenzwerte | I34: =IFERROR(INDEX(Rules!$G:$G,MATCH(G34,Rules!$E:$E,0)),"") -> Conditions de fonctionnement et limites | J34: =IFERROR(INDEX(Rules!$H:$H,MATCH(G34,Rules!$E:$E,0)),"") -> Condizioni operative e limiti | K34: OccupancyNumber | L34: Personenbelegung ist | O34: Number of people required for the activity assigned to this space. | P34: Anzahl Personen für die zugewiesene Nutzung dieses Raums. | S34: INTEGER | T34: IfcInteger | U34: Actual occupancy | W34: https://identifier.buildingsmart.org/uri/buildingsmart/ifc/4.3/prop/OccupancyNumber | X34: Pset_SpaceOccupancyRequirements | AA34: Preview | AB34: 2026-07-09T10:30+02:00 | AC34: IFMA
D35: https://identifier.buildingsmart.org/uri/buildingsmart/ifc/4.3/prop/FloorCovering | F35: IFMA_P_31020034 | G35: Material and construction | H35: =IFERROR(INDEX(Rules!$F:$F,MATCH(G35,Rules!$E:$E,0)),"") -> Material und Aufbau | I35: =IFERROR(INDEX(Rules!$G:$G,MATCH(G35,Rules!$E:$E,0)),"") -> Matériau et constitution | J35: =IFERROR(INDEX(Rules!$H:$H,MATCH(G35,Rules!$E:$E,0)),"") -> Materiale e struttura | K35: FloorCovering | L35: Bodenbelag | O35: Label to indicate the material or finish of the space flooring. The label is used for room book information and often displayed in room stamp.The material information is provided in absence of an Covering (type=FLOORING) object with own shape representation and material assignment. In case of inconsistency the material assigned to Covering elements takes precedence. | P35: Kennzeichnung des Materials bzw. der Oberfläche des Bodenbelags im Raum. Die Kennzeichnung wird für Raumbuchinformationen verwendet und häufig im Raumstempel angezeigt. Die Materialinformation wird bereitgestellt, sofern kein Covering-Objekt (Typ=FLOORING) mit eigener Geometrie und Materialzuweisung vorhanden ist. Bei Inkonsistenzen hat die Materialzuweisung der Covering-Elemente Vorrang. | S35: STRING | T35: IfcLabel | U35: Floor covering | W35: https://identifier.buildingsmart.org/uri/buildingsmart/ifc/4.3/prop/FloorCovering | X35: Pset_SpaceCoveringRequirements | AA35: Preview | AB35: 2026-07-09T10:30+02:00 | AC35: IFMA
D36: https://identifier.buildingsmart.org/uri/buildingsmart/ifc/4.3/prop/WallCovering | F36: IFMA_P_31020035 | G36: Manufacturer and product information | H36: =IFERROR(INDEX(Rules!$F:$F,MATCH(G36,Rules!$E:$E,0)),"") -> Hersteller- und Produktinformationen | I36: =IFERROR(INDEX(Rules!$G:$G,MATCH(G36,Rules!$E:$E,0)),"") -> Informations sur le fabricant et le produit | J36: =IFERROR(INDEX(Rules!$H:$H,MATCH(G36,Rules!$E:$E,0)),"") -> Informazioni sul produttore e sul prodotto | K36: WallCovering | L36: Wandbelag | O36: Label to indicate the material or finish of the space cladding. The label is used for room book information and often displayed in room stamp.The material information is provided in absence of an Covering (type=CLADDING) object with own shape representation and material assignment. In case of inconsistency the material assigned to Covering elements takes precedence | P36: Kennzeichnung des Materials bzw. der Oberfläche der Wandbekleidung im Raum. Die Kennzeichnung wird für Raumbuchinformationen verwendet und häufig im Raumstempel angezeigt. Die Materialinformation wird bereitgestellt, sofern kein Covering-Objekt (Typ=CLADDING) mit eigener Geometrie und Materialzuweisung vorhanden ist. Bei Inkonsistenzen hat die Materialzuweisung der Covering-Elemente Vorrang. | S36: STRING | T36: IfcLabel | U36: Wall covering | W36: https://identifier.buildingsmart.org/uri/buildingsmart/ifc/4.3/prop/WallCovering | X36: Pset_SpaceCoveringRequirements | AA36: Preview | AB36: 2026-07-09T10:30+02:00 | AC36: IFMA
D37: https://identifier.buildingsmart.org/uri/buildingsmart/ifc/4.3/prop/CeilingCovering | F37: IFMA_P_31020036 | G37: Material and construction | H37: =IFERROR(INDEX(Rules!$F:$F,MATCH(G37,Rules!$E:$E,0)),"") -> Material und Aufbau | I37: =IFERROR(INDEX(Rules!$G:$G,MATCH(G37,Rules!$E:$E,0)),"") -> Matériau et constitution | J37: =IFERROR(INDEX(Rules!$H:$H,MATCH(G37,Rules!$E:$E,0)),"") -> Materiale e struttura | K37: CeilingCovering | L37: Deckenmaterial | O37: Label to indicate the material or finish of the space ceiling. The label is used for room book information and often displayed in room stamp.The material information is provided in absence of an Covering (type=[[CEILING]]) object with own shape representation and material assignment. In case of inconsistency the material assigned to Covering elements takes precedence. | P37: Kennzeichnung des Materials bzw. der Oberfläche der Raumdecke. Die Kennzeichnung wird für Raumbuchinformationen verwendet und häufig im Raumstempel angezeigt. Die Materialinformation wird bereitgestellt, sofern kein Covering-Objekt (Typ=CEILING) mit eigener Geometrie und Materialzuweisung vorhanden ist. Bei Inkonsistenzen hat die Materialzuweisung der Covering-Elemente Vorrang. | S37: STRING | T37: IfcLabel | U37: Ceiling covering | W37: https://identifier.buildingsmart.org/uri/buildingsmart/ifc/4.3/prop/CeilingCovering | X37: Pset_SpaceCoveringRequirements | AA37: Preview | AB37: 2026-07-09T10:30+02:00 | AC37: IFMA
D38: https://identifier.buildingsmart.org/uri/buildingsmart/ifc/4.3/prop/NaturalVentilation | F38: IFMA_P_31020037 | G38: Thermal characteristics | H38: =IFERROR(INDEX(Rules!$F:$F,MATCH(G38,Rules!$E:$E,0)),"") -> Thermische Kennwerte | I38: =IFERROR(INDEX(Rules!$G:$G,MATCH(G38,Rules!$E:$E,0)),"") -> Caractéristiques thermiques | J38: =IFERROR(INDEX(Rules!$H:$H,MATCH(G38,Rules!$E:$E,0)),"") -> Caratteristiche termiche | K38: NaturalVentilation | L38: Natürliche Belüftung | O38: Indication whether the space is required to have natural ventilation (TRUE), or not (FALSE). | P38: Angabe, ob für den Raum natürliche Lüftung erforderlich ist (TRUE) oder nicht (FALSE). | S38: BOOLEAN | T38: IfcBoolean | U38: Natural ventilation | W38: https://identifier.buildingsmart.org/uri/buildingsmart/ifc/4.3/prop/NaturalVentilation | AA38: Preview | AB38: 2026-07-09T10:30+02:00 | AC38: IFMA
D39: https://identifier.buildingsmart.org/uri/buildingsmart/ifc/4.3/prop/NaturalVentilationRate | F39: IFMA_P_31020038 | G39: Hydraulic / flow characteristics | H39: =IFERROR(INDEX(Rules!$F:$F,MATCH(G39,Rules!$E:$E,0)),"") -> Hydraulische / strömungstechnische Kennwerte | I39: =IFERROR(INDEX(Rules!$G:$G,MATCH(G39,Rules!$E:$E,0)),"") -> Caractéristiques hydrauliques / d’écoulement | J39: =IFERROR(INDEX(Rules!$H:$H,MATCH(G39,Rules!$E:$E,0)),"") -> Caratteristiche idrauliche / di flusso | K39: NaturalVentilationRate | L39: Natürliche Luftwechselrate | O39: Indication of the requirement of a particular natural air ventilation rate, given in air changes per hour. | P39: Angabe der erforderlichen natürlichen Luftwechselrate (in Luftwechseln pro Stunde). | S39: REAL | T39: IfcVolumetricFlowRateMeasure | U39: Natural ventilation rate | W39: https://identifier.buildingsmart.org/uri/buildingsmart/ifc/4.3/prop/NaturalVentilationRate | AA39: Preview | AB39: 2026-07-09T10:30+02:00 | AC39: IFMA
D40: https://identifier.buildingsmart.org/uri/buildingsmart/ifc/4.3/prop/MechanicalVentilation | F40: IFMA_P_31020039 | G40: Performance characteristics | H40: =IFERROR(INDEX(Rules!$F:$F,MATCH(G40,Rules!$E:$E,0)),"") -> Leistungs- und Funktionskennwerte | I40: =IFERROR(INDEX(Rules!$G:$G,MATCH(G40,Rules!$E:$E,0)),"") -> Caractéristiques de performance et de fonctionnement | J40: =IFERROR(INDEX(Rules!$H:$H,MATCH(G40,Rules!$E:$E,0)),"") -> Caratteristiche prestazionali e funzionali | K40: MechanicalVentilation | L40: Mechanische Belüftung | O40: Indication whether the space is required to have mechanical ventilation (TRUE), or not (FALSE). | P40: Angabe, ob für den Raum mechanische Lüftung erforderlich ist (TRUE) oder nicht (FALSE). | S40: BOOLEAN | T40: IfcBoolean | U40: Mechanical ventilation | W40: https://identifier.buildingsmart.org/uri/buildingsmart/ifc/4.3/prop/MechanicalVentilation | AA40: Preview | AB40: 2026-07-09T10:30+02:00 | AC40: IFMA
D41: https://identifier.buildingsmart.org/uri/buildingsmart/ifc/4.3/prop/MechanicalVentilationRate | F41: IFMA_P_31020040 | G41: Hydraulic / flow characteristics | H41: =IFERROR(INDEX(Rules!$F:$F,MATCH(G41,Rules!$E:$E,0)),"") -> Hydraulische / strömungstechnische Kennwerte | I41: =IFERROR(INDEX(Rules!$G:$G,MATCH(G41,Rules!$E:$E,0)),"") -> Caractéristiques hydrauliques / d’écoulement | J41: =IFERROR(INDEX(Rules!$H:$H,MATCH(G41,Rules!$E:$E,0)),"") -> Caratteristiche idrauliche / di flusso | K41: MechanicalVentilationRate | L41: Mechanische Luftwechselrate | O41: Indication of the requirement of a particular mechanical air ventilation rate, given in air changes per hour. | P41: Angabe der erforderlichen mechanischen Luftwechselrate (in Luftwechseln pro Stunde). | S41: REAL | T41: IfcVolumetricFlowRateMeasure | U41: Mechanical ventilation rate | W41: https://identifier.buildingsmart.org/uri/buildingsmart/ifc/4.3/prop/MechanicalVentilationRate | AA41: Preview | AB41: 2026-07-09T10:30+02:00 | AC41: IFMA
D42: https://identifier.buildingsmart.org/uri/buildingsmart/ifc/4.3/prop/AirConditioning | F42: IFMA_P_31020041 | G42: Thermal characteristics | H42: =IFERROR(INDEX(Rules!$F:$F,MATCH(G42,Rules!$E:$E,0)),"") -> Thermische Kennwerte | I42: =IFERROR(INDEX(Rules!$G:$G,MATCH(G42,Rules!$E:$E,0)),"") -> Caractéristiques thermiques | J42: =IFERROR(INDEX(Rules!$H:$H,MATCH(G42,Rules!$E:$E,0)),"") -> Caratteristiche termiche | K42: AirConditioning | L42: Klimatisiert | O42: Indication whether this space requires air conditioning provided (TRUE) or not (FALSE). | P42: Angabe, ob für diesen Raum eine Klimatisierung erforderlich ist (TRUE) oder nicht (FALSE). | S42: BOOLEAN | T42: IfcBoolean | U42: Air conditioning | W42: https://identifier.buildingsmart.org/uri/buildingsmart/ifc/4.3/prop/AirConditioning | AA42: Preview | AB42: 2026-07-09T10:30+02:00 | AC42: IFMA
D43: https://identifier.buildingsmart.org/uri/buildingsmart/ifc/4.3/prop/TemperatureSetPoint | F43: IFMA_P_31020042 | G43: Thermal characteristics | H43: =IFERROR(INDEX(Rules!$F:$F,MATCH(G43,Rules!$E:$E,0)),"") -> Thermische Kennwerte | I43: =IFERROR(INDEX(Rules!$G:$G,MATCH(G43,Rules!$E:$E,0)),"") -> Caractéristiques thermiques | J43: =IFERROR(INDEX(Rules!$H:$H,MATCH(G43,Rules!$E:$E,0)),"") -> Caratteristiche termiche | K43: TemperatureSetPoint | L43: Temperatur Ziel | O43: The temperature setpoint range and default setpoint. | P43: Temperatur-Sollwertbereich und Standard-Sollwert. | S43: REAL | T43: IfcThermodynamicTemperatureMeasure | U43: Temperature set point | W43: https://identifier.buildingsmart.org/uri/buildingsmart/ifc/4.3/prop/TemperatureSetPoint | AA43: Preview | AB43: 2026-07-09T10:30+02:00 | AC43: IFMA
D44: https://identifier.buildingsmart.org/uri/buildingsmart/ifc/4.3/prop/HumiditySetPoint | F44: IFMA_P_31020043 | G44: Thermal characteristics | H44: =IFERROR(INDEX(Rules!$F:$F,MATCH(G44,Rules!$E:$E,0)),"") -> Thermische Kennwerte | I44: =IFERROR(INDEX(Rules!$G:$G,MATCH(G44,Rules!$E:$E,0)),"") -> Caractéristiques thermiques | J44: =IFERROR(INDEX(Rules!$H:$H,MATCH(G44,Rules!$E:$E,0)),"") -> Caratteristiche termiche | K44: HumiditySetPoint | L44: Luftfeuchtigkeit Ziel | O44: Humidity of the space or zone that is required from user/designer view point. If no summer or winter space humidity requirements are given, it applies all year, otherwise for the intermediate period. Provide this property, if no humidity range (Min-Max) is available. | P44: Geforderte Luftfeuchtigkeit des Raums bzw. der Zone aus Sicht Nutzer/Planer. Falls keine sommer- oder winterbezogenen Anforderungen angegeben sind, gilt der Wert ganzjährig, ansonsten für die Übergangszeit. Diese Eigenschaft ist anzugeben, sofern kein Feuchtebereich (Min–Max) verfügbar ist. | S44: REAL | T44: IfcReal | U44: Humidity set point | W44: https://identifier.buildingsmart.org/uri/buildingsmart/ifc/4.3/prop/HumiditySetPoint | AA44: Preview | AB44: 2026-07-09T10:30+02:00 | AC44: IFMA
D45: https://identifier.buildingsmart.org/uri/buildingsmart/ifc/4.3/prop/FireExit | F45: IFMA_P_31020044 | G45: Safety and protection characteristics | H45: =IFERROR(INDEX(Rules!$F:$F,MATCH(G45,Rules!$E:$E,0)),"") -> Sicherheits- und Schutzmerkmale | I45: =IFERROR(INDEX(Rules!$G:$G,MATCH(G45,Rules!$E:$E,0)),"") -> Caractéristiques de sécurité et de protection | J45: =IFERROR(INDEX(Rules!$H:$H,MATCH(G45,Rules!$E:$E,0)),"") -> Caratteristiche di sicurezza e protezione | K45: FireExit | L45: Fluchtweg | O45: Indication whether this object is designed to serve as an exit in the case of fire (TRUE) or not (FALSE). | P45: Angabe, ob dieses Objekt im Brandfall als Ausgang dient (TRUE) oder nicht (FALSE). | S45: BOOLEAN | T45: IfcBoolean | U45: Fire exit | W45: https://identifier.buildingsmart.org/uri/buildingsmart/ifc/4.3/prop/FireExit | X45: Pset_SpaceFireSafetyRequirements | AA45: Preview | AB45: 2026-07-09T10:30+02:00 | AC45: IFMA
D46: https://identifier.buildingsmart.org/uri/buildingsmart/ifc/4.3/prop/GrossFloorArea | F46: IFMA_P_31020045 | G46: Geometric characteristics | H46: =IFERROR(INDEX(Rules!$F:$F,MATCH(G46,Rules!$E:$E,0)),"") -> Geometrische Eigenschaften | I46: =IFERROR(INDEX(Rules!$G:$G,MATCH(G46,Rules!$E:$E,0)),"") -> Caractéristiques géométriques | J46: =IFERROR(INDEX(Rules!$H:$H,MATCH(G46,Rules!$E:$E,0)),"") -> Caratteristiche geometriche | K46: GrossFloorArea | L46: Bruttofläche | O46: Sum of all gross floor areas within the spatial structure element | P46: Summe aller Bruttogrundflächen innerhalb des räumlichen Strukturelements. | S46: REAL | T46: IfcAreaMeasure | U46: Gross floor area | W46: https://identifier.buildingsmart.org/uri/buildingsmart/ifc/4.3/prop/GrossFloorArea | X46: Qto_SpaceBaseQuantities | AA46: Preview | AB46: 2026-07-09T10:30+02:00 | AC46: IFMA
D47: https://identifier.buildingsmart.org/uri/buildingsmart/ifc/4.3/prop/GrossVolume | F47: IFMA_P_31020046 | G47: Geometric characteristics | H47: =IFERROR(INDEX(Rules!$F:$F,MATCH(G47,Rules!$E:$E,0)),"") -> Geometrische Eigenschaften | I47: =IFERROR(INDEX(Rules!$G:$G,MATCH(G47,Rules!$E:$E,0)),"") -> Caractéristiques géométriques | J47: =IFERROR(INDEX(Rules!$H:$H,MATCH(G47,Rules!$E:$E,0)),"") -> Caratteristiche geometriche | K47: GrossVolume | L47: Bruttovolumen | O47: Total gross volume of the object. Openings, recesses, enclosed objects and projections are not taken into account. | P47: Gesamtes Bruttovolumen des Objekts. Öffnungen, Aussparungen, eingeschlossene Objekte und Vorsprünge werden nicht berücksichtigt. | S47: REAL | T47: IfcVolumeMeasure | U47: Gross volume | W47: https://identifier.buildingsmart.org/uri/buildingsmart/ifc/4.3/prop/GrossVolume | X47: Qto_SpaceBaseQuantities | AA47: Preview | AB47: 2026-07-09T10:30+02:00 | AC47: IFMA
D48: https://identifier.buildingsmart.org/uri/buildingsmart/ifc/4.3/prop/NetFloorArea | F48: IFMA_P_31020047 | G48: Geometric characteristics | H48: =IFERROR(INDEX(Rules!$F:$F,MATCH(G48,Rules!$E:$E,0)),"") -> Geometrische Eigenschaften | I48: =IFERROR(INDEX(Rules!$G:$G,MATCH(G48,Rules!$E:$E,0)),"") -> Caractéristiques géométriques | J48: =IFERROR(INDEX(Rules!$H:$H,MATCH(G48,Rules!$E:$E,0)),"") -> Caratteristiche geometriche | K48: NetFloorArea | L48: Nettofläche | O48: Sum of all net usable floor areas. | P48: Summe aller Nettogrundflächen. | S48: REAL | T48: IfcAreaMeasure | U48: Net floor area | W48: https://identifier.buildingsmart.org/uri/buildingsmart/ifc/4.3/prop/NetFloorArea | X48: Qto_SpaceBaseQuantities | AA48: Preview | AB48: 2026-07-09T10:30+02:00 | AC48: IFMA
D49: https://identifier.buildingsmart.org/uri/buildingsmart/ifc/4.3/prop/NetVolume | F49: IFMA_P_31020048 | G49: Geometric characteristics | H49: =IFERROR(INDEX(Rules!$F:$F,MATCH(G49,Rules!$E:$E,0)),"") -> Geometrische Eigenschaften | I49: =IFERROR(INDEX(Rules!$G:$G,MATCH(G49,Rules!$E:$E,0)),"") -> Caractéristiques géométriques | J49: =IFERROR(INDEX(Rules!$H:$H,MATCH(G49,Rules!$E:$E,0)),"") -> Caratteristiche geometriche | K49: NetVolume | L49: Nettovolumen | O49: Total net volume of the object, taking into account possible processing features (cut-out's, etc.) or openings and recesses. | P49: Gesamtes Nettovolumen des Objekts unter Berücksichtigung von Bearbeitungen (z. B. Ausschnitte) sowie Öffnungen und Aussparungen. | S49: REAL | T49: IfcVolumeMeasure | U49: Net volume | W49: https://identifier.buildingsmart.org/uri/buildingsmart/ifc/4.3/prop/NetVolume | X49: Qto_SpaceBaseQuantities | AA49: Preview | AB49: 2026-07-09T10:30+02:00 | AC49: IFMA
F50: IFMA_P_31020049 | G50: Geometric characteristics | H50: =IFERROR(INDEX(Rules!$F:$F,MATCH(G50,Rules!$E:$E,0)),"") -> Geometrische Eigenschaften | I50: =IFERROR(INDEX(Rules!$G:$G,MATCH(G50,Rules!$E:$E,0)),"") -> Caractéristiques géométriques | J50: =IFERROR(INDEX(Rules!$H:$H,MATCH(G50,Rules!$E:$E,0)),"") -> Caratteristiche geometriche | K50: NetWallArea | L50: Wandfläche netto | O50: Sum of all wall (and other vertically bounding elements, like columns) areas bounded by the space. It excludes the area covered by elements inside the wall area (doors, windows, other openings, etc.). | P50: Summe aller Wandflächen (und anderer vertikal begrenzender Elemente wie Stützen), die den Raum begrenzen. Flächenanteile von Einbauten innerhalb der Wand (Türen, Fenster, Öffnungen usw.) werden nicht berücksichtigt. | S50: REAL | T50: IfcAreaMeasure | U50: Net wall area | X50: Qto_SpaceBaseQuantities | AA50: Preview | AB50: 2026-07-09T10:30+02:00 | AC50: IFMA
D51: https://identifier.buildingsmart.org/uri/buildingsmart/ifc/4.3/prop/Height | F51: IFMA_P_31020050 | G51: Geometric characteristics | H51: =IFERROR(INDEX(Rules!$F:$F,MATCH(G51,Rules!$E:$E,0)),"") -> Geometrische Eigenschaften | I51: =IFERROR(INDEX(Rules!$G:$G,MATCH(G51,Rules!$E:$E,0)),"") -> Caractéristiques géométriques | J51: =IFERROR(INDEX(Rules!$H:$H,MATCH(G51,Rules!$E:$E,0)),"") -> Caratteristiche geometriche | K51: Height | L51: Höhe | O51: Vertical extent or height of the element or space. | P51: Vertikale Ausdehnung bzw. Höhe des Elements oder Raums. | S51: REAL | T51: IfcLengthMeasure | U51: Height | W51: https://identifier.buildingsmart.org/uri/buildingsmart/ifc/4.3/prop/Height | X51: Qto_SpaceBaseQuantities | AA51: Preview | AB51: 2026-07-09T10:30+02:00 | AC51: IFMA
F52: IFMA_P_31020051 | G52: Identification and classification | H52: =IFERROR(INDEX(Rules!$F:$F,MATCH(G52,Rules!$E:$E,0)),"") -> Identifikation und Klassifikation | I52: =IFERROR(INDEX(Rules!$G:$G,MATCH(G52,Rules!$E:$E,0)),"") -> Identification et classification | J52: =IFERROR(INDEX(Rules!$H:$H,MATCH(G52,Rules!$E:$E,0)),"") -> Identificazione e classificazione | K52: AboveGround | L52: Oberirdisch | O52: Indication whether this building storey is fully above ground (TRUE), or below ground (FALSE), or partially above and below ground (UNKNOWN) - as in sloped terrain. | P52: Angabe, ob sich dieses Stockwerk vollständig über der Erde (TRUE), unter der Erde (FALSE) oder teilweise über und unter der Erde (UNKNOWN) befindet – beispielsweise bei abschüssigem Gelände. | S52: BOOLEAN | T52: IfcBoolean | AA52: Preview | AB52: 2026-07-09T10:30+02:00 | AC52: IFMA
F53: IFMA_P_31020052 | G53: Identification and classification | H53: =IFERROR(INDEX(Rules!$F:$F,MATCH(G53,Rules!$E:$E,0)),"") -> Identifikation und Klassifikation | I53: =IFERROR(INDEX(Rules!$G:$G,MATCH(G53,Rules!$E:$E,0)),"") -> Identification et classification | J53: =IFERROR(INDEX(Rules!$H:$H,MATCH(G53,Rules!$E:$E,0)),"") -> Identificazione e classificazione | K53: CostZone | L53: Kostenzone | O53: Cost zone: for cost allocation according to commercial use, investor and/or sales product (business line) | P53: Kostenzone: für die Kostenaufteilung nach kommerzieller Nutzung bzw. Investor und/oder Verkaufsprodukt (Business Line) | S53: STRING | T53: IfcLabel | AA53: Preview | AB53: 2026-07-09T10:30+02:00 | AC53: IFMA

Sheet Values
A1: Filter | B1: Hinweise zur Handhabung | C1: Enumerations | D1: GUID/URI | E1: Enumeration-ID | F1: Enumeration-Code | G1: Designation (EN) | H1: Bezeichnung (DE) | I1: Désignation (FR) | J1: Designazione (IT) | K1: Enumeration (EN) | L1: Werteliste (DE) | M1: Liste de valeurs (FR) | N1: Lista valori (IT) | O1: Units/Einheit/Unité/Unità | P1: Governance | Q1: Status | R1: Version date | S1: Provenance (PROV) | U1: User Defined (not part of HE Data Dictionary / not validated by Validator)
B2: Erforderlich für Excel | D2: no | E2: no | F2: yes | G2: yes | H2: yes | I2: optional | J2: optional | K2: yes | L2: yes | M2: optional | N2: optional | O2: yes | Q2: yes | R2: yes | S2: yes
B3: Sprachen | D3: neutral | E3: EN | F3: neutral | G3: EN | H3: DE | I3: FR | J3: IT | K3: EN | L3: DE | M3: FR | N3: IT | O3: multilingual | Q3: EN | R3: neutral | S3: EN
B4: Referenziert / System generiert | D4: system-generated | E4: system-generated | Q4: referenced | R4: referenced | S4: referenced
B5: Dropdown Liste | Q5: Rules.Status
B6: Validierung | D6: not validated. Info: If available system-generated URI / user defined backend reference | E6: system-generated from Designation (EN) | F6: user defined | G6: user defined | H6: user defined | I6: user defined | J6: user defined | K6: must use JSON-style list syntax, e.g. ["A", "B", "C"] or ["A", 1.5, "C"] for alphanumeric/numeric values | L6: must use JSON-style list syntax, e.g. ["A", "B", "C"] or ["A", 1.5, "C"] for alphanumeric/numeric values | M6: must use JSON-style list syntax, e.g. ["A", "B", "C"] or ["A", 1.5, "C"] for alphanumeric/numeric values | N6: must use JSON-style list syntax, e.g. ["A", "B", "C"] or ["A", 1.5, "C"] for alphanumeric/numeric values | O6: user defined | Q6: must match Rules.Status | R6: date format 2026-06-18T15:30+02:00 | S6: user defined
F7: IFMA_V_31030000 | G7: PredefinedType | H7: Vordefinierter Typ | K7: ["GFA", "PARKING", "USERDEFINED"] | L7: ["GFA", "PARKING", "USERDEFINED"] | M7: ["GFA", "PARKING", "USERDEFINED"] | Q7: Preview | R7: 2026-07-09T10:30+02:00 | S7: IFMA
F8: IFMA_V_31030001 | G8: ObjectType | H8: Objekttyp | K8: ["SITE_AREA", "LANDSCAPE_AREA", "ROOM,EXTERNAL_ROOM", "RENTABLE_AREA"] | L8: ["SITE_AREA", "LANDSCAPE_AREA", "ROOM,EXTERNAL_ROOM", "RENTABLE_AREA"] | M8: ["SITE_AREA", "LANDSCAPE_AREA", "ROOM,EXTERNAL_ROOM", "RENTABLE_AREA"] | Q8: Preview | R8: 2026-07-09T10:30+02:00 | S8: IFMA
F9: IFMA_V_31030002 | G9: ID | H9: ID | Q9: Preview | R9: 2026-07-09T10:30+02:00 | S9: IFMA
F10: IFMA_V_31030003 | G10: Room designation | H10: Raumbezeichnung | Q10: Preview | R10: 2026-07-09T10:30+02:00 | S10: IFMA
F11: IFMA_V_31030004 | G11: Area type SIA 416 code | H11: Flächenart SIA 416 Code | K11: ["1.2", "1.2.1", "1.2.2", 2, "2.1.1.1", "2.1.1.2", "2.1.2", "2.1.3", 3, "3.1.1", "3.1.2", "3.1.3", "AIRSPACE", "ROOF"] | L11: ["1_GSF", "1.1_GGF", "1.2_UF", "1.2.1_BUF", "1.2.2_UUF", "2_GF", "2.1.1.1_HNF", "2.1.1.2_NNF", "2.1.2_VF", "2.1.3_FF", "3_AGF", "3.1_ANGF", "3.1.1_ANF", "3.1.2_AVF", "3.1.3_AFF", "5_GV", "AIRSPACE_LUFTRAUM", "ROOF_DACH"] | M11: ["1_ST", "1.1_SB", "1.2_SA", "1.2.1_SAA", "1.2.2_SAN", "2_SP", "2.1.1.1_SUP", "2.1.1.2_SUS", "2.1.2_SD", "2.1.3_SI", "3_SEP", "3.1_SEN", "3.1.1_SEU", "3.1.2_SED", "3.1.3_SEI", "5_VB", "AIRSPACE_VIDE", "ROOF_TOIT"] | Q11: Preview | R11: 2026-07-09T10:30+02:00 | S11: IFMA
F12: IFMA_V_31030007 | G12: Room designation SIA 380 label | H12: Raumbezeichnung SIA 380 Bezeichnung | K12: ["1", "2", "3", "4", "5", "6", "1", "8", "9", "10"] | L12: ["HNF1", "HNF2", "HNF3", "HNF4", "HNF5", "HNF6", "NNF7", "FF8", "VF9", "BUF10"] | M12: ["SUP1", "SUP2", "SUP3", "SUP4", "SUP5", "SUP6", "SUS7", "SI8", "SD9", "SAA10"] | Q12: Preview | R12: 2026-07-09T10:30+02:00 | S12: IFMA
F13: IFMA_V_31030008 | G13: Room usage SIA 2024 code | H13: Raumnutzung SIA 2024 Code | K13: [1.01, 1.02, 2.01, 2.02, 3.01, 3.02, 3.03, 3.04, 4.01, 4.02, 4.03, 4.04, 4.05, 5.01, 5.02, 5.03, 6.01, 6.02, 6.03, 6.04, 7.01, 7.02, 7.03, 8.01, 8.02, 8.03, 9.01, 9.02, 9.03, 10.01, 11.01, 11.02, 11.03, 12.01, 12.02, 12.03, 12.04, 12.05, 12.06, 12.07, 12.08, 12.09, 12.1, 12.11, 12.12] | L13: ["1.01_Wohnen Mehrfamilienhaus", "1.02_Wohnen Einfamilienhaus", "2.01_Hotelzimmer", "2.02_Empfang oder Lobby", "3.01_Einzel- oder Gruppenbüro", "3.02_Grossraumbüro", "3.03_Sitzungszimmer", "3.04_Schalterhalle oder Empfang", "4.01_Schulzimmer", "4.02_Lehrerzimmer", "4.03_Bibliothek", "4.04_Hörsaal", "4.05_Schulfachraum", "5.01_Lebensmittelverkauf", "5.02_Fachgeschäft", "5.03_Verkauf Möbel-Bau-Garten", "6.01_Restaurant", "6.02_Selbstbedienungsrestaurant", "6.03_Küche zu Restaurant", "6.04_Küche zu Selbstbedienungsrestaurant", "7.01_Vorstellungsraum", "7.02_Mehrzweckhalle", "7.03_Ausstellungshalle", "8.01_Bettenzimmer", "8.02_Stationszimmer", "8.03_Behandlungsraum", "9.01_Produktion (grobe Arbeit)", "9.02_Produktion (feine Arbeit)", "9.03_Laborraum", "10.01_Lagerhalle", "11.01_Turnhalle", "11.02_Fitnessraum", "11.03_Schwimmhalle", "12.01_Verkehrsfläche", "12.02_Verkehrsfläche 24 h", "12.03_Treppenhaus", "12.04_Nebenraum", "12.05_Küche oder Teeküche", "12.06_WC-Bad-Dusche zu Hotel oder Spital", "12.07_WC alle Nutzungen", "12.08_Garderobe oder Dusche", "12.09_Parkhaus", "12.10_Wasch- oder Trockenraum", "12.11_Kühlraum", "12.12_Serverraum"] | Q13: Preview | R13: 2026-07-09T10:30+02:00 | S13: IFMA
F14: IFMA_V_31030010 | G14: Area type d0165 code | H14: Flächenart d0165 Code | K14: [1.1, 1.2, 1.3, 1.4, 1.5, 1.6, 2.1, 2.2, 2.3, 2.4, 2.5, 2.6, 2.7, 2.8, 3.1, 3.2, 3.3, 3.4, 3.5, 3.6, 3.7, 3.8, 3.9, 4.1, 4.2, 4.3, 4.4, 4.5, 4.6, 5.1, 5.2, 5.3, 5.4, 5.5, 5.6, 5.7, 5.8, 5.9, 6.1, 6.2, 6.3, 6.4, 6.5, 6.6, 6.7, 6.8, 7.1, 7.2, 7.3, 7.4, 7.5, 7.6, 7.7, 8.1, 8.2, 8.3, 8.4, 8.5, 8.6, 8.7, 8.8, 8.9, 9.1, 9.2, 9.3, 9.4, 10.1] | L14: ["1.1_Wohnräume", "1.2_Gemeinschaftsräume", "1.3_Pausenräume", "1.4_Warteräume", "1.5_Speiseräume", "1.6_Hafträume", "2.1_Büroräume", "2.2_Grossraumbüros", "2.3_Besprechungsräume", "2.4_Konstruktionsräume", "2.5_Schalterräume", "2.6_Bedienungsräume", "2.7_Aufsichtsräume", "2.8_Bürotechnikräume", "3.1_Werkhallen", "3.2_Werkstätten", "3.3_Technologische Labors", "3.4_Physikalische/physikaltechnische/elektrotechnische Labors", "3.5_Chemische/bakteriologische/morphologische Labors", "3.6_Räume für Tierhaltung", "3.7_Räume für Pflanzenzucht", "3.8_Küchen", "3.9_Sonderarbeitsräume", "4.1_Lagerräume", "4.2_Archive/Sammlungsräume", "4.3_Kühlräume", "4.4_Annahme- und Ausgaberäume", "4.5_Verkaufsräume", "4.6_Ausstellungsräume", "5.1_Unterrichtsräume mit festem Gestühl", "5.2_Allgemein Unterrichts- und Übungsräume ohne festes Gestühl", "5.3_Besondere Unterrichts- und Übungsräume ohne festes Gestühl", "5.4_Bibliotheksräume", "5.5_Sporträume", "5.6_Versammlungsräume", "5.7_Bühnen-/Studioräume", "5.8_Schauräume", "5.9_Sakralräume", "6.1_Räume mit allgemeiner medizinischen Ausstattung", "6.2_Räume mit besonderer medizinischen Ausstattung", "6.3_Räume für operative Eingriffe/Endoskopien/Entbindungen", "6.4_Räume für Strahlendiagnostik", "6.5_Räume für Strahlentherapie", "6.6_Räume für Physiotherapie und Rehabilitation", "6.7_Bettenräume mit allgemeiner Ausstattung", "6.8_Bettenräume mit besonderer Ausstattung", "7.1_Sanitärräume", "7.2_Garderoben", "7.3_Abstellräume", "7.4_Fahrzeugabstellflächen", "7.5_Fahrgastflächen", "7.6_Räume für zentrale Technik", "7.7_Schutzräum", "8.1_Abwasseraufbereitung u. -beseitigung", "8.2_Wasserversorgung", "8.3_Heizung und Brauchwassererwärmung", "8.4_Gase und Flüssigkeiten", "8.5_Elektrische Stromversorgung", "8.6_Fernmeldetechnik", "8.7_Raumlufttechnische Anlagen", "8.8_Aufzugs- und Förderanlagen", "8.9_Sonstige betriebstechnische Anlagen", "9.1_Flure/Hallen", "9.2_Treppen", "9.3_Schächte für Förderanlagen", "9.4_Fahrzeugsverkehrsflächen", "10.1_aussenliegende Fahrzeugabstellflächen"] | Q14: Preview | R14: 2026-07-09T10:30+02:00 | S14: IFMA
F15: IFMA_V_31030012 | G15: Program use | H15: Raumnutzung | Q15: Preview | R15: 2026-07-09T10:30+02:00 | S15: IFMA
F16: IFMA_V_31030013 | G16: Room type | H16: Raumtyp | Q16: Preview | R16: 2026-07-09T10:30+02:00 | S16: IFMA
F17: IFMA_V_31030014 | G17: Unit type | H17: Einheitstyp | Q17: Preview | R17: 2026-07-09T10:30+02:00 | S17: IFMA
F18: IFMA_V_31030015 | G18: Unit ID | H18: Einheitsnummer | Q18: Preview | R18: 2026-07-09T10:30+02:00 | S18: IFMA
F19: IFMA_V_31030016 | G19: Operational room number | H19: Raumnummer Betrieb | Q19: Preview | R19: 2026-07-09T10:30+02:00 | S19: IFMA
F20: IFMA_V_31030017 | G20: Room signal label | H20: Raumbeschriftung | Q20: Preview | R20: 2026-07-09T10:30+02:00 | S20: IFMA
F21: IFMA_V_31030018 | G21: Cleaning group | H21: Reinigungsgruppe | Q21: Preview | R21: 2026-07-09T10:30+02:00 | S21: IFMA
F22: IFMA_V_31030019 | G22: Area load | H22: Flächenlast | Q22: Preview | R22: 2026-07-09T10:30+02:00 | S22: IFMA
F23: IFMA_V_31030020 | G23: Point load | H23: Punktlast | Q23: Preview | R23: 2026-07-09T10:30+02:00 | S23: IFMA
F24: IFMA_V_31030021 | G24: Energy reference area | H24: Energiebezugsfläche | K24: ["true", "false"] | L24: ["true", "false"] | M24: ["true", "false"] | Q24: Preview | R24: 2026-07-09T10:30+02:00 | S24: IFMA
F25: IFMA_V_31030022 | G25: Window area | H25: Fensterfläche | Q25: Preview | R25: 2026-07-09T10:30+02:00 | S25: IFMA
F26: IFMA_V_31030023 | G26: Window openable | H26: Fenster öffenbar | K26: ["true", "false"] | L26: ["true", "false"] | M26: ["true", "false"] | Q26: Preview | R26: 2026-07-09T10:30+02:00 | S26: IFMA
F27: IFMA_V_31030024 | G27: Occupant | H27: Raumnutzer | Q27: Preview | R27: 2026-07-09T10:30+02:00 | S27: IFMA
F28: IFMA_V_31030025 | G28: Solar shading | H28: Sonnenschutz | K28: ["true", "false"] | L28: ["true", "false"] | M28: ["true", "false"] | Q28: Preview | R28: 2026-07-09T10:30+02:00 | S28: IFMA
F29: IFMA_V_31030026 | G29: Humidified | H29: Befeuchtet | K29: ["true", "false"] | L29: ["true", "false"] | M29: ["true", "false"] | Q29: Preview | R29: 2026-07-09T10:30+02:00 | S29: IFMA
F30: IFMA_V_31030027 | G30: Dehumidified | H30: Entfeuchtet | K30: ["true", "false"] | L30: ["true", "false"] | M30: ["true", "false"] | Q30: Preview | R30: 2026-07-09T10:30+02:00 | S30: IFMA
F31: IFMA_V_31030028 | G31: Rentable | H31: Vermietbarkeit | K31: ["true", "false"] | L31: ["true", "false"] | M31: ["true", "false"] | Q31: Preview | R31: 2026-07-09T10:30+02:00 | S31: IFMA
F32: IFMA_V_31030029 | G32: External space | H32: Aussenraum | K32: ["true", "false"] | L32: ["true", "false"] | M32: ["true", "false"] | Q32: Preview | R32: 2026-07-09T10:30+02:00 | S32: IFMA
F33: IFMA_V_31030030 | G33: Occupancy type | H33: Nutzungsart | Q33: Preview | R33: 2026-07-09T10:30+02:00 | S33: IFMA
F34: IFMA_V_31030031 | G34: Headroom | H34: Raumnutzhöhe | Q34: Preview | R34: 2026-07-09T10:30+02:00 | S34: IFMA
F35: IFMA_V_31030032 | G35: Planned occupancy | H35: Personenbelegung geplant | Q35: Preview | R35: 2026-07-09T10:30+02:00 | S35: IFMA
F36: IFMA_V_31030033 | G36: Actual occupancy | H36: Personenbelegung ist | Q36: Preview | R36: 2026-07-09T10:30+02:00 | S36: IFMA
F37: IFMA_V_31030034 | G37: Floor covering | H37: Bodenbelag | Q37: Preview | R37: 2026-07-09T10:30+02:00 | S37: IFMA
F38: IFMA_V_31030035 | G38: Wall covering | H38: Wandbelag | Q38: Preview | R38: 2026-07-09T10:30+02:00 | S38: IFMA
F39: IFMA_V_31030036 | G39: Ceiling covering | H39: Deckenmaterial | Q39: Preview | R39: 2026-07-09T10:30+02:00 | S39: IFMA
F40: IFMA_V_31030037 | G40: Natural ventilation | H40: Natürliche Belüftung | K40: ["true", "false"] | L40: ["true", "false"] | M40: ["true", "false"] | Q40: Preview | R40: 2026-07-09T10:30+02:00 | S40: IFMA
F41: IFMA_V_31030038 | G41: Natural ventilation rate | H41: Natürliche Lüftung | Q41: Preview | R41: 2026-07-09T10:30+02:00 | S41: IFMA
F42: IFMA_V_31030039 | G42: Mechanical ventilation | H42: Mechanische Belüftung | K42: ["true", "false"] | L42: ["true", "false"] | M42: ["true", "false"] | Q42: Preview | R42: 2026-07-09T10:30+02:00 | S42: IFMA
F43: IFMA_V_31030040 | G43: Mechanical ventilation rate | H43: Mechanische Lüftung | Q43: Preview | R43: 2026-07-09T10:30+02:00 | S43: IFMA
F44: IFMA_V_31030041 | G44: Air conditioning | H44: Klimatisiert | K44: ["true", "false"] | L44: ["true", "false"] | M44: ["true", "false"] | Q44: Preview | R44: 2026-07-09T10:30+02:00 | S44: IFMA
F45: IFMA_V_31030042 | G45: Temperature set point | H45: Temperatur Ziel | Q45: Preview | R45: 2026-07-09T10:30+02:00 | S45: IFMA
F46: IFMA_V_31030043 | G46: Humidity set point | H46: Luftfeuchtigkeit Ziel | Q46: Preview | R46: 2026-07-09T10:30+02:00 | S46: IFMA
F47: IFMA_V_31030044 | G47: Fire exit | H47: Fluchtweg | K47: ["true", "false"] | L47: ["true", "false"] | M47: ["true", "false"] | Q47: Preview | R47: 2026-07-09T10:30+02:00 | S47: IFMA
F48: IFMA_V_31030045 | G48: Gross floor area | H48: Bruttofläche | Q48: Preview | R48: 2026-07-09T10:30+02:00 | S48: IFMA
F49: IFMA_V_31030046 | G49: Gross volume | H49: Bruttovolumen | Q49: Preview | R49: 2026-07-09T10:30+02:00 | S49: IFMA
F50: IFMA_V_31030047 | G50: Net floor area | H50: Nettofläche | Q50: Preview | R50: 2026-07-09T10:30+02:00 | S50: IFMA
F51: IFMA_V_31030048 | G51: Net volume | H51: Nettovolumen | Q51: Preview | R51: 2026-07-09T10:30+02:00 | S51: IFMA
F52: IFMA_V_31030049 | G52: Net wall area | H52: Wandfläche netto | Q52: Preview | R52: 2026-07-09T10:30+02:00 | S52: IFMA
F53: IFMA_V_31030050 | G53: Height | H53: Höhe | Q53: Preview | R53: 2026-07-09T10:30+02:00 | S53: IFMA

Sheet Documents
A1: Filter | B1: Hinweise zur Handhabung | C1: Documents | D1: GUID/URI | E1: Document-ID | F1: Document-Code | G1: DocumentName (EN) | H1: Bezeichnung (DE) | I1: Désignation (FR) | J1: Designazione (IT) | K1: Security level/Sicherheitsstufe/Niveau de sécurité/Livello di sicurezza | L1: Accessibility/Zugänglichkeit/Accessibilité/Accessibilità | M1: Revision | N1: DocumentOwner | O1: Governance | P1: Status | Q1: Version date | R1: Provenance (PROV) | T1: User Defined (not part of HE Data Dictionary / not validated by Validator)
B2: Erforderlich für Excel | D2: no | E2: no | F2: optional | G2: optional | H2: optional | I2: optional | J2: optional | K2: optional | L2: optional | M2: optional | N2: optional | P2: optional | Q2: optional | R2: optional
B3: Sprachen | D3: multilingual | E3: multilingual | F3: multilingual | G3: EN | H3: DE | I3: FR | J3: IT | K3: multilingual | L3: multilingual | M3: multilingual | N3: multilingual | P3: EN | Q3: neutral | R3: EN
B4: Referenziert / System generiert | E4: system-generated | G4: referenced | M4: referenced | N4: referenced | P4: referenced | Q4: referenced | R4: referenced
B5: Dropdown Liste | K5: Rules.ISG - Informationssicherheitsgesetz | L5: Rules.FAIR Prinzipien | P5: Rules.Status
B6: Validierung | D6: not validated. Info: If available system-generated URI / user defined backend reference | E6: system-generated from DocumentName (EN) | F6: user defined | G6: user defined | H6: user defined | I6: user defined | J6: user defined | K6: must match Rules.ISG - Informationssicherheitsgesetz | L6: must match Rules.FAIR Prinzipien | M6: user defined | N6: user defined | P6: must match Rules.Status | Q6: date format 2026-06-18T15:30+02:00 | R6: user defined
F7: IFMA_D_31040000 | G7: SN 504 416 - Areas and volumes of buildings | H7: SN 504 416 -Flächen und Volumen von Gebäuden | K7: nicht klassifiziert | L7: Zugänglich kostenpflichtig | M7: 2003 | N7: SIA | P7: Preview | Q7: 2026-07-09T10:30+02:00 | R7: IFMA

Sheet GroupOfProperties
A1: Filter | B1: Hinweise zur Handhabung | C1: Group of Properties | D1: GoP-ID | E1: GoP-Code | F1: Designation (EN) | G1: Description (EN) | H1: Beschreibung (DE) | I1: Description (FR) | J1: Descrizione (IT) | K1: Governance | L1: Status | M1: Version date | N1: Provenance (PROV) | P1: User Defined (not part of HE Data Dictionary / not validated by Validator)
B2: Erforderlich für Excel | D2: no | E2: no | F2: yes | G2: yes | H2: yes | I2: optional | J2: optional | L2: yes | M2: yes | N2: yes
B3: Sprachen | D3: EN | E3: neutral | F3: EN | G3: EN | H3: DE | I3: FR | J3: IT | L3: multilingual | M3: multilingual | N3: multilingual
B4: Referenziert / System generiert | D4: system-generated | L4: referenced | M4: referenced | N4: referenced
B5: Dropdown Liste | L5: Rules.Status
B6: Validierung | D6: system-generated from Designation (EN) | E6: user defined | F6: must start with <OrganizationCode>_; forbidden prefixes: Pset_, IFC_, CH_ | G6: user defined | H6: user defined | I6: user defined | J6: user defined | L6: must match Rules.Status | M6: date format 2026-06-18T15:30+02:00 | N6: user defined
F7: IFMA_AreaMgmt | G7: Includes all area-related parameters in accordance with the SIA 416 standard. It defines primary, secondary and circulation areas to enable precise control of facility management. | H7: Enthält alle flächenbezogenen Parameter gemäss Norm SIA 416. Sie definiert Hauptnutz-, Nebennutz- und Verkehrsflächen zur präzisen Steuerung beim Facility Management | L7: Preview | M7: 2026-07-09T10:30+02:00 | N7: IFMA

Sheet Data_Template
C1: GoP | E1: Properties | BC1: Documents
C2: GoP - Designation/Bezeichnung/Désignation/Designazione | E2: Property - Designation/Bezeichnung/Désignation/Designazione | F2: {=TRANSPOSE(Properties!K7:K53)} -> Name | G2: LongName | H2: SIA_416_2003 | I2: SIA_380_2015 | J2: SIA_2024_2021 | K2: SIA_d0615_2000 | L2: ProgramUse | M2: RoomType | N2: UnitType | O2: Unit_ID | P2: RoomNumberFM | Q2: RoomSignalLabel | R2: CleaningGroup | S2: AreaLoad | T2: PointLoad | U2: EnergyReferenceArea | V2: WindowsCleaningArea | W2: WindowsOpenable | X2: Occupant | Y2: Shading | Z2: IsHumidified | AA2: IsDehumidified | AB2: IsRentable | AC2: IsExternal | AD2: OccupancyType | AE2: MinimumHeadroom | AF2: OccupancyNumberPeak | AG2: OccupancyNumber | AH2: FloorCovering | AI2: WallCovering | AJ2: CeilingCovering | AK2: NaturalVentilation | AL2: NaturalVentilationRate | AM2: MechanicalVentilation | AN2: MechanicalVentilationRate | AO2: AirConditioning | AP2: TemperatureSetPoint | AQ2: HumiditySetPoint | AR2: FireExit | AS2: GrossFloorArea | AT2: GrossVolume | AU2: NetFloorArea | AV2: NetVolume | AW2: NetWallArea | AX2: Height | AY2: AboveGround | AZ2: CostZone | BC2: Document - Designation/Bezeichnung/Désignation/Designazione
A3: Classes
A4: Class - Designation/Bezeichnung/Désignation/Designazione
A5: =Classes!P7 -> Geschossebene | C5: IFMA_AreaMgmt | F5: x | G5: x
A6: =Classes!P8 -> Grundstückfläche | C6: IFMA_AreaMgmt | H6: [1] | AC6: ["true"] | AS6: x
A7: =Classes!P9 -> Umgebungsfläche | C7: IFMA_AreaMgmt | G7: x | H7: [1.2, "1.2.1", "1.2.2"] | L7: x | M7: x | O7: x | X7: x | AC7: ["true"] | AH7: x | AS7: x | AZ7: x
A8: =Classes!P10 -> Geschossvolumen | C8: IFMA_AreaMgmt | H8: [2, 3, "AIRSPACE", "ROOF"] | L8: x | X8: x | AC8: x | AS8: x | AT8: x | AX8: x | AY8: x | AZ8: x
A9: =Classes!P11 -> Nettogeschossfläche | C9: IFMA_AreaMgmt | F9: x | G9: x | H9: ["2.1.1.1", "2.1.1.2", "2.1.2", "2.1.3"] | I9: ["HNF1", "HNF2", "HNF3", "HNF4", "HNF5", "HNF6", "NNF7", "FF8", "VF9", "BUF10", "SUP1", "SUP2", "SUP3", "SUP4", "SUP5", "SUP6", "SUS7", "SI8", "SD9", "SAA10"] | J9: x | K9: x | L9: x | M9: x | O9: x | P9: x | Q9: x | R9: x | S9: x | T9: x | U9: x | V9: x | W9: x | X9: x | Y9: x | Z9: x | AA9: x | AB9: x | AC9: "false" | AD9: x | AE9: x | AF9: x | AG9: x | AH9: x | AI9: x | AJ9: x | AK9: x | AL9: x | AM9: x | AN9: x | AO9: x | AP9: x | AQ9: x | AR9: x | AU9: x | AV9: x | AW9: x | AX9: x | AY9: x | AZ9: x
A10: =Classes!P12 -> Aussen-Nettogeschossfläche | C10: IFMA_AreaMgmt | F10: x | G10: x | H10: ["3.1.1", "3.1.2", "3.1.3"] | L10: x | M10: x | O10: x | X10: x | AC10: ["true"] | AD10: x | AF10: x | AG10: x | AH10: x | AU10: x | AY10: x | AZ10: x
A11: =Classes!P13 -> Stellplatz | C11: IFMA_AreaMgmt | F11: x | G11: x | K11: x | L11: x | X11: x | AC11: x | AD11: x | AU11: x
A12: =Classes!P14 -> Vermietbare Fläche | C12: IFMA_AreaMgmt | F12: x | G12: x | L12: x | N12: x | O12: x | X12: x | AB12: x | AF12: x | AG12: x | AS12: x | AU12: x

Sheet Gelöschte Bauteile
B1: D | C1: 05 | D1: . | E1: 01 | F1: . | G1: 004 | H1: . | I1: nnn | L1: Schalldämpfer | N1: 242.2 | O1: - | P1: - | Q1: - | R1: x | U1: x | V1: Rohrzubehör | Y1: Apparat HLKS | Z1: IfcDuctSilencerType | AA1: ROUND/RECTANGULAR | AD1: 200 | AE1: 200 | AF1: 300 | AG1: 300 | AH1: 300 | AI1: 300 | AV1: x | BE1: =IF(COUNTIF(AJ1:BD1,"x")>0,"x","") -> x
B2: D | C2: 05 | D2: . | E2: 01 | F2: . | G2: 004 | H2: . | I2: nnn | L2: Dacheinfassung | N2: 242.2 | O2: - | P2: - | Q2: - | R2: x | U2: x | V2: Rohrzubehör | Y2: Installationszubehör | Z2: IfcCoveringType | AA2: ROOFING | AD2: 200 | AE2: 200 | AF2: 300 | AG2: 300 | AH2: 300 | AI2: 300 | AV2: x | BE2: =IF(COUNTIF(AJ2:BD2,"x")>0,"x","") -> x
B3: D | C3: 05 | D3: . | E3: 01 | F3: . | G3: 004 | H3: . | I3: nnn | L3: Revisionsstück | N3: 242.2 | O3: - | P3: - | Q3: - | R3: x | U3: x | V3: Rohrformteile | Z3: IfcPipeSegmentType | AA3: SPOOL | AD3: 200 | AE3: 200 | AF3: 300 | AG3: 300 | AH3: 300 | AI3: 300 | AV3: x | BE3: =IF(COUNTIF(AJ3:BD3,"x")>0,"x","") -> x
B4: D | C4: 05 | D4: . | E4: 01 | F4: . | G4: 004 | H4: . | I4: nnn | L4: Messstutzen | N4: 242.2 | O4: - | P4: - | Q4: - | R4: x | U4: x | V4: Rohrformteile | Z4: IfcPipeFittingType | AA4: ENTRY | AD4: 200 | AE4: 200 | AF4: 300 | AG4: 300 | AH4: 300 | AI4: 300 | AV4: x | BE4: =IF(COUNTIF(AJ4:BD4,"x")>0,"x","") -> x
B5: D | C5: 05 | D5: . | E5: 01 | F5: . | G5: 004 | H5: . | I5: nnn | L5: Abscheider | N5: 242.2 | O5: - | P5: - | Q5: - | R5: x | U5: x | V5: Rohrzubehör | Y5: Armatur HLKS | Z5: IfcValveType | AA5: DRAWOFFCOCK | AD5: 200 | AE5: 200 | AF5: 300 | AG5: 300 | AH5: 300 | AI5: 300 | AV5: x | BE5: =IF(COUNTIF(AJ5:BD5,"x")>0,"x","") -> x
B6: D | C6: 05 | D6: . | E6: 01 | F6: . | G6: 004 | H6: . | I6: nnn | L6: Isolierstück | N6: 242.2 | O6: - | P6: - | Q6: - | R6: x | U6: x | V6: Rohrformteile | Z6: IfcPipeSegmentType | AA6: SPOOL | AD6: 200 | AE6: 200 | AF6: 300 | AG6: 300 | AH6: 300 | AI6: 300 | AV6: x | BE6: =IF(COUNTIF(AJ6:BD6,"x")>0,"x","") -> x
B7: D | C7: 05 | D7: . | E7: 01 | F7: . | G7: 004 | H7: . | I7: nnn | L7: Kontrolldeckel | N7: 242.2 | O7: - | P7: - | Q7: - | R7: x | U7: x | V7: Rohrzubehör | AV7: x | BE7: =IF(COUNTIF(AJ7:BD7,"x")>0,"x","") -> x
B8: D | C8: 05 | D8: . | E8: 01 | F8: . | G8: 004 | H8: . | I8: nnn | L8: Schlammsammler | N8: 242.2 | O8: - | P8: - | Q8: - | R8: x | U8: x | V8: Rohrzubehör | Y8: Apparat HLKS | Z8: IfcFilterType | AA8: WATERFILTER | AD8: 200 | AE8: 200 | AF8: 300 | AG8: 300 | AH8: 300 | AI8: 300 | AV8: x | BE8: =IF(COUNTIF(AJ8:BD8,"x")>0,"x","") -> x
B9: D | C9: 05 | D9: . | E9: 01 | F9: . | G9: 004 | H9: . | I9: nnn | L9: Storzkupplung | N9: 242.2 | O9: - | P9: - | Q9: - | R9: x | U9: x | V9: Rohrformteile | Z9: IfcPipeFittingType | AA9: CONNECTOR | AD9: 200 | AE9: 200 | AF9: 300 | AG9: 300 | AH9: 300 | AI9: 300 | AV9: x | BE9: =IF(COUNTIF(AJ9:BD9,"x")>0,"x","") -> x
B10: D | C10: 05 | D10: . | E10: 02 | F10: . | G10: 009 | H10: . | I10: nnn | L10: Wärmeübertrager | N10: 242.0 | O10: - | P10: - | Q10: - | R10: x | U10: x | V10: HLS-Bauteile | Y10: Apparat HLKS | Z10: IfcHeatExchanger | AA10: - | AD10: 200 | AE10: 200 | AF10: 300 | AG10: 300 | AH10: 300 | AI10: 300 | AV10: x | BE10: =IF(COUNTIF(AJ10:BD10,"x")>0,"x","") -> x
B11: D | C11: 05 | D11: . | E11: 02 | F11: . | G11: 009 | H11: . | I11: nnn | L11: Wassermangelsicherung | N11: 242.2 | O11: - | P11: - | Q11: - | R11: x | U11: x | V11: HLS-Bauteile | Y11: Schaltung & Steuerung HLKSE | Z11: IfcFlowController | AA11: - | AD11: 200 | AE11: 200 | AF11: 300 | AG11: 300 | AH11: 300 | AI11: 300 | AV11: x | BE11: =IF(COUNTIF(AJ11:BD11,"x")>0,"x","") -> x

Sheet Rules
A1: Class-Assignment | B1: Klassen-Zuordnung | C1: Affectation de classe | D1: Assegnazione della classe | E1: Property-Assignment | F1: Merkmals-Zuordnung | G1: Attribution de propriété | H1: Assegnazione della proprietà | I1: DataType | J1: IFC Data Type | K1: Status | L1: ISG - Informationssicherheitsgesetz | M1: FAIR Prinzipien | N1: LifecycleStatus
A2: Systems / Installations | B2: Systeme / Anlagen | C2: Systèmes / installations | D2: Sistemi / installazioni | E2: not defined | F2: nicht definiert | G2: non défini | H2: non definito | I2: BOOLEAN | J2: nicht definiert | K2: Preview | L2: nicht klassifiziert | M2: Zugänglich kostenpflichtig | N2: Preview
A3: Physical elements | B3: Physische Bauteile | C3: Éléments physiques | D3: Elementi fisici | E3: Identification and classification | F3: Identifikation und Klassifikation | G3: Identification et classification | H3: Identificazione e classificazione | I3: CHARACTER | J3: IfcBoolean | K3: Active | L3: intern | M3: Zugänglich unentgeltlich | N3: Active
A4: Spatial structure | B4: Räumliche Struktur | C4: Structure spatiale | D4: Struttura spaziale | E4: Manufacturer and product information | F4: Hersteller- und Produktinformationen | G4: Informations sur le fabricant et le produit | H4: Informazioni sul produttore e sul prodotto | I4: INTEGER | J4: IfcDate | K4: Inactive | L4: sensitiv | M4: Nicht zugänglich - kostenpflichtig | N4: Inactive
A5: Logical zones & groups | B5: Logische Zonen & Gruppen | C5: Zones logiques et groupes | D5: Zone logiche e gruppi | E5: Geometric characteristics | F5: Geometrische Eigenschaften | G5: Caractéristiques géométriques | H5: Caratteristiche geometriche | I5: REAL | J5: IfcDateTime | K5: Deprecated | L5: geheim | M5: Nicht zugänglich - unentgeltlich | N5: Deprecated
A6: Geometric references & grids | B6: Geometrische Referenzen & Raster | C6: Références géométriques et grilles | D6: Riferimenti geometrici e griglie | E6: Physical characteristics | F6: Physikalische Eigenschaften | G6: Caractéristiques physiques | H6: Caratteristiche fisiche | I6: STRING | J6: IfcDuration | K6: Retired | N6: Retired
A7: Actors | B7: Akteure | C7: Acteurs | D7: Attori | E7: Material and construction | F7: Material und Aufbau | G7: Matériau et constitution | H7: Materiale e struttura | I7: TIME | J7: IfcGloballyUniqueId | K7: Candidate | N7: Candidate
A8: Resources | B8: Ressourcen | C8: Ressources | D8: Risorse | E8: Operating conditions and limits | F8: Betriebsbedingungen und Grenzwerte | G8: Conditions de fonctionnement et limites | H8: Condizioni operative e limiti | I8: DATETIME | J8: IfcIdentifier | K8: Recorded | N8: Recorded
A9: Processes & tasks | B9: Prozesse & Aufgaben | C9: Processus et tâches | D9: Processi e compiti | E9: Performance characteristics | F9: Leistungs- und Funktionskennwerte | G9: Caractéristiques de performance et de fonctionnement | H9: Caratteristiche prestazionali e funzionali | J9: IfcInteger | K9: Superseded | N9: Superseded
E10: Hydraulic / flow characteristics | F10: Hydraulische / strömungstechnische Kennwerte | G10: Caractéristiques hydrauliques / d’écoulement | H10: Caratteristiche idrauliche / di flusso | J10: IfcLabel | K10: Incomplete | N10: Incomplete
E11: Thermal characteristics | F11: Thermische Kennwerte | G11: Caractéristiques thermiques | H11: Caratteristiche termiche | J11: IfcLengthMeasure
E12: Electrical characteristics | F12: Elektrische Kennwerte | G12: Caractéristiques électriques | H12: Caratteristiche elettriche | J12: IfcLocalTime
E13: Measurement, control and sensing | F13: Mess-, Steuer- und Regelungsdaten | G13: Caractéristiques de mesure, de commande et de détection | H13: Caratteristiche di misurazione, controllo e rilevamento | J13: IfcLogical
E14: Connection and interface characteristics | F14: Anschluss- und Schnittstelleninformationen | G14: Caractéristiques de raccordement et d’interface | H14: Caratteristiche di collegamento e interfaccia | J14: IfcNormalisedRatioMeasure
E15: Safety and protection characteristics | F15: Sicherheits- und Schutzmerkmale | G15: Caractéristiques de sécurité et de protection | H15: Caratteristiche di sicurezza e protezione | J15: IfcPositiveInteger
E16: Installation and delivery information | F16: Montage-, Einbau- und Lieferinformationen | G16: Informations de montage, d’installation et de livraison | H16: Informazioni di montaggio, installazione e fornitura | J16: IfcPositiveLengthMeasure
E17: Reference and documentation information | F17: Referenz- und Dokumentationsinformationen | G17: Informations de référence et de documentation | H17: Informazioni di riferimento e documentazione | J17: IfcPositiveRatioMeasure
J18: IfcPositiveTimeMeasure
J19: IfcRatioMeasure
J20: IfcReal
J21: IfcText
J22: IfcThermalTransmittanceMeasure
J23: IfcTime
J24: IfcURIReference
