Workbook
Name Affectation_de_classe: Rules!$C$2:$C$47
Name Assegnazione_della_classe: Rules!$D$2:$D$47
Name Assegnazione_della_proprieta: Rules!$H$2:$H$47
Name Attribution_de_propriete: Rules!$G$2:$G$47
Name DataType: Rules!$I$2:$I$47
Name FAIR_Prinzipien: Rules!$M$2:$M$47
Name IFC_Data_Type: Rules!$J$2:$J$47
Name ISG___Informationssicherheitsgesetz: Rules!$L$2:$L$47
Name Klassen_Zuordnung: Rules!$B$2:$B$47
Name Klassifikation: Rules!$B$2:$B$47
Name LifecycleStatus: Rules!$N$2:$N$47
Name Markmals_Klassifikation: Rules!$F$2:$F$47
Name Merkmals_Zuordnung: Rules!$F$2:$F$47
Name Objekt_Einordnung: Rules!$A$2:$A$47
Name Property_Classification: Rules!$E$2:$E$47
Name Status: Rules!$K$2:$K$47

Sheet Impressum
B1: Data Dictionary - Flächenmanagement
B3: Dokumenteninformationen
C4: Status | D4: Entwurf
C5: Version | D5: v20260701
C6: Letzte Änderung | D6: 46204
C7: Autor | D7: Truong, Wendy / Joslyn, Alexander
C9: Trägerschaft
D10: IFMA
D11: Bauen digital Schweiz / buildingSMART Switzerland
B12: Projektteam
C13: Truong, Wendy | D13: IFMA
C14: Pick. Patrick | D14: IFMA
C15: Joslyn, Alexander | D15: Losinger Marazzi AG
B17: Abgrenzung | D17: Fokus auf Austauschformat IFC 4.3.2.0 (IFC4X3_ADD2)
D18: Andere Formate (z. B. CityGML, gbXML, LandXML) sind kein Bestandteil
D19: Keine Abbildung von Geodaten (Geologie, Topographie, Bewuchs, Gewässer)
D20: Strukturvorlage ist eine methodische Grundlage, kein vollständiger Data Dictionary
D21: Vollständige Datenkataloge müssen in Datenbanken realsiert werden
D22: Die Handlungsempfehlung ist keine Implementierungsrichtlinie für Softwareentwicklung
D23: Die Strukturvorlage ist ein Best Practice Beispiel und kann jederzeit an neue Anforderungen angepasst werden. Es wird davon abgeraten, auf der Basis der Strukturvorlage Applikationen oder Tools zu entwickeln.
D24: Keine konkrete Implementierung oder Vernetzung von Data Dictionaries
B27: Copyright | D27: https://creativecommons.org/licenses/by-nc-sa/4.0/

Sheet Anleitung
A1: Anleitung Strukturvorlage Data Dictionaries
B3: Inhaltsverzeichnis
B5: 1 | C5: Handhabung
B6: 2 | C6: Governance
B7: 3 | C7: Header (Kopfzeile)
B8: 4 | C8: Classes (Objekte)
B9: 5 | C9: Properties (Merkmale)
B10: 6 | C10: Values (Werte)
B11: 7 | C11: Documents (Dokument) | G11: Data Template (Datenvorlage)
B12: 8 | C12: GroupOfProperties (Merkmalsgruppen)
B14: Hinweise zur Handhabung
C16: A | D16: B | E16: C | F16: D | G16: E
B17: Hinweise zur Handhabung | C17: Erforderlich für Excel | D17: Sprachen | E17: Referenziert / System generiert | F17: Rules | G17: Erforderlich für Validierung
B18: A | C18: Erforderlich für Objektkatalog / Merkmalskatalog / Wertekatalog
C19: Definiert die Mindestanforderungen an einen Katalog. Unterscheidung zwischen yes = erforderlich / optional = bei Bedarf ergänzen / no = nicht notwendig
B20: B | C20: Sprachen
C21: Angabe zur Sprache: mehrsprachig = muss in der für den Katalog führenden Sprache enthalten sein
C22: EN, DE, FR, IT = gibt Sprache zwingend vor / neutral = nicht von Sprache abhängig
B23: C | C23: Regelt die Eingabe der Spalten
C24: Darf nicht vom Ersteller manuell ausgefüllt werden, sondern wird auf eine Quelle referenziert, resp. von eine Datenbank automatisch generiert
C25: referenced = Referenz auf anderen Katalog / system-generated = vom Zielsystem generiert
B26: D | C26: Vordefinierte Regeln
C27: Verweist auf die Dropdownliste in diesem Template
B28: E | C28: Erforderlich für eine automatische Validierung zur technischen Qualitätssicherung
C29: Gibt die Valdierungsregeln an, nach welchen die Spalteninhalte geprüft werden
A31: 2 | B31: Governance
B33: Vorgabe einer minimalen Governance für die verschiedenen Kataloge
B34: Optional können aller Regeln der SN EN ISO 23386 ergänzt werden
B36: A | C36: B | D36: C | E36: D | F36: E | G36: F | H36: G
B37: Governance | C37: Status | D37: Versionsdatum | E37: Herkunft (PROV) | F37: Regeln zur Festlegung von Merkmalen | G37: Regeln zur Festlegung von Merkmalsgruppen | H37: Management-Regeln für die Erstellung und Pflege
B38: B | C38: Vorgeschriebener Status des Merkmals während seines Lebenszyklus gemäss Liste (Enumeration)
B39: C | C39: Datum der Version. Format nach ISO 8601 = YYYY-MM-DDThh:mm:ssTDZ (T = festes Trennzeichen zwischen Datum und Uhrzeit / TDZ = Zeitzonenbezeichnung. Z = UTC, Abweichung zu UTC angeben)
C40: Beispiel: CET Zeit: 15:30 = UTC+2h > Korrekte Angabe: 2026-06-18T15:30+02:00
B41: D | C41: EN: PROV = Provenance, DE = Herkunft, Entstehungsgeschichte oder Nachweis der Datenherkunft
B42: E | C42: Um eindeutig, maschinenlesbar und für den Menschen verständlich zu sein, müssen Merkmale als Liste von Attributen festgelegt werden. Einige Attribute sind zwingend erforderlich und andere sind freigestellt.
C43: Hinweis: Entspricht PA002 bis PA040 - Attribute eines Merkmals
C44: Anwendung: Die Regeln zur Festlegung von Merkmalen müssen erst für über Datenbanken publizierte Data Dictionaries angewandt werden
B45: F | C45: Um eindeutig, maschinenlesbar und für den Menschen verständlich zu sein, müssen Merkmalsgruppen als Liste von Attributen festgelegt werden. Einige Attribute sind zwingend erforderlich und andere sind freigestellt.
C46: Hinweis: Entspricht GA001 bis GA02 - Attribute eines Merkmalsgruppe
C47: Anwendung: Die Regeln zur Festlegung von Merkmalsgruppen müssen erst für über Datenbanken publizierte Data Dictionaries angewandt werden
B48: G | C48: Verbindliche Regeln zur Erstellung, Pflege und Versionierung von Merkmalen und Merkmalsgruppen sowie zur koordinierten Abstimmung und Freigabe zwischen Akteuren zur Sicherstellung von Qualität, Konsistenz und Interoperabilität.
C49: Um eindeutig, maschinenlesbar und für den Menschen verständlich zu sein, müssen Merkmale als Liste von Attributen festgelegt werden. Einige Attribute sind zwingend erforderlich und andere sind freigestellt.
C50: Hinweis: Entspricht RA001 bis RA008 - Attribute einer Anfrage
C51: Anwendung: Die Management-Regeln für die Erstellung und Pflege müssen erst für über Datenbanken publizierte Data Dictionaries angewandt werden
A53: 3 | B53: Header (Kopfzeile)
B54: 1 | C54: Metadaten zur Erstellung eines Data Dictionaries
B55: 1.1 | C55: OrganizationCode = Kurzzeichen der Organisation
B56: 1.2 | C56: DictionaryCode = Systemgenerierter Code
B57: 1.3 | C57: DictionaryName (DE, FR, IT) = Name des Data Dictionary – mind. 1 Landessprache erforderlich
B58: 1.4 | C58: DictionaryName (EN) = Name des Data Dictionary in Englisch erforderlich
B59: 1.5 | C59: DictionaryVersion = Versionsnummer
B60: 1.6 | C60: DictionaryUri = Systemgeneriert
B61: 1.7 | C61: LifecycleStatus gemäss Dropdown Liste Ausfüllen
A63: 4 | B63: Classes (Objekte)
C65: B | D65: C | E65: D | F65: E | G65: F | H65: G | I65: H | J65: I | K65: J | O65: K | S65: L | T65: M | U65: N | V65: O | W65: P | X65: Q | Y65: R | Z65: S | AA65: T | AB65: U | AC65: V | AD65: W
B66: Structural categorisation | C66: Domain/Domäne/Domaine/Dominio | D66: System/System/Système/Sistema | E66: Category/Kategorie/Catégorie/Categoria | F66: Classes | G66: GUID/URI | H66: Class-ID | I66: Class-Code | J66: Objekt-Einordnung | K66: Bezeichnung (DE) | L66: Designation (EN) | M66: Désignation (FR) | N66: Designazione (IT) | O66: Beschreibung (DE) | P66: Description (EN) | Q66: Description (FR) | R66: Descrizione (IT) | S66: IFC 4.3.2.0 (IFC4X3_ADD2) | T66: IFC_URI | U66: IfcObject Entity | V66: IfcTypeObject Entity | W66: PredefinedType | X66: ObjectType | Y66: Governance | Z66: Status | AA66: Version date | AB66: Provenance (PROV) | AC66: RelatedDocuments | AD66: RelatedDocumentName (EN)
A68: 4.1 | B68: Structural categorisation (Strukturelle Einordnung)
C70: B | D70: C | E70: D
B71: Structural categorisation | C71: Domain/Domäne/Domaine/Dominio | D71: System/System/Système/Sistema | E71: Category/Kategorie/Catégorie/Categoria
B72: B | C72: Fachlicher Gesamtbereich, oberste Gliederung nach Disziplin Biespiele: Architektur, Tragwerk, HVAC, Verkehrswegebau, Bahntechnik, Werkleitungen
B73: C | C73: Funktionale Einheit innerhalb einer Domäne. Bündelt Objekte zu einer technischen Gesamtanlage oder Konstruktion.
C74: Beispiele: Lufttechnische Anlage, Fahrbahnkonstruktion, Oberbau Geleise, Abwasserentsorgung
B75: D | C75: Gliedert Objekte nach technischer Funktion, Material oder Bauart. Beispiele: Verteilnetz Lüftung, Belagsschichten, Schwellen, Kanalisation
A77: 4.2 | B77: Classes (Objekte)
B79: E | C79: F | D79: G | E79: H | F79: I | G79: J | K79: K
B80: Objekte | C80: GUID/URI | D80: Class-ID | E80: Class-Code | F80: Objekt-Einordnung | G80: Bezeichnung (DE) | H80: Designation (EN) | I80: Désignation (FR) | J80: Designazione (IT) | K80: Beschreibung (DE) | L80: Description (EN) | M80: Description (FR) | N80: Descrizione (IT)
B81: F | C81: System generierte URI / benutzerdefinierte Backend-Referenz = Global eindeutige, persistente Identifikatoren zur interoperablen Referenzierung von Ressourcen. Mehrfach verwendete Objekte müssen die gleiche GUID/URI besitzen
B82: G | C82: Systemgeneriert Code, bezeiht sich auf „Designation“ (EN)
B83: H | C83: Stabiler, systeminterner Code zur eindeutigen, sprachneutralen Identifikation des Objekts. Mehrfach verwendete Objekte müssen die gleiche Class-Code besitzen
B84: I | C84: Einheitliche Einordnung von Objekten entlang einer strukturierten Gliederung (räumlich, logisch, kontextuell) als fachliche Abstraktion über den gesamten Lebenszyklus.
B85: J | C85: Eindeutiger, fachlicher Name eines Objekts zur Identifikation und Einordnung. EN = zwingend & mind. eine weitere Sprache (DE, FR, IT)
B86: K | C86: Kurzbeschreibung oder Definition zur fachlichen Erläuterung eines Objekts. EN = zwingend & mind. eine weitere Sprache (DE, FR, IT)
A88: 4.3 | B88: IFC 4.3.2.0 (IFC4X3_ADD2)
B90: L | C90: M | D90: N | E90: O | F90: P | G90: Q
B91: IFC 4.3.2.0 (IFC4X3_ADD2) | C91: GUID/URI | D91: IfcObject Entity | E91: IfcTypeObject Entity | F91: PredefinedType | G91: ObjectType
B92: M | C92: URI aus buildingSMART Data Dictionary (bSDD)
B93: N | C93: Ein IfcObject ist die Verallgemeinerung jedes semantisch behandelten Objekts oder Prozesses. Objekte sind Dinge, wie sie erscheinen – d. h. Instanzen.
C94: Beispiele: physisch greifbare Elemente wie Wände, Träger oder Verkleidungen, physisch vorhandene Elemente wie Räume oder konzeptionelle Elemente wie Raster oder virtuelle Begrenzungen.
C95: Der Begriff steht auch für Prozesse wie Arbeitsaufgaben, für Steuerungselemente wie Kostenpositionen oder für Akteure wie Personen, die am Entwurfsprozess beteiligt sind.
B96: O | C96: Der Objekttyp definiert die spezifischen Informationen zu einem Typ, die allen Instanzen dieses Typs gemeinsam sind.
B97: P | C97: Enumerierter Attributwert im IFC-Schema zur normierten Klassifizierung eines Objekttyps gemäss vordefinierter Auswahlliste.
B98: Q | C98: Freitext-Attribut zur zusätzlichen, projektspezifischen Typisierung eines Objekts, wenn keine passende Klassifizierung über PredefinedType existiert.
A100: 4.4 | B100: RelatedDocuments (zugehörige Dokumente)
B102: V | C102: W
B103: RelatedDocuments | C103: RelatedDocumentName (EN)
B104: W | C104: Referenz auf „DocumentName (EN)“ im Reiter "Documents"
A106: 5 | B106: Properties (Merkmale)
B108: A | C108: B | D108: C | E108: D | F108: E | J108: F | N108: G | O108: H | P108: I | Q108: J | R108: K | S108: L | T108: M
B109: Properties (Merkmale) | C109: GUID/URI | D109: Property-ID | E109: Property-Code | F109: Bezeichnung (DE) | G109: Designation (EN) | H109: Désignation (FR) | I109: Designazione (IT) | J109: Beschreibung (DE) | K109: Description (EN) | L109: Description (FR) | M109: Descrizione (IT) | N109: DataType (Base Type) | O109: DataType (IFC) | P109: EnumerationDesignation (EN) | Q109: IFC 4.3.2.0 (IFC4X3_ADD2) | R109: IFC_URI | S109: IfcPropertySet (Pset) / IfcQuantitySet (Qto) | T109: Units/Einheit/Unité/Unità
A111: 5.1 | B111: Properties (Merkmale)
B113: A | C113: B | D113: C | E113: D | F113: E | J113: F | N113: G | O113: H | P113: I
B114: Properties (Merkmale) | C114: GUID/URI | D114: Property-ID | E114: Property-Code | F114: Bezeichnung (DE) | G114: Designation (EN) | H114: Désignation (FR) | I114: Designazione (IT) | J114: Beschreibung (DE) | K114: Description (EN) | L114: Description (FR) | M114: Descrizione (IT) | N114: DataType (Base Type) | O114: DataType (IFC) | P114: EnumerationDesignation (EN)
B115: B | C115: System generierte URI / benutzerdefinierte Backend-Referenz = Global eindeutige, persistente Identifikatoren zur interoperablen Referenzierung von Ressourcen. Mehrfach verwendete Merkmale müssen die gleiche GUID/URI besitzen
B116: C | C116: Systemgeneriert Code, bezeiht sich auf „Designation“ (EN)
B117: D | C117: Stabiler, systeminterner Code zur eindeutigen, sprachneutralen Identifikation des Merkmals. Mehrfach verwendete Merkmale müssen den gleichen Property-Code besitzen
B118: E | C118: Fachlich definiertes Merkmal zur strukturierten und maschineninterpretierbar Beschreibung eines Objekts. EN = zwingend & mind. eine weitere Sprache (DE, FR, IT)
B119: F | C119: Textliche Erläuterung zur fachlichen Bedeutung und Anwendung eines Merkmals. EN = zwingend & mind. eine weitere Sprache (DE, FR, IT)
B120: G | C120: Grundlegender Datentyp (z. B. STRING, REAL) zur Festlegung von Struktur und Werteformat. Hinweis: Entspricht PA030 - Attribute eines Merkmals
B121: H | C121: IFC-spezifischer Datentyp (z. B. IfcLabel, IfcReal) gemäss ISO 16739-1 zur Standardisierung.
B122: I | C122: Stabiler, systeminterner Code zur eindeutigen, sprachneutralen Identifikation der Werteliste.
...

Sheet Header
A1: Data Dictionary — Core Metadata
A2: Field | B2: Value | C2: Requirement | D2: Notes / Maps to
A3: IDENTIFICATION
A4: OrganizationCode | B4: BdCH | C4: user defined name (small or capital letters), max 7 chars | D4: Short org code — lowercase, max 7 chars, appears in all derived IRIs
A5: DictionaryCode | B5: data_dictionary_area_management | C5: SYSTEM-GENERATED | D5: Generated from DictionaryName (EN)
A6: DictionaryName (EN) | B6: Data Dictionary Area Management | C6: REQUIRED | D6: Required authoring title in English — source for DictionaryCode generation
A7: DictionaryName (DE) | B7: Data Dictionary Flächenmanagement | C7: OPTIONAL | D7: Core authoring title in German — minimal DCAT
A8: DictionaryName (FR) | B8: Data Dictionary Gestion des zones | C8: OPTIONAL | D8: Optional multilingual title support
A9: DictionaryName (IT) | B9: Data Dictionary Gestione dell'area | C9: DictionaryName (IT) | D9: Optional multilingual title support
A10: DictionaryVersion | B10: 0.9.0 | C10: REQUIRED | D10: Semantic versioning: MAJOR.MINOR.PATCH
A11: DictionaryUri | B11: https://example.com/BdCH/data_dictionary_area_management | C11: SYSTEM-GENERATED | D11: Derived from OrganizationCode and DictionaryCode; canonical base pattern https://example.com/<OrganizationCode>/<DictionaryCode>
C12: Guide | D12: Private organisations may keep only this tab and delete Dictionary_public.
A13: GOVERNANCE
A14: LifecycleStatus | B14: Candidate | C14: REQUIRED | D14: Governance state used to derive i14y registration status
A16: LEGEND
A17: REQUIRED: | B17: Must be filled before validation/export
A18: OPTIONAL: | B18: Fill if available

Sheet Classes
A1: Filter | B1: Hinweise zur Handhabung | C1: Structural categorisation | D1: Domain/Domäne/Domaine/Dominio | E1: System/System/Système/Sistema | F1: Category/Kategorie/Catégorie/Categoria | G1: Classes | H1: GUID/URI | I1: Class-ID | J1: Class-Code | K1: Class-Assignment | L1: Klassen-Zuordnung (DE) | M1: Affectation de classe (FR) | N1: Assegnazione della classe (IT) | O1: Designation (EN) | P1: Bezeichnung (DE) | Q1: Désignation (FR) | R1: Designazione (IT) | S1: Description (EN) | T1: Beschreibung (DE) | U1: Description (FR) | V1: Descrizione (IT) | W1: IFC 4.3.2.0 (IFC4X3_ADD2) | X1: IFC_URI | Y1: IfcObject Entity | Z1: IfcTypeObject Entity | AA1: PredefinedType | AB1: ObjectType | AC1: Governance | AD1: Status | AE1: Version date | AF1: Provenance (PROV) | AG1: RelatedDocuments | AH1: RelatedDocumentName (EN) | AJ1: User Defined (not part of HE Data Dictionary / not validated by Validator)
B2: Erforderlich für Excel | D2: optional | E2: optional | F2: optional | H2: no | I2: no | J2: yes | K2: yes | O2: yes | P2: yes | Q2: optional | R2: optional | S2: ja | T2: ja | U2: optional | V2: optional | X2: yes | Y2: yes | Z2: yes | AA2: yes | AB2: yes | AD2: yes | AE2: yes | AF2: yes | AH2: optional
B3: Sprachen | D3: multilingual | E3: multilingual | F3: multilingual | H3: neutral | I3: neutral | J3: neutral | K3: multilingual | L3: DE | M3: FR | N3: IT | O3: EN | P3: DE | Q3: FR | R3: IT | S3: EN | T3: DE | U3: FR | V3: IT | X3: multilingual | Y3: multilingual | Z3: multilingual | AA3: multilingual | AB3: multilingual | AD3: EN | AE3: neutral | AF3: EN | AH3: EN
B4: Referenziert / System generiert | H4: referenced | I4: system-generated | L4: system-generated | M4: system-generated | N4: system-generated | X4: referenced | Y4: referenced | Z4: referenced | AA4: referenced | AB4: referenced | AD4: referenced | AE4: referenced | AF4: referenced | AH4: referenced
B5: Dropdown Liste | K5: Rules.Class-Assignment | L5: Rules.Klassen-Zuordnung | M5: Rules.Affectation de classe | N5: Rules.Assegnazione della classe | AD5: Rules.Status
B6: Validierung | D6: user defined | E6: user defined | F6: user defined | H6: not validated. Info: If available system-generated URI / user defined backend reference | I6: system-generated from Designation (EN) | J6: user defined | K6: must match Rules.Class-Assignment | L6: system-generated from Class-Assignment via Rules | M6: system-generated from Class-Assignment via Rules | N6: system-generated from Class-Assignment via Rules | O6: user defined | P6: user defined | Q6: user defined | R6: user defined | S6: user defined | T6: user defined | U6: user defined | V6: user defined | X6: validated against identifiers from https://search.bsdd.buildingsmart.org/uri/buildingsmart/ifc/4.3 | Y6: validated against IFC 4.3 entity identifiers | Z6: validated against IFC 4.3 entity identifiers | AA6: validated against IFC predefined types when applicable | AB6: validated against IFC 4.3 entity identifiers | AD6: must match Rules.Status | AE6: date format 2026-06-18T15:30+02:00 | AF6: user defined | AH6: must match a DocumentName (EN) entry from Documents.DocumentName (EN)
J7: BdCH_O_31010000 | K7: Spatial structure | L7: =IFERROR(INDEX(Rules!$B:$B,MATCH(K7,Rules!$A:$A,0)),"") | M7: =IFERROR(INDEX(Rules!$C:$C,MATCH(K7,Rules!$A:$A,0)),"") | N7: =IFERROR(INDEX(Rules!$D:$D,MATCH(K7,Rules!$A:$A,0)),"") | O7: Elevation | P7: Geschossebene | S7: The physical floor level or storey level of a building. | T7: Die physische Geschossebene bzw. Etage eines Gebäudes. | X7: https://identifier.buildingsmart.org/uri/buildingsmart/ifc/4.3/class/IfcBuildingStorey | Y7: IfcBuildingStorey | Z7: IfcBuildingStorey | AD7: Candidate | AE7: 2026-06-18T15:30+02:00 | AF7: BdCH | AH7: Document type catalogue
J8: BdCH_O_31010001 | K8: Spatial structure | L8: =IFERROR(INDEX(Rules!$B:$B,MATCH(K8,Rules!$A:$A,0)),"") | M8: =IFERROR(INDEX(Rules!$C:$C,MATCH(K8,Rules!$A:$A,0)),"") | N8: =IFERROR(INDEX(Rules!$D:$D,MATCH(K8,Rules!$A:$A,0)),"") | O8: Site area | P8: Grundstückfläche | S8: Site area (plot area according to SIA 416) | T8: Parzellenfläche (Grundstückfläche gemäss SIA 416) | X8: https://identifier.buildingsmart.org/uri/buildingsmart/ifc/4.3/class/IfcSite | Y8: IfcSite | Z8: IfcSite | AD8: Candidate | AE8: 2026-06-18T15:30+02:00 | AF8: BdCH | AH8: Document type catalogue
J9: BdCH_O_31010002 | K9: Spatial structure | L9: =IFERROR(INDEX(Rules!$B:$B,MATCH(K9,Rules!$A:$A,0)),"") | M9: =IFERROR(INDEX(Rules!$C:$C,MATCH(K9,Rules!$A:$A,0)),"") | N9: =IFERROR(INDEX(Rules!$D:$D,MATCH(K9,Rules!$A:$A,0)),"") | O9: Surrounding area | P9: Umgebungsfläche | S9: Surrounding area according to SIA 416 | T9: Umgebungsfläche gemäss SIA 416 | X9: https://identifier.buildingsmart.org/uri/buildingsmart/ifc/4.3/class/IfcSpace | Y9: IfcSpace | Z9: IfcSpace | AA9: USERDEFINED | AB9: SITE_AREA | AD9: Candidate | AE9: 2026-06-18T15:30+02:00 | AF9: BdCH | AH9: Document type catalogue
J10: BdCH_O_31010003 | K10: Spatial structure | L10: =IFERROR(INDEX(Rules!$B:$B,MATCH(K10,Rules!$A:$A,0)),"") | M10: =IFERROR(INDEX(Rules!$C:$C,MATCH(K10,Rules!$A:$A,0)),"") | N10: =IFERROR(INDEX(Rules!$D:$D,MATCH(K10,Rules!$A:$A,0)),"") | O10: Gross floor area | P10: Geschossvolumen | S10: Volumetric representation of gross floor areas and storey volumes according to SIA 416 | T10: Volumetrische Darstellung der Geschossflächen (brutto) und Geschossvolumen gemäss SIA 416 | X10: https://identifier.buildingsmart.org/uri/buildingsmart/ifc/4.3/class/IfcSpace | Y10: IfcSpace | Z10: IfcSpace | AA10: USERDEFINED | AB10: SURROUNDING_AREA | AD10: Candidate | AE10: 2026-06-18T15:30+02:00 | AF10: BdCH | AH10: Document type catalogue
J11: BdCH_O_31010004 | K11: Spatial structure | L11: =IFERROR(INDEX(Rules!$B:$B,MATCH(K11,Rules!$A:$A,0)),"") | M11: =IFERROR(INDEX(Rules!$C:$C,MATCH(K11,Rules!$A:$A,0)),"") | N11: =IFERROR(INDEX(Rules!$D:$D,MATCH(K11,Rules!$A:$A,0)),"") | O11: Room | P11: Nettogeschossfläche | S11: Internal spaces (net floor areas according to SIA 416) | T11: Innenräume (Nettogeschossflächen gemäss SIA 416) | U11: https://identifier.buildingsmart.org/uri/buildingsmart/ifc/4.3/class/IfcSpaceGFA | X11: https://identifier.buildingsmart.org/uri/buildingsmart/ifc/4.3/class/IfcSpaceGFA | Y11: IfcSpace | Z11: IfcSpace | AA11: GFA | AD11: Candidate | AE11: 2026-06-18T15:30+02:00 | AF11: BdCH | AH11: Document type catalogue
J12: BdCH_O_31010005 | K12: Spatial structure | L12: =IFERROR(INDEX(Rules!$B:$B,MATCH(K12,Rules!$A:$A,0)),"") | M12: =IFERROR(INDEX(Rules!$C:$C,MATCH(K12,Rules!$A:$A,0)),"") | N12: =IFERROR(INDEX(Rules!$D:$D,MATCH(K12,Rules!$A:$A,0)),"") | O12: External room | P12: Aussen-Nettogeschossfläche | S12: External spaces (external net floor areas according to SIA 416) | T12: Aussenräume (Aussen-Nettogeschossflächen gemäss SIA 416) | X12: https://identifier.buildingsmart.org/uri/buildingsmart/ifc/4.3/class/IfcSpace | Y12: IfcSpace | Z12: IfcSpace | AA12: USERDEFINED | AB12: ROOM | AD12: Candidate | AE12: 2026-06-18T15:30+02:00 | AF12: BdCH | AH12: Document type catalogue
J13: BdCH_O_31010006 | K13: Spatial structure | L13: =IFERROR(INDEX(Rules!$B:$B,MATCH(K13,Rules!$A:$A,0)),"") | M13: =IFERROR(INDEX(Rules!$C:$C,MATCH(K13,Rules!$A:$A,0)),"") | N13: =IFERROR(INDEX(Rules!$D:$D,MATCH(K13,Rules!$A:$A,0)),"") | O13: Parking space | P13: Stellplatz | S13: Parking spaces such as car parking spaces, moped parking, bicycle parking, fire service access/parking bays | T13: Stellplätze wie z.B. Autoparkplatz, Mofa-Parkplatz, Velostellplatz, Feuerwehrstellplatz | X13: https://identifier.buildingsmart.org/uri/buildingsmart/ifc/4.3/class/IfcSpace | Y13: IfcSpace | Z13: IfcSpace | AA13: USERDEFINED | AB13: EXTERNAL_ROOM | AD13: Candidate | AE13: 2026-06-18T15:30+02:00 | AF13: BdCH | AH13: Document type catalogue
J14: BdCH_O_31010007 | K14: Spatial structure | L14: =IFERROR(INDEX(Rules!$B:$B,MATCH(K14,Rules!$A:$A,0)),"") | M14: =IFERROR(INDEX(Rules!$C:$C,MATCH(K14,Rules!$A:$A,0)),"") | N14: =IFERROR(INDEX(Rules!$D:$D,MATCH(K14,Rules!$A:$A,0)),"") | O14: Rentable area | P14: Vermietbare Fläche | S14: Representation of lettable area where this differs from net floor areas | T14: Darstellung der vermietbaren Fläche, insofern diese von den Nettoraumflächen differiert | X14: https://identifier.buildingsmart.org/uri/buildingsmart/ifc/4.3/class/IfcSpacePARKING | Y14: IfcSpace | Z14: IfcSpace | AA14: PARKING | AD14: Candidate | AE14: 2026-06-18T15:30+02:00 | AF14: BdCH | AH14: Document type catalogue
M16: =IFERROR(INDEX(Rules!$C:$C,MATCH(K16,Rules!$A:$A,0)),"") | N16: =IFERROR(INDEX(Rules!$D:$D,MATCH(K16,Rules!$A:$A,0)),"")
L17: =IFERROR(INDEX(Rules!$B:$B,MATCH(K17,Rules!$A:$A,0)),"") | M17: =IFERROR(INDEX(Rules!$C:$C,MATCH(K17,Rules!$A:$A,0)),"") | N17: =IFERROR(INDEX(Rules!$D:$D,MATCH(K17,Rules!$A:$A,0)),"")
L18: =IFERROR(INDEX(Rules!$B:$B,MATCH(K18,Rules!$A:$A,0)),"") | M18: =IFERROR(INDEX(Rules!$C:$C,MATCH(K18,Rules!$A:$A,0)),"") | N18: =IFERROR(INDEX(Rules!$D:$D,MATCH(K18,Rules!$A:$A,0)),"")
L19: =IFERROR(INDEX(Rules!$B:$B,MATCH(K19,Rules!$A:$A,0)),"") | M19: =IFERROR(INDEX(Rules!$C:$C,MATCH(K19,Rules!$A:$A,0)),"") | N19: =IFERROR(INDEX(Rules!$D:$D,MATCH(K19,Rules!$A:$A,0)),"")
L20: =IFERROR(INDEX(Rules!$B:$B,MATCH(K20,Rules!$A:$A,0)),"") | M20: =IFERROR(INDEX(Rules!$C:$C,MATCH(K20,Rules!$A:$A,0)),"") | N20: =IFERROR(INDEX(Rules!$D:$D,MATCH(K20,Rules!$A:$A,0)),"")
L21: =IFERROR(INDEX(Rules!$B:$B,MATCH(K21,Rules!$A:$A,0)),"") | M21: =IFERROR(INDEX(Rules!$C:$C,MATCH(K21,Rules!$A:$A,0)),"") | N21: =IFERROR(INDEX(Rules!$D:$D,MATCH(K21,Rules!$A:$A,0)),"")
L22: =IFERROR(INDEX(Rules!$B:$B,MATCH(K22,Rules!$A:$A,0)),"") | M22: =IFERROR(INDEX(Rules!$C:$C,MATCH(K22,Rules!$A:$A,0)),"") | N22: =IFERROR(INDEX(Rules!$D:$D,MATCH(K22,Rules!$A:$A,0)),"")
L23: =IFERROR(INDEX(Rules!$B:$B,MATCH(K23,Rules!$A:$A,0)),"") | M23: =IFERROR(INDEX(Rules!$C:$C,MATCH(K23,Rules!$A:$A,0)),"") | N23: =IFERROR(INDEX(Rules!$D:$D,MATCH(K23,Rules!$A:$A,0)),"")
L24: =IFERROR(INDEX(Rules!$B:$B,MATCH(K24,Rules!$A:$A,0)),"") | M24: =IFERROR(INDEX(Rules!$C:$C,MATCH(K24,Rules!$A:$A,0)),"") | N24: =IFERROR(INDEX(Rules!$D:$D,MATCH(K24,Rules!$A:$A,0)),"")

Sheet Properties
A1: Filter | B1: Hinweise zur Handhabung | C1: Properties | D1: GUID/URI | E1: Property-ID | F1: Property-Code | G1: Property-Assignment | H1: Merkmals-Zuordnung (DE) | I1: Attribution de propriété (FR) | J1: Assegnazione della proprietà (IT) | K1: Designation (EN) | L1: Bezeichnung (DE) | M1: Désignation (FR) | N1: Designazione (IT) | O1: Description (EN) | P1: Beschreibung (DE) | Q1: Description (FR) | R1: Descrizione (IT) | S1: DataType (Base Type) | T1: DataType (IFC) | U1: EnumerationDesignation (EN) | V1: IFC 4.3.2.0 (IFC4X3_ADD2) | W1: IFC_URI | X1: IfcPropertySet (Pset) IfcQuantitySet (Qto) | Y1: Units/Einheit/Unité/Unità | Z1: Governance | AA1: Status | AB1: Version date | AC1: Provenance (PROV) | AE1: User Defined (not part of HE Data Dictionary / not validated by Validator)
B2: Erforderlich für Excel | D2: no | E2: no | F2: yes | G2: yes | K2: yes | L2: yes | M2: optional | N2: optional | O2: yes | P2: yes | Q2: optional | R2: optional | S2: yes | T2: yes | U2: yes | W2: yes | X2: yes | Y2: yes | AA2: yes | AB2: yes | AC2: yes
B3: Sprachen | D3: neutral | E3: neutral | F3: neutral | G3: neutral | H3: DE | I3: FR | J3: IT | K3: EN | L3: DE | M3: FR | N3: IT | O3: EN | P3: DE | Q3: FR | R3: IT | S3: neutral | T3: neutral | U3: EN | W3: neutral | X3: EN | Y3: neutral | AA3: EN | AB3: neutral | AC3: EN
B4: Referenziert / System generiert | D4: referenced | E4: system-generated | H4: system-generated | I4: system-generated | J4: system-generated | S4: referenced | T4: referenced | U4: referenced | W4: referenced | X4: referenced | AA4: referenced | AB4: referenced | AC4: referenced
B5: Dropdown Liste | G5: Rules.Property-Assignment | H5: Rules.Merkmals-Zuordnung | I5: Rules.Attribution de propriété | J5: Rules.Assegnazione della proprietà | S5: Rules.DataType | T5: Rules.IFC Data Type | AA5: Rules.Status
B6: Validierung | D6: not validated. Info: If available system-generated URI / user defined backend reference | E6: system-generated from Designation (EN) | F6: user defined | G6: must match Rules.Property-Assignment | H6: system-generated from Property-Assignment via Rules | I6: system-generated from Property-Assignment via Rules | J6: system-generated from Property-Assignment via Rules | K6: user defined | L6: user defined | M6: user defined | N6: user defined | O6: user defined | P6: user defined | Q6: user defined | R6: user defined | S6: must match Rules.DataType | T6: must match Rules.IFC Data Type | U6: must match a Designation (EN) entry from Values.Designation (EN) | W6: validated against identifiers from https://search.bsdd.buildingsmart.org/uri/buildingsmart/ifc/4.3 | X6: validated against IFC 4.3 property/quantity set identifiers when IFC_URI is present | Y6: user defined | AA6: must match Rules.Status | AB6: date format 2026-06-18T15:30+02:00 | AC6: user defined
F7: BdCH_P_31020002 | H7: =IFERROR(INDEX(Rules!$F:$F,MATCH(G7,Rules!$E:$E,0)),"") | I7: =IFERROR(INDEX(Rules!$G:$G,MATCH(G7,Rules!$E:$E,0)),"") | J7: =IFERROR(INDEX(Rules!$H:$H,MATCH(G7,Rules!$E:$E,0)),"") | K7: Name | L7: ID | O7: Unique room number or floor number according to numbering scheme | P7: Eindeutige Raumnummer bzw. Geschossnummer gemäss Nummerierungskonzept | S7: STRING | T7: IfcLabel | AA7: Candidate | AB7: 2026-06-18T15:30+02:00 | AC7: BdCH
F8: BdCH_P_31020003 | H8: =IFERROR(INDEX(Rules!$F:$F,MATCH(G8,Rules!$E:$E,0)),"") | I8: =IFERROR(INDEX(Rules!$G:$G,MATCH(G8,Rules!$E:$E,0)),"") | J8: =IFERROR(INDEX(Rules!$H:$H,MATCH(G8,Rules!$E:$E,0)),"") | K8: LongName | L8: Raumbezeichnung | O8: Designation | P8: Bezeichnung | S8: STRING | T8: IfcLabel | AA8: Candidate | AB8: 2026-06-18T15:30+02:00 | AC8: BdCH
F9: BdCH_P_31020004 | H9: =IFERROR(INDEX(Rules!$F:$F,MATCH(G9,Rules!$E:$E,0)),"") | I9: =IFERROR(INDEX(Rules!$G:$G,MATCH(G9,Rules!$E:$E,0)),"") | J9: =IFERROR(INDEX(Rules!$H:$H,MATCH(G9,Rules!$E:$E,0)),"") | K9: SIA_416_2003_Code | L9: Flächenart SIA 416 Code | O9: Classification according to SIA 416 / 2003 | P9: Klassifizierung gemäss SIA 416 / 2003 | S9: STRING | T9: IfcLabel | U9: Area type SIA 416 code | AA9: Candidate | AB9: 2026-06-18T15:30+02:00 | AC9: BdCH
F10: BdCH_P_31020005 | H10: =IFERROR(INDEX(Rules!$F:$F,MATCH(G10,Rules!$E:$E,0)),"") | I10: =IFERROR(INDEX(Rules!$G:$G,MATCH(G10,Rules!$E:$E,0)),"") | J10: =IFERROR(INDEX(Rules!$H:$H,MATCH(G10,Rules!$E:$E,0)),"") | K10: SIA_416_2003_Label | L10: Flächenart SIA 416 Label | O10: Classification according to SIA 416 / 2003 | P10: Klassifizierung gemäss SIA 416 / 2003 | S10: STRING | T10: IfcLabel | U10: Area type SIA 416 label | AA10: Candidate | AB10: 2026-06-18T15:30+02:00 | AC10: BdCH
F11: BdCH_P_31020006 | H11: =IFERROR(INDEX(Rules!$F:$F,MATCH(G11,Rules!$E:$E,0)),"") | I11: =IFERROR(INDEX(Rules!$G:$G,MATCH(G11,Rules!$E:$E,0)),"") | J11: =IFERROR(INDEX(Rules!$H:$H,MATCH(G11,Rules!$E:$E,0)),"") | K11: SIA_380_2015_Code | L11: Raumbezeichnung SIA 380 Code | O11: Classification according to SIA 380 / 2015 | P11: Klassifizierung gemäss SIA 380 / 2015 | S11: STRING | T11: IfcLabel | U11: Room designation SIA 380 code | AA11: Candidate | AB11: 2026-06-18T15:30+02:00 | AC11: BdCH
F12: BdCH_P_31020007 | H12: =IFERROR(INDEX(Rules!$F:$F,MATCH(G12,Rules!$E:$E,0)),"") | I12: =IFERROR(INDEX(Rules!$G:$G,MATCH(G12,Rules!$E:$E,0)),"") | J12: =IFERROR(INDEX(Rules!$H:$H,MATCH(G12,Rules!$E:$E,0)),"") | K12: SIA_380_2015_Label | L12: Raumbezeichnung SIA 380 Label | O12: Classification according to SIA 380 / 2015 | P12: Klassifizierung gemäss SIA 380 / 2015 | S12: STRING | T12: IfcLabel | U12: Room designation SIA 380 label | AA12: Candidate | AB12: 2026-06-18T15:30+02:00 | AC12: BdCH
F13: BdCH_P_31020008 | H13: =IFERROR(INDEX(Rules!$F:$F,MATCH(G13,Rules!$E:$E,0)),"") | I13: =IFERROR(INDEX(Rules!$G:$G,MATCH(G13,Rules!$E:$E,0)),"") | J13: =IFERROR(INDEX(Rules!$H:$H,MATCH(G13,Rules!$E:$E,0)),"") | K13: SIA_2024_2021_Code | L13: Raumnutzung SIA 2024 Code | O13: Classification according to SIA 2024 / 2021 | P13: Klassifizierung gemäss SIA 2024 / 2021 | S13: STRING | T13: IfcLabel | U13: Room usage SIA 2024 code | AA13: Candidate | AB13: 2026-06-18T15:30+02:00 | AC13: BdCH
F14: BdCH_P_31020009 | H14: =IFERROR(INDEX(Rules!$F:$F,MATCH(G14,Rules!$E:$E,0)),"") | I14: =IFERROR(INDEX(Rules!$G:$G,MATCH(G14,Rules!$E:$E,0)),"") | J14: =IFERROR(INDEX(Rules!$H:$H,MATCH(G14,Rules!$E:$E,0)),"") | K14: SIA_2024_2021_Label | L14: Raumnutzung SIA 2024 Label | O14: Classification according to SIA 2024 / 2021 | P14: Klassifizierung gemäss SIA 2024 / 2021 | S14: STRING | T14: IfcLabel | U14: Room usage SIA 2024 label | AA14: Candidate | AB14: 2026-06-18T15:30+02:00 | AC14: BdCH
F15: BdCH_P_31020010 | H15: =IFERROR(INDEX(Rules!$F:$F,MATCH(G15,Rules!$E:$E,0)),"") | I15: =IFERROR(INDEX(Rules!$G:$G,MATCH(G15,Rules!$E:$E,0)),"") | J15: =IFERROR(INDEX(Rules!$H:$H,MATCH(G15,Rules!$E:$E,0)),"") | K15: SIA_d0615_2000_Code | L15: Flächenart d0165 Code | O15: Classification according to SIA D 0165 / 2000 | P15: Klassifizierung gemäss SIA D 0165 / 2000 | S15: STRING | T15: IfcLabel | U15: Area type d0165 code | AA15: Candidate | AB15: 2026-06-18T15:30+02:00 | AC15: BdCH
F16: BdCH_P_31020011 | H16: =IFERROR(INDEX(Rules!$F:$F,MATCH(G16,Rules!$E:$E,0)),"") | I16: =IFERROR(INDEX(Rules!$G:$G,MATCH(G16,Rules!$E:$E,0)),"") | J16: =IFERROR(INDEX(Rules!$H:$H,MATCH(G16,Rules!$E:$E,0)),"") | K16: SIA_d0615_2000_Label | L16: Flächenart d0165 Label | O16: Classification according to SIA D 0165 / 2000 | P16: Klassifizierung gemäss SIA D 0165 / 2000 | S16: STRING | T16: IfcLabel | U16: Area type d0165 label | AA16: Candidate | AB16: 2026-06-18T15:30+02:00 | AC16: BdCH
F17: BdCH_P_31020012 | H17: =IFERROR(INDEX(Rules!$F:$F,MATCH(G17,Rules!$E:$E,0)),"") | I17: =IFERROR(INDEX(Rules!$G:$G,MATCH(G17,Rules!$E:$E,0)),"") | J17: =IFERROR(INDEX(Rules!$H:$H,MATCH(G17,Rules!$E:$E,0)),"") | K17: ProgramUse | L17: Raumnutzung | O17: Room usage according to room programme | P17: Raumnutzung gemäss Raumprogramm | S17: STRING | T17: IfcLabel | U17: Program use | AA17: Candidate | AB17: 2026-06-18T15:30+02:00 | AC17: BdCH
F18: BdCH_P_31020013 | H18: =IFERROR(INDEX(Rules!$F:$F,MATCH(G18,Rules!$E:$E,0)),"") | I18: =IFERROR(INDEX(Rules!$G:$G,MATCH(G18,Rules!$E:$E,0)),"") | J18: =IFERROR(INDEX(Rules!$H:$H,MATCH(G18,Rules!$E:$E,0)),"") | K18: RoomType | L18: Raumtyp | O18: Room type (functional type) according to room catalogue (room data sheets) | P18: Raumtyp (Funktionstyp) gemäss Raumkatalog (Raumdatenblätter) | S18: STRING | T18: IfcLabel | U18: Room type | AA18: Candidate | AB18: 2026-06-18T15:30+02:00 | AC18: BdCH
F19: BdCH_P_31020014 | H19: =IFERROR(INDEX(Rules!$F:$F,MATCH(G19,Rules!$E:$E,0)),"") | I19: =IFERROR(INDEX(Rules!$G:$G,MATCH(G19,Rules!$E:$E,0)),"") | J19: =IFERROR(INDEX(Rules!$H:$H,MATCH(G19,Rules!$E:$E,0)),"") | K19: UnitType | L19: Einheitstyp | O19: Unit type, in particular dwelling type (e.g. 3.5-room flat) | P19: Einheitstyp, insb. Wohnungstyp z.B. 3,5-Zi | S19: STRING | T19: IfcLabel | U19: Unit type | AA19: Candidate | AB19: 2026-06-18T15:30+02:00 | AC19: BdCH
F20: BdCH_P_31020015 | H20: =IFERROR(INDEX(Rules!$F:$F,MATCH(G20,Rules!$E:$E,0)),"") | I20: =IFERROR(INDEX(Rules!$G:$G,MATCH(G20,Rules!$E:$E,0)),"") | J20: =IFERROR(INDEX(Rules!$H:$H,MATCH(G20,Rules!$E:$E,0)),"") | K20: Unit_ID | L20: Einheitsnummer | O20: Unique unit number (ID) according to numbering scheme for sale or rental units (e.g. apartment number) | P20: Eindeutige Einheitsnummer (ID) gemäss Nummerierungskonzept für Verkaufs- bzw. Mieteinheiten, z.B. Wohnungsnummer | S20: STRING | T20: IfcLabel | U20: Unit ID | AA20: Candidate | AB20: 2026-06-18T15:30+02:00 | AC20: BdCH
... F33: BdCH_P_31020028 | H33: =IFERROR(INDEX(Rules!$F:$F,MATCH(G33,Rules!$E:$E,0)),"") | I33: =IFERROR(INDEX(Rules!$G:$G,MATCH(G33,Rules!$E:$E,0)),"") | J33: =IFERROR(INDEX(Rules!$H:$H,MATCH(G33,Rules!$E:$E,0)),"") | K33: IsRentable | L33: Vermietbarkeit | O33: Letting suitability | P33: Vermietbarkeit | S33: BOOLEAN | T33: IfcBoolean | U33: Rentable | AA33: Candidate | AB33: 2026-06-18T15:30+02:00 | AC33: BdCH
F34: BdCH_P_31020029 | H34: =IFERROR(INDEX(Rules!$F:$F,MATCH(G34,Rules!$E:$E,0)),"") | I34: =IFERROR(INDEX(Rules!$G:$G,MATCH(G34,Rules!$E:$E,0)),"") | J34: =IFERROR(INDEX(Rules!$H:$H,MATCH(G34,Rules!$E:$E,0)),"") | K34: IsExternal | L34: Aussenraum | O34: Indicates whether the element is intended for outdoor use (TRUE) or not (FALSE). If set to (TRUE), the element is an external element that forms the outer boundary of a building. | P34: Angabe, ob das Element für die Verwendung im Aussenbereich vorgesehen ist (TRUE) oder nicht (FALSE). Bei (TRUE) handelt es sich um ein Aussenelement, das ein Gebäude nach außen abschliesst. | S34: BOOLEAN | T34: IfcBoolean | U34: External space | W34: https://identifier.buildingsmart.org/uri/buildingsmart/ifc/4.3/prop/IsExternal | X34: Pset_SpaceCommon | AA34: Candidate | AB34: 2026-06-18T15:30+02:00 | AC34: BdCH
F35: BdCH_P_31020030 | H35: =IFERROR(INDEX(Rules!$F:$F,MATCH(G35,Rules!$E:$E,0)),"") | I35: =IFERROR(INDEX(Rules!$G:$G,MATCH(G35,Rules!$E:$E,0)),"") | J35: =IFERROR(INDEX(Rules!$H:$H,MATCH(G35,Rules!$E:$E,0)),"") | K35: OccupancyType | L35: Nutzungsart | O35: Occupancy type for this object.; It is defined according to the presiding national building code. | P35: Nutzungsart dieses Objekts; sie wird gemäss den geltenden nationalen Bauvorschriften definiert. | S35: STRING | T35: IfcLabel | U35: Occupancy type | W35: https://identifier.buildingsmart.org/uri/buildingsmart/ifc/4.3/prop/OccupancyType | X35: Pset_SpaceOccupancyRequirements | AA35: Candidate | AB35: 2026-06-18T15:30+02:00 | AC35: BdCH
F36: BdCH_P_31020031 | H36: =IFERROR(INDEX(Rules!$F:$F,MATCH(G36,Rules!$E:$E,0)),"") | I36: =IFERROR(INDEX(Rules!$G:$G,MATCH(G36,Rules!$E:$E,0)),"") | J36: =IFERROR(INDEX(Rules!$H:$H,MATCH(G36,Rules!$E:$E,0)),"") | K36: MinimumHeadroom | L36: Raumnutzhöhe | O36: Effective clear height | P36: Lichte Höhe | S36: REAL | T36: IfcLengthMeasure | U36: Headroom | X36: Pset_SpaceOccupancyRequirements | AA36: Candidate | AB36: 2026-06-18T15:30+02:00 | AC36: BdCH
F37: BdCH_P_31020032 | H37: =IFERROR(INDEX(Rules!$F:$F,MATCH(G37,Rules!$E:$E,0)),"") | I37: =IFERROR(INDEX(Rules!$G:$G,MATCH(G37,Rules!$E:$E,0)),"") | J37: =IFERROR(INDEX(Rules!$H:$H,MATCH(G37,Rules!$E:$E,0)),"") | K37: OccupancyNumberPeak | L37: Personenbelegung geplant | O37: Maximal number of people required for the activity assigned to this space in peak time. | P37: Maximale Anzahl Personen für die zugewiesene Nutzung dieses Raums in Spitzenzeiten. | S37: INTEGER | T37: IfcInteger | U37: Planned occupancy | W37: https://identifier.buildingsmart.org/uri/buildingsmart/ifc/4.3/prop/OccupancyNumberPeak | X37: Pset_SpaceOccupancyRequirements | AA37: Candidate | AB37: 2026-06-18T15:30+02:00 | AC37: BdCH
F38: BdCH_P_31020033 | H38: =IFERROR(INDEX(Rules!$F:$F,MATCH(G38,Rules!$E:$E,0)),"") | I38: =IFERROR(INDEX(Rules!$G:$G,MATCH(G38,Rules!$E:$E,0)),"") | J38: =IFERROR(INDEX(Rules!$H:$H,MATCH(G38,Rules!$E:$E,0)),"") | K38: OccupancyNumber | L38: Personenbelegung ist | O38: Number of people required for the activity assigned to this space. | P38: Anzahl Personen für die zugewiesene Nutzung dieses Raums. | S38: INTEGER | T38: IfcInteger | U38: Actual occupancy | W38: https://identifier.buildingsmart.org/uri/buildingsmart/ifc/4.3/prop/OccupancyNumber | X38: Pset_SpaceOccupancyRequirements | AA38: Candidate | AB38: 2026-06-18T15:30+02:00 | AC38: BdCH
F39: BdCH_P_31020034 | H39: =IFERROR(INDEX(Rules!$F:$F,MATCH(G39,Rules!$E:$E,0)),"") | I39: =IFERROR(INDEX(Rules!$G:$G,MATCH(G39,Rules!$E:$E,0)),"") | J39: =IFERROR(INDEX(Rules!$H:$H,MATCH(G39,Rules!$E:$E,0)),"") | K39: FloorCovering | L39: Bodenbelag | O39: Label to indicate the material or finish of the space flooring. The label is used for room book information and often displayed in room stamp.The material information is provided in absence of an Covering (type=FLOORING) object with own shape representation and material assignment. In case of inconsistency the material assigned to Covering elements takes precedence. | P39: Kennzeichnung des Materials bzw. der Oberfläche des Bodenbelags im Raum. Die Kennzeichnung wird für Raumbuchinformationen verwendet und häufig im Raumstempel angezeigt. Die Materialinformation wird bereitgestellt, sofern kein Covering-Objekt (Typ=FLOORING) mit eigener Geometrie und Materialzuweisung vorhanden ist. Bei Inkonsistenzen hat die Materialzuweisung der Covering-Elemente Vorrang. | S39: STRING | T39: IfcLabel | U39: Floor covering | W39: https://identifier.buildingsmart.org/uri/buildingsmart/ifc/4.3/prop/FloorCovering | X39: Pset_SpaceCoveringRequirements | AA39: Candidate | AB39: 2026-06-18T15:30+02:00 | AC39: BdCH
F40: BdCH_P_31020035 | H40: =IFERROR(INDEX(Rules!$F:$F,MATCH(G40,Rules!$E:$E,0)),"") | I40: =IFERROR(INDEX(Rules!$G:$G,MATCH(G40,Rules!$E:$E,0)),"") | J40: =IFERROR(INDEX(Rules!$H:$H,MATCH(G40,Rules!$E:$E,0)),"") | K40: WallCovering | L40: Wandbelag | O40: Label to indicate the material or finish of the space cladding. The label is used for room book information and often displayed in room stamp.The material information is provided in absence of an Covering (type=CLADDING) object with own shape representation and material assignment. In case of inconsistency the material assigned to Covering elements takes precedence | P40: Kennzeichnung des Materials bzw. der Oberfläche der Wandbekleidung im Raum. Die Kennzeichnung wird für Raumbuchinformationen verwendet und häufig im Raumstempel angezeigt. Die Materialinformation wird bereitgestellt, sofern kein Covering-Objekt (Typ=CLADDING) mit eigener Geometrie und Materialzuweisung vorhanden ist. Bei Inkonsistenzen hat die Materialzuweisung der Covering-Elemente Vorrang. | S40: STRING | T40: IfcLabel | U40: Wall covering | W40: https://identifier.buildingsmart.org/uri/buildingsmart/ifc/4.3/prop/WallCovering | X40: Pset_SpaceCoveringRequirements | AA40: Candidate | AB40: 2026-06-18T15:30+02:00 | AC40: BdCH
F41: BdCH_P_31020036 | H41: =IFERROR(INDEX(Rules!$F:$F,MATCH(G41,Rules!$E:$E,0)),"") | I41: =IFERROR(INDEX(Rules!$G:$G,MATCH(G41,Rules!$E:$E,0)),"") | J41: =IFERROR(INDEX(Rules!$H:$H,MATCH(G41,Rules!$E:$E,0)),"") | K41: CeilingCovering | L41: Deckenmaterial | O41: Label to indicate the material or finish of the space ceiling. The label is used for room book information and often displayed in room stamp.The material information is provided in absence of an Covering (type=[[CEILING]]) object with own shape representation and material assignment. In case of inconsistency the material assigned to Covering elements takes precedence. | P41: Kennzeichnung des Materials bzw. der Oberfläche der Raumdecke. Die Kennzeichnung wird für Raumbuchinformationen verwendet und häufig im Raumstempel angezeigt. Die Materialinformation wird bereitgestellt, sofern kein Covering-Objekt (Typ=CEILING) mit eigener Geometrie und Materialzuweisung vorhanden ist. Bei Inkonsistenzen hat die Materialzuweisung der Covering-Elemente Vorrang. | S41: STRING | T41: IfcLabel | U41: Ceiling covering | W41: https://identifier.buildingsmart.org/uri/buildingsmart/ifc/4.3/prop/CeilingCovering | X41: Pset_SpaceCoveringRequirements | AA41: Candidate | AB41: 2026-06-18T15:30+02:00 | AC41: BdCH
F42: BdCH_P_31020037 | H42: =IFERROR(INDEX(Rules!$F:$F,MATCH(G42,Rules!$E:$E,0)),"") | I42: =IFERROR(INDEX(Rules!$G:$G,MATCH(G42,Rules!$E:$E,0)),"") | J42: =IFERROR(INDEX(Rules!$H:$H,MATCH(G42,Rules!$E:$E,0)),"") | K42: NaturalVentilation | L42: Natürliche Belüftung | O42: Indication whether the space is required to have natural ventilation (TRUE), or not (FALSE). | P42: Angabe, ob für den Raum natürliche Lüftung erforderlich ist (TRUE) oder nicht (FALSE). | S42: BOOLEAN | T42: IfcBoolean | U42: Natural ventilation | W42: https://identifier.buildingsmart.org/uri/buildingsmart/ifc/4.3/prop/NaturalVentilation | AA42: Candidate | AB42: 2026-06-18T15:30+02:00 | AC42: BdCH
F43: BdCH_P_31020038 | H43: =IFERROR(INDEX(Rules!$F:$F,MATCH(G43,Rules!$E:$E,0)),"") | I43: =IFERROR(INDEX(Rules!$G:$G,MATCH(G43,Rules!$E:$E,0)),"") | J43: =IFERROR(INDEX(Rules!$H:$H,MATCH(G43,Rules!$E:$E,0)),"") | K43: NaturalVentilationRate | L43: Natürliche Luftwechselrate | O43: Indication of the requirement of a particular natural air ventilation rate, given in air changes per hour. | P43: Angabe der erforderlichen natürlichen Luftwechselrate (in Luftwechseln pro Stunde). | S43: REAL | T43: IfcVolumetricFlowRateMeasure | U43: Natural ventilation rate | W43: https://identifier.buildingsmart.org/uri/buildingsmart/ifc/4.3/prop/NaturalVentilationRate | AA43: Candidate | AB43: 2026-06-18T15:30+02:00 | AC43: BdCH
F44: BdCH_P_31020039 | H44: =IFERROR(INDEX(Rules!$F:$F,MATCH(G44,Rules!$E:$E,0)),"") | I44: =IFERROR(INDEX(Rules!$G:$G,MATCH(G44,Rules!$E:$E,0)),"") | J44: =IFERROR(INDEX(Rules!$H:$H,MATCH(G44,Rules!$E:$E,0)),"") | K44: MechanicalVentilation | L44: Mechanische Belüftung | O44: Indication whether the space is required to have mechanical ventilation (TRUE), or not (FALSE). | P44: Angabe, ob für den Raum mechanische Lüftung erforderlich ist (TRUE) oder nicht (FALSE). | S44: BOOLEAN | T44: IfcBoolean | U44: Mechanical ventilation | W44: https://identifier.buildingsmart.org/uri/buildingsmart/ifc/4.3/prop/MechanicalVentilation | AA44: Candidate | AB44: 2026-06-18T15:30+02:00 | AC44: BdCH
F45: BdCH_P_31020040 | H45: =IFERROR(INDEX(Rules!$F:$F,MATCH(G45,Rules!$E:$E,0)),"") | I45: =IFERROR(INDEX(Rules!$G:$G,MATCH(G45,Rules!$E:$E,0)),"") | J45: =IFERROR(INDEX(Rules!$H:$H,MATCH(G45,Rules!$E:$E,0)),"") | K45: MechanicalVentilationRate | L45: Mechanische Luftwechselrate | O45: Indication of the requirement of a particular mechanical air ventilation rate, given in air changes per hour. | P45: Angabe der erforderlichen mechanischen Luftwechselrate (in Luftwechseln pro Stunde). | S45: REAL | T45: IfcVolumetricFlowRateMeasure | U45: Mechanical ventilation rate | W45: https://identifier.buildingsmart.org/uri/buildingsmart/ifc/4.3/prop/MechanicalVentilationRate | AA45: Candidate | AB45: 2026-06-18T15:30+02:00 | AC45: BdCH
F46: BdCH_P_31020041 | H46: =IFERROR(INDEX(Rules!$F:$F,MATCH(G46,Rules!$E:$E,0)),"") | I46: =IFERROR(INDEX(Rules!$G:$G,MATCH(G46,Rules!$E:$E,0)),"") | J46: =IFERROR(INDEX(Rules!$H:$H,MATCH(G46,Rules!$E:$E,0)),"") | K46: AirConditioning | L46: Klimatisiert | O46: Indication whether this space requires air conditioning provided (TRUE) or not (FALSE). | P46: Angabe, ob für diesen Raum eine Klimatisierung erforderlich ist (TRUE) oder nicht (FALSE). | S46: BOOLEAN | T46: IfcBoolean | U46: Air conditioning | W46: https://identifier.buildingsmart.org/uri/buildingsmart/ifc/4.3/prop/AirConditioning | AA46: Candidate | AB46: 2026-06-18T15:30+02:00 | AC46: BdCH
F47: BdCH_P_31020042 | H47: =IFERROR(INDEX(Rules!$F:$F,MATCH(G47,Rules!$E:$E,0)),"") | I47: =IFERROR(INDEX(Rules!$G:$G,MATCH(G47,Rules!$E:$E,0)),"") | J47: =IFERROR(INDEX(Rules!$H:$H,MATCH(G47,Rules!$E:$E,0)),"") | K47: TemperatureSetPoint | L47: Temperatur Ziel | O47: The temperature setpoint range and default setpoint. | P47: Temperatur-Sollwertbereich und Standard-Sollwert. | S47: REAL | T47: IfcThermodynamicTemperatureMeasure | U47: Temperature set point | W47: https://identifier.buildingsmart.org/uri/buildingsmart/ifc/4.3/prop/TemperatureSetPoint | AA47: Candidate | AB47: 2026-06-18T15:30+02:00 | AC47: BdCH
F48: BdCH_P_31020043 | H48: =IFERROR(INDEX(Rules!$F:$F,MATCH(G48,Rules!$E:$E,0)),"") | I48: =IFERROR(INDEX(Rules!$G:$G,MATCH(G48,Rules!$E:$E,0)),"") | J48: =IFERROR(INDEX(Rules!$H:$H,MATCH(G48,Rules!$E:$E,0)),"") | K48: HumiditySetPoint | L48: Luftfeuchtigkeit Ziel | O48: Humidity of the space or zone that is required from user/designer view point. If no summer or winter space humidity requirements are given, it applies all year, otherwise for the intermediate period. Provide this property, if no humidity range (Min-Max) is available. | P48: Geforderte Luftfeuchtigkeit des Raums bzw. der Zone aus Sicht Nutzer/Planer. Falls keine sommer- oder winterbezogenen Anforderungen angegeben sind, gilt der Wert ganzjährig, ansonsten für die Übergangszeit. Diese Eigenschaft ist anzugeben, sofern kein Feuchtebereich (Min–Max) verfügbar ist. | S48: REAL | T48: IfcReal | U48: Humidity set point | W48: https://identifier.buildingsmart.org/uri/buildingsmart/ifc/4.3/prop/HumiditySetPoint | AA48: Candidate | AB48: 2026-06-18T15:30+02:00 | AC48: BdCH
F49: BdCH_P_31020044 | H49: =IFERROR(INDEX(Rules!$F:$F,MATCH(G49,Rules!$E:$E,0)),"") | I49: =IFERROR(INDEX(Rules!$G:$G,MATCH(G49,Rules!$E:$E,0)),"") | J49: =IFERROR(INDEX(Rules!$H:$H,MATCH(G49,Rules!$E:$E,0)),"") | K49: FireExit | L49: Fluchtweg | O49: Indication whether this object is designed to serve as an exit in the case of fire (TRUE) or not (FALSE). | P49: Angabe, ob dieses Objekt im Brandfall als Ausgang dient (TRUE) oder nicht (FALSE). | S49: BOOLEAN | T49: IfcBoolean | U49: Fire exit | W49: https://identifier.buildingsmart.org/uri/buildingsmart/ifc/4.3/prop/FireExit | X49: Pset_SpaceFireSafetyRequirements | AA49: Candidate | AB49: 2026-06-18T15:30+02:00 | AC49: BdCH
F50: BdCH_P_31020045 | H50: =IFERROR(INDEX(Rules!$F:$F,MATCH(G50,Rules!$E:$E,0)),"") | I50: =IFERROR(INDEX(Rules!$G:$G,MATCH(G50,Rules!$E:$E,0)),"") | J50: =IFERROR(INDEX(Rules!$H:$H,MATCH(G50,Rules!$E:$E,0)),"") | K50: GrossFloorArea | L50: Bruttofläche | O50: Sum of all gross floor areas within the spatial structure element | P50: Summe aller Bruttogrundflächen innerhalb des räumlichen Strukturelements. | S50: REAL | T50: IfcAreaMeasure | U50: Gross floor area | W50: https://identifier.buildingsmart.org/uri/buildingsmart/ifc/4.3/prop/GrossFloorArea | X50: Qto_SpaceBaseQuantities | AA50: Candidate | AB50: 2026-06-18T15:30+02:00 | AC50: BdCH
F51: BdCH_P_31020046 | H51: =IFERROR(INDEX(Rules!$F:$F,MATCH(G51,Rules!$E:$E,0)),"") | I51: =IFERROR(INDEX(Rules!$G:$G,MATCH(G51,Rules!$E:$E,0)),"") | J51: =IFERROR(INDEX(Rules!$H:$H,MATCH(G51,Rules!$E:$E,0)),"") | K51: GrossVolume | L51: Bruttovolumen | O51: Total gross volume of the object. Openings, recesses, enclosed objects and projections are not taken into account. | P51: Gesamtes Bruttovolumen des Objekts. Öffnungen, Aussparungen, eingeschlossene Objekte und Vorsprünge werden nicht berücksichtigt. | S51: REAL | T51: IfcVolumeMeasure | U51: Gross volume | W51: https://identifier.buildingsmart.org/uri/buildingsmart/ifc/4.3/prop/GrossVolume | X51: Qto_SpaceBaseQuantities | AA51: Candidate | AB51: 2026-06-18T15:30+02:00 | AC51: BdCH
F52: BdCH_P_31020047 | H52: =IFERROR(INDEX(Rules!$F:$F,MATCH(G52,Rules!$E:$E,0)),"") | I52: =IFERROR(INDEX(Rules!$G:$G,MATCH(G52,Rules!$E:$E,0)),"") | J52: =IFERROR(INDEX(Rules!$H:$H,MATCH(G52,Rules!$E:$E,0)),"") | K52: NetFloorArea | L52: Nettofläche | O52: Sum of all net usable floor areas. | P52: Summe aller Nettogrundflächen. | S52: REAL | T52: IfcAreaMeasure | U52: Net floor area | W52: https://identifier.buildingsmart.org/uri/buildingsmart/ifc/4.3/prop/NetFloorArea | X52: Qto_SpaceBaseQuantities | AA52: Candidate | AB52: 2026-06-18T15:30+02:00 | AC52: BdCH
F53: BdCH_P_31020048 | H53: =IFERROR(INDEX(Rules!$F:$F,MATCH(G53,Rules!$E:$E,0)),"") | I53: =IFERROR(INDEX(Rules!$G:$G,MATCH(G53,Rules!$E:$E,0)),"") | J53: =IFERROR(INDEX(Rules!$H:$H,MATCH(G53,Rules!$E:$E,0)),"") | K53: NetVolume | L53: Nettovolumen | O53: Total net volume of the object, taking into account possible processing features (cut-out's, etc.) or openings and recesses. | P53: Gesamtes Nettovolumen des Objekts unter Berücksichtigung von Bearbeitungen (z. B. Ausschnitte) sowie Öffnungen und Aussparungen. | S53: REAL | T53: IfcVolumeMeasure | U53: Net volume | W53: https://identifier.buildingsmart.org/uri/buildingsmart/ifc/4.3/prop/NetVolume | X53: Qto_SpaceBaseQuantities | AA53: Candidate | AB53: 2026-06-18T15:30+02:00 | AC53: BdCH
F54: BdCH_P_31020049 | H54: =IFERROR(INDEX(Rules!$F:$F,MATCH(G54,Rules!$E:$E,0)),"") | I54: =IFERROR(INDEX(Rules!$G:$G,MATCH(G54,Rules!$E:$E,0)),"") | J54: =IFERROR(INDEX(Rules!$H:$H,MATCH(G54,Rules!$E:$E,0)),"") | K54: NetWallArea | L54: Wandfläche netto | O54: Sum of all wall (and other vertically bounding elements, like columns) areas bounded by the space. It excludes the area covered by elements inside the wall area (doors, windows, other openings, etc.). | P54: Summe aller Wandflächen (und anderer vertikal begrenzender Elemente wie Stützen), die den Raum begrenzen. Flächenanteile von Einbauten innerhalb der Wand (Türen, Fenster, Öffnungen usw.) werden nicht berücksichtigt. | S54: REAL | T54: IfcAreaMeasure | U54: Net wall area | X54: Qto_SpaceBaseQuantities | AA54: Candidate | AB54: 2026-06-18T15:30+02:00 | AC54: BdCH
F55: BdCH_P_31020050 | H55: =IFERROR(INDEX(Rules!$F:$F,MATCH(G55,Rules!$E:$E,0)),"") | I55: =IFERROR(INDEX(Rules!$G:$G,MATCH(G55,Rules!$E:$E,0)),"") | J55: =IFERROR(INDEX(Rules!$H:$H,MATCH(G55,Rules!$E:$E,0)),"") | K55: Height | L55: Höhe | O55: Vertical extent or height of the element or space. | P55: Vertikale Ausdehnung bzw. Höhe des Elements oder Raums. | S55: REAL | T55: IfcLengthMeasure | U55: Height | W55: https://identifier.buildingsmart.org/uri/buildingsmart/ifc/4.3/prop/Height | X55: Qto_SpaceBaseQuantities | AA55: Candidate | AB55: 2026-06-18T15:30+02:00 | AC55: BdCH
F56: BdCH_P_31020051 | H56: =IFERROR(INDEX(Rules!$F:$F,MATCH(G56,Rules!$E:$E,0)),"") | I56: =IFERROR(INDEX(Rules!$G:$G,MATCH(G56,Rules!$E:$E,0)),"") | J56: =IFERROR(INDEX(Rules!$H:$H,MATCH(G56,Rules!$E:$E,0)),"") | K56: AboveGround | L56: Oberirdisch | O56: Indication whether this building storey is fully above ground (TRUE), or below ground (FALSE), or partially above and below ground (UNKNOWN) - as in sloped terrain. | P56: Angabe, ob sich dieses Stockwerk vollständig über der Erde (TRUE), unter der Erde (FALSE) oder teilweise über und unter der Erde (UNKNOWN) befindet – beispielsweise bei abschüssigem Gelände. | S56: BOOLEAN | T56: IfcBoolean | AA56: Candidate | AB56: 2026-06-18T15:30+02:00 | AC56: BdCH
F57: BdCH_P_31020052 | H57: =IFERROR(INDEX(Rules!$F:$F,MATCH(G57,Rules!$E:$E,0)),"") | I57: =IFERROR(INDEX(Rules!$G:$G,MATCH(G57,Rules!$E:$E,0)),"") | J57: =IFERROR(INDEX(Rules!$H:$H,MATCH(G57,Rules!$E:$E,0)),"") | K57: CostZone | L57: Kostenzone | O57: Cost zone: for cost allocation according to commercial use, investor and/or sales product (business line) | P57: Kostenzone: für die Kostenaufteilung nach kommerzieller Nutzung bzw. Investor und/oder Verkaufsprodukt (Business Line) | S57: STRING | T57: IfcLabel | AA57: Candidate | AB57: 2026-06-18T15:30+02:00 | AC57: BdCH

Sheet Values
A1: Filter | B1: Hinweise zur Handhabung | C1: Enumerations | D1: GUID/URI | E1: Enumeration-ID | F1: Enumeration-Code | G1: Designation (EN) | H1: Bezeichnung (DE) | I1: Désignation (FR) | J1: Designazione (IT) | K1: Enumeration (EN) | L1: Werteliste (DE) | M1: Liste de valeurs (FR) | N1: Lista valori (IT) | O1: Units/Einheit/Unité/Unità | P1: Governance | Q1: Status | R1: Version date | S1: Provenance (PROV) | U1: User Defined (not part of HE Data Dictionary / not validated by Validator)
B2: Erforderlich für Excel | D2: no | E2: no | F2: yes | G2: yes | H2: yes | I2: optional | J2: optional | K2: yes | L2: yes | M2: optional | N2: optional | O2: yes | Q2: yes | R2: yes | S2: yes
B3: Sprachen | D3: neutral | E3: EN | F3: neutral | G3: EN | H3: DE | I3: FR | J3: IT | K3: EN | L3: DE | M3: FR | N3: IT | O3: multilingual | Q3: EN | R3: neutral | S3: EN
B4: Referenziert / System generiert | D4: system-generated | E4: system-generated | Q4: referenced | R4: referenced | S4: referenced
B5: Dropdown Liste | Q5: Rules.Status
B6: Validierung | D6: not validated. Info: If available system-generated URI / user defined backend reference | E6: system-generated from Designation (EN) | F6: user defined | G6: user defined | H6: user defined | I6: user defined | J6: user defined | K6: must use JSON-style list syntax, e.g. ["A", "B", "C"] or ["A", 1.5, "C"] for alphanumeric/numeric values | L6: must use JSON-style list syntax, e.g. ["A", "B", "C"] or ["A", 1.5, "C"] for alphanumeric/numeric values | M6: must use JSON-style list syntax, e.g. ["A", "B", "C"] or ["A", 1.5, "C"] for alphanumeric/numeric values | N6: must use JSON-style list syntax, e.g. ["A", "B", "C"] or ["A", 1.5, "C"] for alphanumeric/numeric values | O6: user defined | Q6: must match Rules.Status | R6: date format 2026-06-18T15:30+02:00 | S6: user defined
E7: predefinedtype_enum | F7: BDCH_V_31030000 | G7: PredefinedType | H7: Vordefinierter Typ | K7: ["GFA", "PARKING", "USERDEFINED"] | L7: ["GFA", "PARKING", "USERDEFINED"] | M7: ["GFA", "PARKING", "USERDEFINED"] | Q7: Candidate | R7: 2026-06-18T15:30+02:00 | S7: client-migration
E8: objecttype_enum | F8: BDCH_V_31030001 | G8: ObjectType | H8: Objekttyp | K8: ["SITE_AREA", "LANDSCAPE_AREA", "ROOM,EXTERNAL_ROOM", "RENTABLE_AREA"] | L8: ["SITE_AREA", "LANDSCAPE_AREA", "ROOM,EXTERNAL_ROOM", "RENTABLE_AREA"] | M8: ["SITE_AREA", "LANDSCAPE_AREA", "ROOM,EXTERNAL_ROOM", "RENTABLE_AREA"] | Q8: Candidate | R8: 2026-06-18T15:30+02:00 | S8: client-migration
E9: id_enum | F9: BDCH_V_31030002 | G9: ID | H9: ID | Q9: Candidate | R9: 2026-06-18T15:30+02:00 | S9: client-migration
E10: room_designation_enum | F10: BDCH_V_31030003 | G10: Room designation | H10: Raumbezeichnung | Q10: Candidate | R10: 2026-06-18T15:30+02:00 | S10: client-migration
E11: area_type_sia_416_code_enum | F11: BDCH_V_31030004 | G11: Area type SIA 416 code | H11: Flächenart SIA 416 Code | K11: [1.2, "1.2.1", "1.2.2", 2, "2.1.1.1", "2.1.1.2", "2.1.2", "2.1.3", 3, "3.1.1", "3.1.2", "3.1.3", "AIRSPACE", "ROOF"] | L11: [1.2, "1.2.1", "1.2.2", 2, "2.1.1.1", "2.1.1.2", "2.1.2", "2.1.3", 3, "3.1.1", "3.1.2", "3.1.3", "AIRSPACE", "ROOF"] | M11: [1.2, "1.2.1", "1.2.2", 2, "2.1.1.1", "2.1.1.2", "2.1.2", "2.1.3", 3, "3.1.1", "3.1.2", "3.1.3", "AIRSPACE", "ROOF"] | Q11: Candidate | R11: 2026-06-18T15:30+02:00 | S11: client-migration
E12: area_type_sia_416_label_enum | F12: BDCH_V_31030005 | G12: Area type SIA 416 label | H12: Flächenart SIA 416 Bezeichnung | K12: ["GSF", "UF", "BUF", "UUF", "GF", "HNF", "NNF", "VF", "FF", "AGF", "ANF", "AVF", "AFF", "GV"] | L12: ["GSF", "UF", "BUF", "UUF", "GF", "HNF", "NNF", "VF", "FF", "AGF", "ANF", "AVF", "AFF", "GV"] | M12: ["ST", "SA", "SAA", "SAN", "SP", "SUP", "SUS", "SD", "SI", "SEP", "SEU", "SED", "SEI", "VB"] | Q12: Candidate | R12: 2026-06-18T15:30+02:00 | S12: client-migration
E13: room_designation_sia_380_code_enum | F13: BDCH_V_31030006 | G13: Room designation SIA 380 code | H13: Raumbezeichnung SIA 380 Code | K13: [1, 2, 3, 4, 5, 6, 7, 8, 9, 10] | L13: [1, 2, 3, 4, 5, 6, 7, 8, 9, 10] | M13: [1, 2, 3, 4, 5, 6, 7, 8, 9, 10] | Q13: Candidate | R13: 2026-06-18T15:30+02:00 | S13: client-migration
E14: room_designation_sia_380_label_enum | F14: BDCH_V_31030007 | G14: Room designation SIA 380 label | H14: Raumbezeichnung SIA 380 Bezeichnung | K14: ["HNF1", "HNF2", "HNF3", "HNF4", "HNF5", "HNF6", "NNF7", "FF8", "VF9", "BUF10"] | L14: ["HNF1", "HNF2", "HNF3", "HNF4", "HNF5", "HNF6", "NNF7", "FF8", "VF9", "BUF10"] | M14: ["SUP1", "SUP2", "SUP3", "SUP4", "SUP5", "SUP6", "SUS7", "SI8", "SD9", "SAA10"] | Q14: Candidate | R14: 2026-06-18T15:30+02:00 | S14: client-migration
E15: room_usage_sia_2024_code_enum | F15: BDCH_V_31030008 | G15: Room usage SIA 2024 code | H15: Raumnutzung SIA 2024 Code | K15: [1.01, 1.02, 2.01, 2.02, 3.01, 3.02, 3.03, 3.04, 4.01, 4.02, 4.03, 4.04, 4.05, 5.01, 5.02, 5.03, 6.01, 6.02, 6.03, 6.04, 7.01, 7.02, 7.03, 8.01, 8.02, 8.03, 9.01, 9.02, 9.03, 10.01, 11.01, 11.02, 11.03, 12.01, 12.02, 12.03, 12.04, 12.05, 12.06, 12.07, 12.08, 12.09, 12.1, 12.11, 12.12] | L15: [1.01, 1.02, 2.01, 2.02, 3.01, 3.02, 3.03, 3.04, 4.01, 4.02, 4.03, 4.04, 4.05, 5.01, 5.02, 5.03, 6.01, 6.02, 6.03, 6.04, 7.01, 7.02, 7.03, 8.01, 8.02, 8.03, 9.01, 9.02, 9.03, 10.01, 11.01, 11.02, 11.03, 12.01, 12.02, 12.03, 12.04, 12.05, 12.06, 12.07, 12.08, 12.09, 12.1, 12.11, 12.12] | M15: [1.01, 1.02, 2.01, 2.02, 3.01, 3.02, 3.03, 3.04, 4.01, 4.02, 4.03, 4.04, 4.05, 5.01, 5.02, 5.03, 6.01, 6.02, 6.03, 6.04, 7.01, 7.02, 7.03, 8.01, 8.02, 8.03, 9.01, 9.02, 9.03, 10.01, 11.01, 11.02, 11.03, 12.01, 12.02, 12.03, 12.04, 12.05, 12.06, 12.07, 12.08, 12.09, 12.1, 12.11, 12.12] | Q15: Candidate | R15: 2026-06-18T15:30+02:00 | S15: client-migration
E16: room_usage_sia_2024_label_enum | F16: BDCH_V_31030009 | G16: Room usage SIA 2024 label | H16: Raumnutzung SIA 2024 Bezeichnung | K16: ["Wohnen Mehrfamilienhaus", "Wohnen Einfamilienhaus", "Hotelzimmer", "Empfang, Lobby", "Einzel-, Gruppenbüro", "Grossraumbüro", "Sitzungszimmer", "Schalterhalle, Empfang", "Schulzimmer", "Lehrerzimmer", "Bibliothek", "Hörsaal", "Schulfachraum", "Lebensmittelverkauf", "Fachgeschäft", "Verkauf Möbel, Bau, Garten", "Restaurant", "Selbstbedienungsrestaurant", "Küche zu Restaurant", "Küche zu Selbstbedienungsrestaurant", "Vorstellungsraum", "Mehrzweckhalle", "Ausstellungshalle", "Bettenzimmer", "Stationszimmer", "Behandlungsraum", "Produktion (grobe Arbeit)", "Produktion (feine Arbeit)", "Laborraum", "Lagerhalle", "Turnhalle", "Fitnessraum", "Schwimmhalle", "Verkehrsfläche", "Verkehrsfläche 24 h", "Treppenhaus", "Nebenraum", "Küche, Teeküche", "WC, Bad, Dusche", "WC", "Garderobe, Dusche", "Parkhaus", "Wasch- und Trockenraum", "Kühlraum", "Serverraum"] | L16: ["Wohnen Mehrfamilienhaus", "Wohnen Einfamilienhaus", "Hotelzimmer", "Empfang, Lobby", "Einzel-, Gruppenbüro", "Grossraumbüro", "Sitzungszimmer", "Schalterhalle, Empfang", "Schulzimmer", "Lehrerzimmer", "Bibliothek", "Hörsaal", "Schulfachraum", "Lebensmittelverkauf", "Fachgeschäft", "Verkauf Möbel, Bau, Garten", "Restaurant", "Selbstbedienungsrestaurant", "Küche zu Restaurant", "Küche zu Selbstbedienungsrestaurant", "Vorstellungsraum", "Mehrzweckhalle", "Ausstellungshalle", "Bettenzimmer", "Stationszimmer", "Behandlungsraum", "Produktion (grobe Arbeit)", "Produktion (feine Arbeit)", "Laborraum", "Lagerhalle", "Turnhalle", "Fitnessraum", "Schwimmhalle", "Verkehrsfläche", "Verkehrsfläche 24 h", "Treppenhaus", "Nebenraum", "Küche, Teeküche", "WC, Bad, Dusche", "WC", "Garderobe, Dusche", "Parkhaus", "Wasch- und Trockenraum", "Kühlraum", "Serverraum"] | Q16: Candidate | R16: 2026-06-18T15:30+02:00 | S16: client-migration
E17: area_type_d0165_code_enum | F17: BDCH_V_31030010 | G17: Area type d0165 code | H17: Flächenart d0165 Code | K17: [1.1, 1.2, 1.3, 1.4, 1.5, 1.6, 2.1, 2.2, 2.3, 2.4, 2.5, 2.6, 2.7, 2.8, 3.1, 3.2, 3.3, 3.4, 3.5, 3.6, 3.7, 3.8, 3.9, 4.1, 4.2, 4.3, 4.4, 4.5, 4.6, 5.1, 5.2, 5.3, 5.4, 5.5, 5.6, 5.7, 5.8, 5.9, 6.1, 6.2, 6.3, 6.4, 6.5, 6.6, 6.7, 6.8, 7.1, 7.2, 7.3, 7.4, 7.5, 7.6, 7.7, 8.1, 8.2, 8.3, 8.4, 8.5, 8.6, 8.7, 8.8, 8.9, 9.1, 9.2, 9.3, 9.4, 10.1] | L17: [1.1, 1.2, 1.3, 1.4, 1.5, 1.6, 2.1, 2.2, 2.3, 2.4, 2.5, 2.6, 2.7, 2.8, 3.1, 3.2, 3.3, 3.4, 3.5, 3.6, 3.7, 3.8, 3.9, 4.1, 4.2, 4.3, 4.4, 4.5, 4.6, 5.1, 5.2, 5.3, 5.4, 5.5, 5.6, 5.7, 5.8, 5.9, 6.1, 6.2, 6.3, 6.4, 6.5, 6.6, 6.7, 6.8, 7.1, 7.2, 7.3, 7.4, 7.5, 7.6, 7.7, 8.1, 8.2, 8.3, 8.4, 8.5, 8.6, 8.7, 8.8, 8.9, 9.1, 9.2, 9.3, 9.4, 10.1] | Q17: Candidate | R17: 2026-06-18T15:30+02:00 | S17: client-migration
E18: area_type_d0165_label_enum | F18: BDCH_V_31030011 | G18: Area type d0165 label | H18: Flächenart d0165 Bezeichnung | K18: ["Wohnräume", "Gemeinschaftsräume", "Pausenräume", "Warteräume", "Speiseräume", "Hafträume", "Büroräume", "Grossraumbüros", "Besprechungsräume", "Konstruktionsräume", "Schalterräume", "Bedienungsräume", "Aufsichtsräume", "Bürotechnikräume", "Werkhallen", "Werkstätten", "Technologische Labors", "Physikalische, physikaltechnische, elektrotechnische Labors", "Chemische, bekteriologische, morphologische Labors", "Räume für Tierhaltung", "Räume für Pflanzenzucht", "Küchen", "Sonderarbeitsräume", "Lagerräume", "Archive, Sammlungsräume", "Kühlräume", "Annahme- und Ausgaberäume", "Verkaufsräume", "Ausstellungsräume", "Unterrichtsräume mit festem Gestühl", "Allgemein Unterrichts- und Übungsräume ohne festes Gestühl", "Besondere Unterrichts- und Übungsräume ohne festes Gestühl", "Bibliotheksräume", "Sporträume", "Versammlungsräume", "Bühnen-, Studioräume", "Schauräume", "Sakralräume", "Räume mit allgemeiner medizinischen Ausstattung", "Räume mit besonderer medizinischen Ausstattung", "Räume für operative Eingriffe, Endoskopien und Entbindungen", "Räume für Strahlendiagnostik", "Räume für Strahlentherapie", "Räume für Physiotherapie und Rehabilitation", "Bettenräume mit allgemeiner Ausstattung", "Bettenräume mit besonderer Ausstattung", "Sanitärräume", "Garderoben", "Abstellräume", "Fahrzeugabstellflächen", "Fahrgastflächen", "Räume für zentrale Technik", "Schutzräum", "Abwasseraufbereitung u. -beseitigung", "Wasserversorgung", "Heizung und Brauchwassererwärmung", "Gase und Flüssigkeiten", "Elektrische Stromversorgung", "Fernmeldetechnik", "Raumlufttechnische Anlagen", "Aufzugs- und Förderanlagen", "Sonstige betriebstechnische Anlagen", "Flure, Hallen", "Treppen", "Schächte für Förderanlagen", "Fahrzeugverkehrsflächen", "aussenliegende Fahrzeugabstellflächen"] | L18: ["Wohnräume", "Gemeinschaftsräume", "Pausenräume", "Warteräume", "Speiseräume", "Hafträume", "Büroräume", "Grossraumbüros", "Besprechungsräume", "Konstruktionsräume", "Schalterräume", "Bedienungsräume", "Aufsichtsräume", "Bürotechnikräume", "Werkhallen", "Werkstätten", "Technologische Labors", "Physikalische, physikaltechnische, elektrotechnische Labors", "Chemische, bekteriologische, morphologische Labors", "Räume für Tierhaltung", "Räume für Pflanzenzucht", "Küchen", "Sonderarbeitsräume", "Lagerräume", "Archive, Sammlungsräume", "Kühlräume", "Annahme- und Ausgaberäume", "Verkaufsräume", "Ausstellungsräume", "Unterrichtsräume mit festem Gestühl", "Allgemein Unterrichts- und Übungsräume ohne festes Gestühl", "Besondere Unterrichts- und Übungsräume ohne festes Gestühl", "Bibliotheksräume", "Sporträume", "Versammlungsräume", "Bühnen-, Studioräume", "Schauräume", "Sakralräume", "Räume mit allgemeiner medizinischen Ausstattung", "Räume mit besonderer medizinischen Ausstattung", "Räume für operative Eingriffe, Endoskopien und Entbindungen", "Räume für Strahlendiagnostik", "Räume für Strahlentherapie", "Räume für Physiotherapie und Rehabilitation", "Bettenräume mit allgemeiner Ausstattung", "Bettenräume mit besonderer Ausstattung", "Sanitärräume", "Garderoben", "Abstellräume", "Fahrzeugabstellflächen", "Fahrgastflächen", "Räume für zentrale Technik", "Schutzräum", "Abwasseraufbereitung u. -beseitigung", "Wasserversorgung", "Heizung und Brauchwassererwärmung", "Gase und Flüssigkeiten", "Elektrische Stromversorgung", "Fernmeldetechnik", "Raumlufttechnische Anlagen", "Aufzugs- und Förderanlagen", "Sonstige betriebstechnische Anlagen", "Flure, Hallen", "Treppen", "Schächte für Förderanlagen", "Fahrzeugverkehrsflächen", "aussenliegende Fahrzeugabstellflächen"] | Q18: Candidate | R18: 2026-06-18T15:30+02:00 | S18: client-migration
E19: program_use_enum | F19: BDCH_V_31030012 | G19: Program use | H19: Raumnutzung | Q19: Candidate | R19: 2026-06-18T15:30+02:00 | S19: client-migration
E20: room_type_enum | F20: BDCH_V_31030013 | G20: Room type | H20: Raumtyp | Q20: Candidate | R20: 2026-06-18T15:30+02:00 | S20: client-migration
E21: unit_type_enum | F21: BDCH_V_31030014 | G21: Unit type | H21: Einheitstyp | Q21: Candidate | R21: 2026-06-18T15:30+02:00 | S21: client-migration
E22: unit_id_enum | F22: BDCH_V_31030015 | G22: Unit ID | H22: Einheitsnummer | Q22: Candidate | R22: 2026-06-18T15:30+02:00 | S22: client-migration
E23: operational_room_number_enum | F23: BDCH_V_31030016 | G23: Operational room number | H23: Raumnummer Betrieb | Q23: Candidate | R23: 2026-06-18T15:30+02:00 | S23: client-migration
E24: room_signal_label_enum | F24: BDCH_V_31030017 | G24: Room signal label | H24: Raumbeschriftung | Q24: Candidate | R24: 2026-06-18T15:30+02:00 | S24: BdCH
E25: cleaning_group_enum | F25: BDCH_V_31030018 | G25: Cleaning group | H25: Reinigungsgruppe | Q25: Candidate | R25: 2026-06-18T15:30+02:00 | S25: BdCH
E26: area_load_enum | F26: BDCH_V_31030019 | G26: Area load | H26: Flächenlast | Q26: Candidate | R26: 2026-06-18T15:30+02:00 | S26: BdCH
E27: point_load_enum | F27: BDCH_V_31030020 | G27: Point load | H27: Punktlast | Q27: Candidate | R27: 2026-06-18T15:30+02:00 | S27: BdCH
E28: energy_reference_area_enum | F28: BDCH_V_31030021 | G28: Energy reference area | H28: Energiebezugsfläche | K28: ["true", "false"] | L28: ["true", "false"] | M28: ["true", "false"] | Q28: Candidate | R28: 2026-06-18T15:30+02:00 | S28: BdCH
E29: window_area_enum | F29: BDCH_V_31030022 | G29: Window area | H29: Fensterfläche | Q29: Candidate | R29: 2026-06-18T15:30+02:00 | S29: BdCH
E30: window_openable_enum | F30: BDCH_V_31030023 | G30: Window openable | H30: Fenster öffenbar | K30: ["true", "false"] | L30: ["true", "false"] | M30: ["true", "false"] | Q30: Candidate | R30: 2026-06-18T15:30+02:00 | S30: BdCH
E31: occupant_enum | F31: BDCH_V_31030024 | G31: Occupant | H31: Raumnutzer | Q31: Candidate | R31: 2026-06-18T15:30+02:00 | S31: BdCH
E32: solar_shading_enum | F32: BDCH_V_31030025 | G32: Solar shading | H32: Sonnenschutz | K32: ["true", "false"] | L32: ["true", "false"] | M32: ["true", "false"] | Q32: Candidate | R32: 2026-06-18T15:30+02:00 | S32: BdCH
E33: humidified_enum | F33: BDCH_V_31030026 | G33: Humidified | H33: Befeuchtet | K33: ["true", "false"] | L33: ["true", "false"] | M33: ["true", "false"] | Q33: Candidate | R33: 2026-06-18T15:30+02:00 | S33: BdCH
E34: dehumidified_enum | F34: BDCH_V_31030027 | G34: Dehumidified | H34: Entfeuchtet | K34: ["true", "false"] | L34: ["true", "false"] | M34: ["true", "false"] | Q34: Candidate | R34: 2026-06-18T15:30+02:00 | S34: BdCH
E35: rentable_enum | F35: BDCH_V_31030028 | G35: Rentable | H35: Vermietbarkeit | K35: ["true", "false"] | L35: ["true", "false"] | M35: ["true", "false"] | Q35: Candidate | R35: 2026-06-18T15:30+02:00 | S35: BdCH
E36: external_space_enum | F36: BDCH_V_31030029 | G36: External space | H36: Aussenraum | K36: ["true", "false"] | L36: ["true", "false"] | M36: ["true", "false"] | Q36: Candidate | R36: 2026-06-18T15:30+02:00 | S36: BdCH
E37: occupancy_type_enum | F37: BDCH_V_31030030 | G37: Occupancy type | H37: Nutzungsart | Q37: Candidate | R37: 2026-06-18T15:30+02:00 | S37: BdCH
E38: headroom_enum | F38: BDCH_V_31030031 | G38: Headroom | H38: Raumnutzhöhe | Q38: Candidate | R38: 2026-06-18T15:30+02:00 | S38: BdCH
E39: planned_occupancy_enum | F39: BDCH_V_31030032 | G39: Planned occupancy | H39: Personenbelegung geplant | Q39: Candidate | R39: 2026-06-18T15:30+02:00 | S39: BdCH
E40: actual_occupancy_enum | F40: BDCH_V_31030033 | G40: Actual occupancy | H40: Personenbelegung ist | Q40: Candidate | R40: 2026-06-18T15:30+02:00 | S40: BdCH
E41: floor_covering_enum | F41: BDCH_V_31030034 | G41: Floor covering | H41: Bodenbelag | Q41: Candidate | R41: 2026-06-18T15:30+02:00 | S41: BdCH
E42: wall_covering_enum | F42: BDCH_V_31030035 | G42: Wall covering | H42: Wandbelag | Q42: Candidate | R42: 2026-06-18T15:30+02:00 | S42: BdCH
E43: ceiling_covering_enum | F43: BDCH_V_31030036 | G43: Ceiling covering | H43: Deckenmaterial | Q43: Candidate | R43: 2026-06-18T15:30+02:00 | S43: BdCH
E44: natural_ventilation_enum | F44: BDCH_V_31030037 | G44: Natural ventilation | H44: Natürliche Belüftung | K44: ["true", "false"] | L44: ["true", "false"] | M44: ["true", "false"] | Q44: Candidate | R44: 2026-06-18T15:30+02:00 | S44: BdCH
E45: natural_ventilation_rate_enum | F45: BDCH_V_31030038 | G45: Natural ventilation rate | H45: Natürliche Lüftung | Q45: Candidate | R45: 2026-06-18T15:30+02:00 | S45: BdCH
E46: mechanical_ventilation_enum | F46: BDCH_V_31030039 | G46: Mechanical ventilation | H46: Mechanische Belüftung | K46: ["true", "false"] | L46: ["true", "false"] | M46: ["true", "false"] | Q46: Candidate | R46: 2026-06-18T15:30+02:00 | S46: BdCH
E47: mechanical_ventilation_rate_enum | F47: BDCH_V_31030040 | G47: Mechanical ventilation rate | H47: Mechanische Lüftung | Q47: Candidate | R47: 2026-06-18T15:30+02:00 | S47: BdCH
E48: air_conditioning_enum | F48: BDCH_V_31030041 | G48: Air conditioning | H48: Klimatisiert | K48: ["true", "false"] | L48: ["true", "false"] | M48: ["true", "false"] | Q48: Candidate | R48: 2026-06-18T15:30+02:00 | S48: BdCH
E49: temperature_set_point_enum | F49: BDCH_V_31030042 | G49: Temperature set point | H49: Temperatur Ziel | Q49: Candidate | R49: 2026-06-18T15:30+02:00 | S49: BdCH
E50: humidity_set_point_enum | F50: BDCH_V_31030043 | G50: Humidity set point | H50: Luftfeuchtigkeit Ziel | Q50: Candidate | R50: 2026-06-18T15:30+02:00 | S50: BdCH
E51: fire_exit_enum | F51: BDCH_V_31030044 | G51: Fire exit | H51: Fluchtweg | K51: ["true", "false"] | L51: ["true", "false"] | M51: ["true", "false"] | Q51: Candidate | R51: 2026-06-18T15:30+02:00 | S51: BdCH
E52: gross_floor_area_enum | F52: BDCH_V_31030045 | G52: Gross floor area | H52: Bruttofläche | Q52: Candidate | R52: 2026-06-18T15:30+02:00 | S52: BdCH
E53: gross_volume_enum | F53: BDCH_V_31030046 | G53: Gross volume | H53: Bruttovolumen | Q53: Candidate | R53: 2026-06-18T15:30+02:00 | S53: BdCH
E54: net_floor_area_enum | F54: BDCH_V_31030047 | G54: Net floor area | H54: Nettofläche | Q54: Candidate | R54: 2026-06-18T15:30+02:00 | S54: BdCH
E55: net_volume_enum | F55: BDCH_V_31030048 | G55: Net volume | H55: Nettovolumen | Q55: Candidate | R55: 2026-06-18T15:30+02:00 | S55: BdCH
E56: net_wall_area_enum | F56: BDCH_V_31030049 | G56: Net wall area | H56: Wandfläche netto | Q56: Candidate | R56: 2026-06-18T15:30+02:00 | S56: BdCH
E57: height_enum | F57: BDCH_V_31030050 | G57: Height | H57: Höhe | Q57: Candidate | R57: 2026-06-18T15:30+02:00 | S57: BdCH

Sheet Documents
A1: Filter | B1: Hinweise zur Handhabung | C1: Documents | D1: GUID/URI | E1: Document-ID | F1: Document-Code | G1: DocumentName (EN) | H1: Bezeichnung (DE) | I1: Désignation (FR) | J1: Designazione (IT) | K1: Security level/Sicherheitsstufe/Niveau de sécurité/Livello di sicurezza | L1: Accessibility/Zugänglichkeit/Accessibilité/Accessibilità | M1: Revision | N1: DocumentOwner | O1: Governance | P1: Status | Q1: Version date | R1: Provenance (PROV) | T1: User Defined (not part of HE Data Dictionary / not validated by Validator)
B2: Erforderlich für Excel | D2: no | E2: no | F2: optional | G2: optional | H2: optional | I2: optional | J2: optional | K2: optional | L2: optional | M2: optional | N2: optional | P2: optional | Q2: optional | R2: optional
B3: Sprachen | D3: multilingual | E3: multilingual | F3: multilingual | G3: EN | H3: DE | I3: FR | J3: IT | K3: multilingual | L3: multilingual | M3: multilingual | N3: multilingual | P3: EN | Q3: neutral | R3: EN
B4: Referenziert / System generiert | E4: system-generated | G4: referenced | M4: referenced | N4: referenced | P4: referenced | Q4: referenced | R4: referenced
B5: Dropdown Liste | K5: Rules.ISG - Informationssicherheitsgesetz | L5: Rules.FAIR Prinzipien | P5: Rules.Status
B6: Validierung | D6: not validated. Info: If available system-generated URI / user defined backend reference | E6: system-generated from DocumentName (EN) | F6: user defined | G6: user defined | H6: user defined | I6: user defined | J6: user defined | K6: must match Rules.ISG - Informationssicherheitsgesetz | L6: must match Rules.FAIR Prinzipien | M6: user defined | N6: user defined | P6: must match Rules.Status | Q6: date format 2026-06-18T15:30+02:00 | R6: user defined
D7: https://www.kbob.admin.ch/dam/de/sd-web/2VV0AVojWznW/20240424_KBOB-IPB_Anhang_C_-_Dokumenttypenkatalog_2016_DE.xlsx | F7: BdCH_D_31040000 | G7: Document type catalogue | H7: Dokumenttypenkatalog | K7: nicht klassifiziert | L7: Zugänglich unentgeltlich | M7: 2016 | N7: KBOB | P7: Candidate | Q7: 2026-06-18T15:30+02:00 | R7: BdCH

Sheet GroupOfProperties
A1: Filter | B1: Hinweise zur Handhabung | C1: Group of Properties | D1: GoP-ID | E1: GoP-Code | F1: Designation (EN) | G1: Description (EN) | H1: Beschreibung (DE) | I1: Description (FR) | J1: Descrizione (IT) | K1: Governance | L1: Status | M1: Version date | N1: Provenance (PROV) | P1: User Defined (not part of HE Data Dictionary / not validated by Validator)
B2: Erforderlich für Excel | D2: no | E2: no | F2: yes | G2: yes | H2: yes | I2: optional | J2: optional | L2: yes | M2: yes | N2: yes
B3: Sprachen | D3: EN | E3: neutral | F3: EN | G3: EN | H3: DE | I3: FR | J3: IT | L3: multilingual | M3: multilingual | N3: multilingual
B4: Referenziert / System generiert | D4: system-generated | L4: referenced | M4: referenced | N4: referenced
B5: Dropdown Liste | L5: Rules.Status
B6: Validierung | D6: system-generated from Designation (EN) | E6: user defined | F6: must start with <OrganizationCode>_; forbidden prefixes: Pset_, IFC_, CH_ | G6: user defined | H6: user defined | I6: user defined | J6: user defined | L6: must match Rules.Status | M6: date format 2026-06-18T15:30+02:00 | N6: user defined
F7: BdCH_AreaMgmt | G7: GoP Area Management | H7: Merkmalsgruppe Flächenmanagement | L7: Candidate | M7: 2026-06-18T15:30+02:00 | N7: BdCH

Sheet Data_Template
C1: GoP | E1: Properties | BF1: Documents | BL1: Governance
C2: GoP - Designation/Bezeichnung/Désignation/Designazione | E2: Property - Designation/Bezeichnung/Désignation/Designazione | F2: Name | G2: LongName | H2: SIA_416_2003_Code | I2: SIA_416_2003_Label | J2: SIA_380_2015_Code | K2: SIA_380_2015_Label | L2: SIA_2024_2021_Code | M2: SIA_2024_2021_Label | N2: SIA_d0615_2000_Code | O2: SIA_d0615_2000_Label | P2: ProgramUse | Q2: RoomType | R2: UnitType | S2: Unit_ID | T2: RoomNumberFM | U2: RoomSignalLabel | V2: CleaningGroup | W2: AreaLoad | X2: PointLoad | Y2: EnergyReferenceArea | Z2: WindowsCleaningArea | AA2: WindowsOpenable | AB2: Occupant | AC2: Shading | AD2: IsHumidified | AE2: IsDehumidified | AF2: IsRentable | AG2: IsExternal | AH2: OccupancyType | AI2: MinimumHeadroom | AJ2: OccupancyNumberPeak | AK2: OccupancyNumber | AL2: FloorCovering | AM2: WallCovering | AN2: CeilingCovering | AO2: NaturalVentilation | AP2: NaturalVentilationRate | AQ2: MechanicalVentilation | AR2: MechanicalVentilationRate | AS2: AirConditioning | AT2: TemperatureSetPoint | AU2: HumiditySetPoint | AV2: FireExit | AW2: GrossFloorArea | AX2: GrossVolume | AY2: NetFloorArea | AZ2: NetVolume | BA2: NetWallArea | BB2: Height | BC2: AboveGround | BD2: CostZone | BF2: Document - Designation/Bezeichnung/Désignation/Designazione | BL2: Governance | BM2: Status | BN2: Version date | BO2: Provenance (PROV) | BQ2: User Defined (not part of HE Data Dictionary / not validated by Validator)
A3: Classes
A4: Class - Designation/Bezeichnung/Désignation/Designazione | BM4: Rules.Status
A5: Geschossebene | C5: BdCH_AreaMgmt | F5: x | G5: x | BM5: Candidate | BN5: 2026-06-30T12:00:00Z | BO5: BdCH
A6: Grundstückfläche | C6: BdCH_AreaMgmt | H6: 1 | I6: ["GSF", "ST"] | AG6: "true" | AW6: x | BM6: Candidate | BN6: 2026-06-30T12:00:00Z | BO6: BdCH
A7: Umgebungsfläche | C7: BdCH_AreaMgmt | G7: x | H7: [1.2, "1.2.1", "1.2.2"] | I7: ["UF", "BUF", "UUF", "SA", "SAA", "SAN"] | J7: x | P7: x | Q7: x | S7: x | AB7: x | AG7: "true" | AL7: x | AW7: x | BD7: x | BM7: Candidate | BN7: 2026-06-30T12:00:00Z | BO7: BdCH
A8: Geschossvolumen | C8: BdCH_AreaMgmt | H8: [2, 3, "AIRSPACE", "ROOF"] | I8: ["GF", "GV", "LUFTRAUM", "DACH", "SP", "VB", "SVIDE", "TOIT"] | P8: x | AB8: x | AG8: x | AW8: x | AX8: x | BB8: x | BC8: x | BD8: x | BM8: Candidate | BN8: 2026-06-30T12:00:00Z | BO8: BdCH
A9: Nettogeschossfläche | C9: BdCH_AreaMgmt | F9: x | G9: x | H9: ["2.1.1.1", "2.1.1.2", "2.1.2", "2.1.3"] | I9: ["HNF", "NNF", "VF", "FF", "SUP", "SUS", "SD", "SI"] | J9: x | K9: ["HNF1", "HNF2", "HNF3", "HNF4", "HNF5", "HNF6", "NNF7", "FF8", "VF9", "BUF10", "SUP1", "SUP2", "SUP3", "SUP4", "SUP5", "SUP6", "SUS7", "SI8", "SD9", "SAA10"] | L9: x | M9: ["Wohnen Mehrfamilienhaus", "Wohnen Einfamilienhaus", "Hotelzimmer", "Empfang, Lobby", "Einzel-, Gruppenbüro", "Grossraumbüro", "Sitzungszimmer", "Schalterhalle", "Empfang", "Schulzimmer", "Lehrerzimmer", "Bibliothek", "Hörsaal", "Schulfachraum", "Lebensmittelverkauf", "Fachgeschäft", "Verkauf Möbel, Bau, Garten", "Restaurant", "Selbstbedienungsrestaurant", "Küche zu Restaurant", "Küche zu Selbstbedienungsrestaurant", "Vorstellungsraum", "Mehrzweckhalle", "Ausstellungshalle", "Bettenzimmer", "Stationszimmer", "Behandlungsraum", "Produktion (grobe Arbeit)", "Produktion (feine Arbeit)", "Laborraum", "Lagerhalle", "Turnhalle", "Fitnessraum", "Schwimmhalle", "Verkehrsfläche", "Verkehrsfläche 24 h", "Treppenhaus", "Nebenraum", "Küche, Teeküche", "WC, Bad, Dusche", "WC", "Garderobe, Dusche", "Parkhaus", "Wasch- und Trockenraum", "Kühlraum", "Serverraum"] | N9: x | O9: ["Wohnräume", "Gemeinschaftsräume", "Pausenräume", "Warteräume", "Speiseräume", "Hafträume", "Büroräume", "Grossraumbüros", "Besprechungsräume", "Konstruktionsräume", "Schalterräume", "Bedienungsräume", "Aufsichtsräume", "Bürotechnikräume", "Werkhallen", "Werkstätten", "Technologische Labors", "Physikalische, physikaltechnische, elektrotechnische Labors", "Chemische, bekteriologische, morphologische Labors", "Räume für Tierhaltung", "Räume für Pflanzenzucht", "Küchen", "Sonderarbeitsräume", "Lagerräume", "Archive, Sammlungsräume", "Kühlräume", "Annahme- und Ausgaberäume", "Verkaufsräume", "Ausstellungsräume", "Unterrichtsräume mit festem Gestühl", "Allgemein Unterrichts- und Übungsräume ohne festes Gestühl", "Besondere Unterrichts- und Übungsräume ohne festes Gestühl", "Bibliotheksräume", "Sporträume", "Versammlungsräume", "Bühnen-, Studioräume", "Schauräume", "Sakralräume", "Räume mit allgemeiner medizinischen Ausstattung", "Räume mit besonderer medizinischen Ausstattung", "Räume für operative Eingriffe, Endoskopien und Entbindungen", "Räume für Strahlendiagnostik", "Räume für Strahlentherapie", "Räume für Physiotherapie und Rehabilitation", "Bettenräume mit allgemeiner Ausstattung", "Bettenräume mit besonderer Ausstattung", "Sanitärräume", "Garderoben", "Abstellräume", "Fahrzeugabstellflächen", "Fahrgastflächen", "Räume für zentrale Technik", "Schutzräum", "Abwasseraufbereitung u. -beseitigung", "Wasserversorgung", "Heizung und Brauchwassererwärmung", "Gase und Flüssigkeiten", "Elektrische Stromversorgung", "Fernmeldetechnik", "Raumlufttechnische Anlagen", "Aufzugs- und Förderanlagen", "Sonstige betriebstechnische Anlagen", "Flure, Hallen", "Treppen", "Schächte für Förderanlagen"] | P9: x | Q9: x | S9: x | T9: x | U9: x | V9: x | W9: x | X9: x | Y9: x | Z9: x | AA9: x | AB9: x | AC9: x | AD9: x | AE9: x | AF9: x | AG9: "false" | AH9: x | AI9: x | AJ9: x | AK9: x | AL9: x | AM9: x | AN9: x | AO9: x | AP9: x | AQ9: x | AR9: x | AS9: x | AT9: x | AU9: x | AV9: x | AY9: x | AZ9: x | BA9: x | BB9: x | BC9: x | BD9: x | BM9: Candidate | BN9: 2026-06-30T12:00:00Z | BO9: BdCH
A10: Aussen-Nettogeschossfläche | C10: BdCH_AreaMgmt | F10: x | G10: x | H10: ["3.1.1", "3.1.2", "3.1.3"] | I10: ["ANF", "AVF", "AFF", "SEU", "SED", "SEI"] | P10: x | Q10: x | S10: x | AB10: x | AG10: "true" | AH10: x | AJ10: x | AK10: x | AL10: x | AY10: x | BC10: x | BD10: x | BM10: Candidate | BN10: 2026-06-30T12:00:00Z | BO10: BdCH
A11: Stellplatz | C11: BdCH_AreaMgmt | F11: x | G11: x | N11: x | O11: ["Fahrzeugverkehrsflächen", "aussenliegende Fahrzeugabstellflächen"] | P11: x | AB11: x | AG11: x | AH11: x | AY11: x | BM11: Candidate | BN11: 2026-06-30T12:00:00Z | BO11: BdCH
A12: Vermietbare Fläche | C12: BdCH_AreaMgmt | F12: x | G12: x | P12: x | R12: x | S12: x | AB12: x | AF12: x | AJ12: x | AK12: x | AW12: x | AY12: x | BM12: Candidate | BN12: 2026-06-30T12:00:00Z | BO12: BdCH

Sheet Gelöschte Bauteile
B1: D | C1: 05 | D1: . | E1: 01 | F1: . | G1: 004 | H1: . | I1: nnn | L1: Schalldämpfer | N1: 242.2 | O1: - | P1: - | Q1: - | R1: x | U1: x | V1: Rohrzubehör | Y1: Apparat HLKS | Z1: IfcDuctSilencerType | AA1: ROUND/RECTANGULAR | AD1: 200 | AE1: 200 | AF1: 300 | AG1: 300 | AH1: 300 | AI1: 300 | AV1: x | BE1: =IF(COUNTIF(AJ1:BD1,"x")>0,"x","")
B2: D | C2: 05 | D2: . | E2: 01 | F2: . | G2: 004 | H2: . | I2: nnn | L2: Dacheinfassung | N2: 242.2 | O2: - | P2: - | Q2: - | R2: x | U2: x | V2: Rohrzubehör | Y2: Installationszubehör | Z2: IfcCoveringType | AA2: ROOFING | AD2: 200 | AE2: 200 | AF2: 300 | AG2: 300 | AH2: 300 | AI2: 300 | AV2: x | BE2: =IF(COUNTIF(AJ2:BD2,"x")>0,"x","")
B3: D | C3: 05 | D3: . | E3: 01 | F3: . | G3: 004 | H3: . | I3: nnn | L3: Revisionsstück | N3: 242.2 | O3: - | P3: - | Q3: - | R3: x | U3: x | V3: Rohrformteile | Z3: IfcPipeSegmentType | AA3: SPOOL | AD3: 200 | AE3: 200 | AF3: 300 | AG3: 300 | AH3: 300 | AI3: 300 | AV3: x | BE3: =IF(COUNTIF(AJ3:BD3,"x")>0,"x","")
B4: D | C4: 05 | D4: . | E4: 01 | F4: . | G4: 004 | H4: . | I4: nnn | L4: Messstutzen | N4: 242.2 | O4: - | P4: - | Q4: - | R4: x | U4: x | V4: Rohrformteile | Z4: IfcPipeFittingType | AA4: ENTRY | AD4: 200 | AE4: 200 | AF4: 300 | AG4: 300 | AH4: 300 | AI4: 300 | AV4: x | BE4: =IF(COUNTIF(AJ4:BD4,"x")>0,"x","")
B5: D | C5: 05 | D5: . | E5: 01 | F5: . | G5: 004 | H5: . | I5: nnn | L5: Abscheider | N5: 242.2 | O5: - | P5: - | Q5: - | R5: x | U5: x | V5: Rohrzubehör | Y5: Armatur HLKS | Z5: IfcValveType | AA5: DRAWOFFCOCK | AD5: 200 | AE5: 200 | AF5: 300 | AG5: 300 | AH5: 300 | AI5: 300 | AV5: x | BE5: =IF(COUNTIF(AJ5:BD5,"x")>0,"x","")
B6: D | C6: 05 | D6: . | E6: 01 | F6: . | G6: 004 | H6: . | I6: nnn | L6: Isolierstück | N6: 242.2 | O6: - | P6: - | Q6: - | R6: x | U6: x | V6: Rohrformteile | Z6: IfcPipeSegmentType | AA6: SPOOL | AD6: 200 | AE6: 200 | AF6: 300 | AG6: 300 | AH6: 300 | AI6: 300 | AV6: x | BE6: =IF(COUNTIF(AJ6:BD6,"x")>0,"x","")
B7: D | C7: 05 | D7: . | E7: 01 | F7: . | G7: 004 | H7: . | I7: nnn | L7: Kontrolldeckel | N7: 242.2 | O7: - | P7: - | Q7: - | R7: x | U7: x | V7: Rohrzubehör | AV7: x | BE7: =IF(COUNTIF(AJ7:BD7,"x")>0,"x","")
B8: D | C8: 05 | D8: . | E8: 01 | F8: . | G8: 004 | H8: . | I8: nnn | L8: Schlammsammler | N8: 242.2 | O8: - | P8: - | Q8: - | R8: x | U8: x | V8: Rohrzubehör | Y8: Apparat HLKS | Z8: IfcFilterType | AA8: WATERFILTER | AD8: 200 | AE8: 200 | AF8: 300 | AG8: 300 | AH8: 300 | AI8: 300 | AV8: x | BE8: =IF(COUNTIF(AJ8:BD8,"x")>0,"x","")
B9: D | C9: 05 | D9: . | E9: 01 | F9: . | G9: 004 | H9: . | I9: nnn | L9: Storzkupplung | N9: 242.2 | O9: - | P9: - | Q9: - | R9: x | U9: x | V9: Rohrformteile | Z9: IfcPipeFittingType | AA9: CONNECTOR | AD9: 200 | AE9: 200 | AF9: 300 | AG9: 300 | AH9: 300 | AI9: 300 | AV9: x | BE9: =IF(COUNTIF(AJ9:BD9,"x")>0,"x","")
B10: D | C10: 05 | D10: . | E10: 02 | F10: . | G10: 009 | H10: . | I10: nnn | L10: Wärmeübertrager | N10: 242.0 | O10: - | P10: - | Q10: - | R10: x | U10: x | V10: HLS-Bauteile | Y10: Apparat HLKS | Z10: IfcHeatExchanger | AA10: - | AD10: 200 | AE10: 200 | AF10: 300 | AG10: 300 | AH10: 300 | AI10: 300 | AV10: x | BE10: =IF(COUNTIF(AJ10:BD10,"x")>0,"x","")
B11: D | C11: 05 | D11: . | E11: 02 | F11: . | G11: 009 | H11: . | I11: nnn | L11: Wassermangelsicherung | N11: 242.2 | O11: - | P11: - | Q11: - | R11: x | U11: x | V11: HLS-Bauteile | Y11: Schaltung & Steuerung HLKSE | Z11: IfcFlowController | AA11: - | AD11: 200 | AE11: 200 | AF11: 300 | AG11: 300 | AH11: 300 | AI11: 300 | AV11: x | BE11: =IF(COUNTIF(AJ11:BD11,"x")>0,"x","")

Sheet Rules
A1: Class-Assignment | B1: Klassen-Zuordnung | C1: Affectation de classe | D1: Assegnazione della classe | E1: Property-Assignment | F1: Merkmals-Zuordnung | G1: Attribution de propriété | H1: Assegnazione della proprietà | I1: DataType | J1: IFC Data Type | K1: Status | L1: ISG - Informationssicherheitsgesetz | M1: FAIR Prinzipien | N1: LifecycleStatus
A2: Systems / Installations | B2: Systeme / Anlagen | C2: Systèmes / installations | D2: Sistemi / installazioni | E2: not defined | F2: nicht definiert | G2: non défini | H2: non definito | I2: BOOLEAN | J2: nicht definiert | K2: Preview | L2: nicht klassifiziert | M2: Zugänglich kostenpflichtig | N2: Preview
A3: Physical elements | B3: Physische Bauteile | C3: Éléments physiques | D3: Elementi fisici | E3: Identification and classification | F3: Identifikation und Klassifikation | G3: Identification et classification | H3: Identificazione e classificazione | I3: CHARACTER | J3: IfcBoolean | K3: Active | L3: intern | M3: Zugänglich unentgeltlich | N3: Active
A4: Spatial structure | B4: Räumliche Struktur | C4: Structure spatiale | D4: Struttura spaziale | E4: Manufacturer and product information | F4: Hersteller- und Produktinformationen | G4: Informations sur le fabricant et le produit | H4: Informazioni sul produttore e sul prodotto | I4: INTEGER | J4: IfcDate | K4: Inactive | L4: sensitiv | M4: Nicht zugänglich - kostenpflichtig | N4: Inactive
A5: Logical zones & groups | B5: Logische Zonen & Gruppen | C5: Zones logiques et groupes | D5: Zone logiche e gruppi | E5: Geometric characteristics | F5: Geometrische Eigenschaften | G5: Caractéristiques géométriques | H5: Caratteristiche geometriche | I5: REAL | J5: IfcDateTime | K5: Deprecated | L5: geheim | M5: Nicht zugänglich - unentgeltlich | N5: Deprecated
A6: Geometric references & grids | B6: Geometrische Referenzen & Raster | C6: Références géométriques et grilles | D6: Riferimenti geometrici e griglie | E6: Physical characteristics | F6: Physikalische Eigenschaften | G6: Caractéristiques physiques | H6: Caratteristiche fisiche | I6: STRING | J6: IfcDuration | K6: Retired | N6: Retired
A7: Actors | B7: Akteure | C7: Acteurs | D7: Attori | E7: Material and construction | F7: Material und Aufbau | G7: Matériau et constitution | H7: Materiale e struttura | I7: TIME | J7: IfcGloballyUniqueId | K7: Candidate | N7: Candidate
A8: Resources | B8: Ressourcen | C8: Ressources | D8: Risorse | E8: Operating conditions and limits | F8: Betriebsbedingungen und Grenzwerte | G8: Conditions de fonctionnement et limites | H8: Condizioni operative e limiti | I8: DATETIME | J8: IfcIdentifier | K8: Recorded | N8: Recorded
A9: Processes & tasks | B9: Prozesse & Aufgaben | C9: Processus et tâches | D9: Processi e compiti | E9: Performance characteristics | F9: Leistungs- und Funktionskennwerte | G9: Caractéristiques de performance et de fonctionnement | H9: Caratteristiche prestazionali e funzionali | J9: IfcInteger | K9: Superseded | N9: Superseded
E10: Hydraulic / flow characteristics | F10: Hydraulische / strömungstechnische Kennwerte | G10: Caractéristiques hydrauliques / d’écoulement | H10: Caratteristiche idrauliche / di flusso | J10: IfcLabel | K10: Incomplete | N10: Incomplete
E11: Thermal characteristics | F11: Thermische Kennwerte | G11: Caractéristiques thermiques | H11: Caratteristiche termiche | J11: IfcLengthMeasure
E12: Electrical characteristics | F12: Elektrische Kennwerte | G12: Caractéristiques électriques | H12: Caratteristiche elettriche | J12: IfcLocalTime
E13: Measurement, control and sensing | F13: Mess-, Steuer- und Regelungsdaten | G13: Caractéristiques de mesure, de commande et de détection | H13: Caratteristiche di misurazione, controllo e rilevamento | J13: IfcLogical
E14: Connection and interface characteristics | F14: Anschluss- und Schnittstelleninformationen | G14: Caractéristiques de raccordement et d’interface | H14: Caratteristiche di collegamento e interfaccia | J14: IfcNormalisedRatioMeasure
E15: Safety and protection characteristics | F15: Sicherheits- und Schutzmerkmale | G15: Caractéristiques de sécurité et de protection | H15: Caratteristiche di sicurezza e protezione | J15: IfcPositiveInteger
E16: Installation and delivery information | F16: Montage-, Einbau- und Lieferinformationen | G16: Informations de montage, d’installation et de livraison | H16: Informazioni di montaggio, installazione e fornitura | J16: IfcPositiveLengthMeasure
E17: Reference and documentation information | F17: Referenz- und Dokumentationsinformationen | G17: Informations de référence et de documentation | H17: Informazioni di riferimento e documentazione | J17: IfcPositiveRatioMeasure
J18: IfcPositiveTimeMeasure
J19: IfcRatioMeasure
J20: IfcReal
J21: IfcText
J22: IfcThermalTransmittanceMeasure
J23: IfcTime
J24: IfcURIReference
