Workbook
Name Affectation_de_classe: Rules!$C$2:$C$47
Name Assegnazione_della_classe: Rules!$D$2:$D$47
Name Assegnazione_della_proprieta: Rules!$H$2:$H$47
Name Attribution_de_propriete: Rules!$G$2:$G$47
Name DataType: Rules!$I$2:$I$47
Name FAIR_Prinzipien: Rules!$M$2:$M$47
Name IFC_Data_Type: Rules!$J$2:$J$47
Name ISG___Informationssicherheitsgesetz: Rules!$L$2:$L$47
Name Klassen_Zuordnung: Rules!$B$2:$B$47
Name Klassifikation: Rules!$B$2:$B$47
Name LifecycleStatus: Rules!$N$2:$N$47
Name Markmals_Klassifikation: Rules!$F$2:$F$47
Name Merkmals_Zuordnung: Rules!$F$2:$F$47
Name Objekt_Einordnung: Rules!$A$2:$A$47
Name Property_Classification: Rules!$E$2:$E$47
Name Status: Rules!$K$2:$K$47

Sheet Impressum
B1: Strukturvorlage Handlungsempfehlung Data Dictionaries
B3: Dokumenteninformationen
C4: Status | D4: Entwurf
C5: Version | D5: v20260510
C6: Letzte Änderung | D6: 46152
C7: Autor | D7: Bauen digital Schweiz / buildingSMART Switzerland (BdCH/bSCH)
B9: Trägerschaft
B12: Mit freundlicher Unterstützung von
C13: Armasuisse | E13: Schweizerische Bundesbahnen (SBB AG)
C14: B+S AG | E14: Schweizerischer Baumeisterverband (SBV)
C15: Basler & Hofmann AG | D15: Lignum Holzwirtschaft Schweiz | E15: Schweizerischer Ingenieur- und Architektenverein (SIA)
C16: Baumschlager Eberle Zürich AG | D16: Lombardi AG | E16: Stadt Luzern
C17: Buildup AG | D17: Losinger Marazzi AG | E17: Stadt Zürich
C18: Bundesamt für Strassen (ASTRA) | D18: Marti Tunnel AG | E18: Steinmann Ingenieure und Planer AG
C19: CRB | D19: MEGA | E19: Suissetec
C20: Fachgruppe für Untertagbau (FGU) | D20: Mensch und Maschine Schweiz AG | E20: Swissgee
C21: FHNW | D21: Open BIM Verband | E21: SWKI / die Planer
C22: Frutiger AG | D22: Penzel Valier AG | E22: Terradata AG
C23: HKG | D23: Rhomberg Sersa Rail Group Schweiz | E23: Walo AG
C24: IBG Engineering AG | D24: Roundtable Gebäudetechnik
C25: ILF BERATENDE INGENIEURE AG | D25: Schindler Aufzüge AG
C26: Implenia Schweiz AG | D26: Siemens AG
B28: Abgrenzung | D28: Fokus auf Austauschformat IFC 4.3.2.0 (IFC4X3_ADD2)
D29: Andere Formate (z. B. CityGML, gbXML, LandXML) sind kein Bestandteil
D30: Keine Abbildung von Geodaten (Geologie, Topographie, Bewuchs, Gewässer)
D31: Strukturvorlage ist eine methodische Grundlage, kein vollständiger Datenkatalog
D32: Vollständige Datenkataloge müssen in Datenbanken realsiert werden
D33: Die Handlungsempfehlung ist keine Implementierungsrichtlinie für Softwareentwicklung
D34: Die Strukturvorlage ist ein Best Practice Beispiel und kann jederzeit an neue Anforderungen angepasst werden. Es wird davon abgeraten, auf der Basis der Strukturvorlage Applikationen oder Tools zu entwickeln.
D35: Keine konkrete Implementierung oder Vernetzung von Datenkatalogen
B38: Copyright
D41: https://creativecommons.org/licenses/by-nc-sa/4.0/
D49: mailto:info@bauen-digital.ch

Sheet Anleitung
A1: Anleitung Strukturvorlage Data Dictionaries
B3: Inhaltsverzeichnis
B5: 1 | C5: Handhabung
B6: 2 | C6: Governance
B7: 3 | C7: Objekte
B8: 4 | C8: Klassifikationen
B9: 5 | C9: Merkmale
B10: 6 | C10: Werteliste
B11: 7 | C11: Dokumente
B13: Hinweise zur Handhabung
C15: A | D15: B | E15: C | F15: D | G15: E
B16: Hinweise zur Handhabung | C16: Erforderlich | D16: Erforderlich für Data Dictionary | E16: Sprachen | F16: Referenziert / System generiert | G16: Dropdown Liste
B17: A | C17: Erforderlich für Objektkatalog
C18: Definiert die Mindestandorderugen an einen Katalog. Unterscheidung zwischen ja = erforderlich / empfohlen / <leer> = nicht notwendig
B19: B | C19: Erforderlich für Data Dictionary
C20: Definiert die Mindestandorderugen an ein in einer Datenbank eingepfegtes Data Dictionaries. Unterscheidung zwischen ja = erforderlich / empfohlen / <leer> = nicht notwendig
B21: C | C21: Sprachen
C22: Angabe zur Sprache: mehrsprachig = muss in der für den Katalog führenden Sprache enthalten sein / EN, DE, FR, IT = gibt Sprache zwingend vor / Sprachneutral = nicht von Sprache abängig
B23: D | C23: Referenziert / System generiert
C24: Darf nicht vom Ersteller manuell ausgefüllt werden, sondern wird auf eine Quelle referenziert, resp. von eine Datenbank automatisch generiert
B25: E | C25: Dropdown Liste
C26: Verweist auf die Dropdownliste in diesem Template
A28: 2 | B28: Governance
B30: Vorgabe einer minimalen Governance für die verschiedenen Kataloge
B31: Optional können aller Regeln der SN EN ISO 23386 ergänzt werden
B33: A | C33: B | D33: C | E33: D | F33: E | G33: F | H33: G
B34: Governance | C34: Status | D34: Versionsdatum | E34: Herkunft (PROV) | F34: Regeln zur Festlegung von Merkmalen | G34: Regeln zur Festlegung von Merkmalsgruppen | H34: Management-Regeln für die Erstellung und Pflege
B35: B | C35: Vorgeschriebner Status des Merkmals während seines Lebenszyklus (Enumeration: active / inactive)
B36: C | C36: Datum der Version. Format nach ISO 8601 = YYYY-MM-DDThh:mm:ssTDZ (T = festes Trennzeichen zwischen Datum und Uhrzeit / TDZ = Zeitzonenbezeichnung. Z = UTC, Abweichung zu UTC angeben)
C38: EN: PROV = Provenance, DE = Herkunft, Entstehungsgeschichte oder Nachweis der Datenherkunft
C39: Um eindeutig, maschinenlesbar und für den Menschen verständlich zu sein, müssen Merkmale als Liste von Attributen festgelegt werden. Einige Attribute sind zwingend erforderlich und andere sind freigestellt.
C42: Um eindeutig, maschinenlesbar und für den Menschen verständlich zu sein, müssen Merkmalsgruppen als Liste von Attributen festgelegt werden. Einige Attribute sind zwingend erforderlich und andere sind freigestellt.
C45: Verbindliche Regeln zur Erstellung, Pflege und Versionierung von Merkmalen und Merkmaslgruppen sowie zur koordinierten Abstimmung und Freigabe zwischen Akteuren zur Sicherstellung von Qualität, Konsistenz und Interoperabilität.
B50: Objekte
C52: B | E52: D | F52: E | G52: F | H52: G | I52: H | J52: I | K52: J | L52: K | M52: L | N52: M | O52: N | P52: O | R52: Q | S52: R
B53: Strukturelle Einordnung | C53: Domäne | E53: Kategorie | F53: Objekte | G53: GUID/URI | H53: Objekt-ID | I53: Objekt-Einordnung | J53: Bezeichnung | K53: Designation | L53: Beschreibung | M53: Description | N53: IFC 4.3.2.0 (IFC4X3_ADD2) | O53: GUID/URI | P53: IfcObject Entity | R53: PredefinedType | S53: ObjectType
B55: Strukturelle Einordnung
C57: B | E57: D
B58: Strukturelle Einordnung | C58: Domäne | E58: Kategorie
C59: Fachlicher Gesamtbereich, oberste Gliederung nach Disziplin Biespiele: Architektur, Tragwerk, HVAC, Verkehrswegebau, Bahntechnik, Werkleitungen
B60: C | C60: Funktionale Einheit innerhalb einer Domäne. Bündelt Bauteile zu einer technischen Gesamtanlage oder Konstruktion. Beispiele: Lufttechnische Anlage, Fahrbahnkonstruktion, Oberbau Geleise, Abwasserentsorgung
B61: D | C61: Gliedert Komponenten nach technischer Funktion, Material oder Bauart. Beispiele: Verteilnetz Lüftung, Belagsschichten, Schwellen, Kanalisation
A63: 3.2 | B63: Objekte
B65: E | C65: F | D65: G | E65: H | F65: I | G65: J | H65: K | I65: L
B66: Objekte | C66: GUID/URI | D66: Objekt-ID | E66: Objekt-Einordnung | F66: Bezeichnung | G66: Designation | H66: Beschreibung | I66: Description
B67: F | C67: Global eindeutige, persistente Identifikatoren zur interoperablen Referenzierung von Ressourcen.
B68: G | C68: Stabiler, systeminterner Code zur eindeutigen, sprachneutralen Identifikation des Objekts. Mehrfach verwendete Objekte müssen die gleiche Objekt-ID besitzen
B69: H | C69: Einheitliche Einordnung von Objekten entlang einer strukturierten Gliederung (räumlich, logisch, kontextuell) als fachliche Abstraktion über den gesamten Lebenszyklus.
B70: I | C70: Eindeutiger, fachlicher Name eines Objekts zur Identifikation und Einordnung
B71: J | C71: EN: Unique, domain-specific name of an object for identification and classification
B72: K | C72: Kurzbeschreibung oder Definition zur fachlichen Erläuterung eines Objekts
B73: L | C73: EN: Short description or definition explaining an object in a domain context
A75: 3.3 | B75: IFC 4.3.2.0 (IFC4X3_ADD2)
B77: M | C77: N | D77: O | E77: P | F77: Q | G77: R
B78: IFC 4.3.2.0 (IFC4X3_ADD2) | C78: GUID/URI | D78: IfcObject Entity | E78: IfcTypeObject Entity | F78: PredefinedType | G78: ObjectType
B79: N | C79: Global eindeutige, persistente Identifikatoren zur interoperablen Referenzierung von Ressourcen.
B80: O | C80: Ein IfcObject ist die Verallgemeinerung jedes semantisch behandelten Objekts oder Prozesses. Objekte sind Dinge, wie sie erscheinen – d. h. Instanzen.
C81: Beispiele: physisch greifbare Elemente wie Wände, Träger oder Verkleidungen, physisch vorhandene Elemente wie Räume oder konzeptionelle Elemente wie Raster oder virtuelle Begrenzungen.
C82: Der Begriff steht auch für Prozesse wie Arbeitsaufgaben, für Steuerungselemente wie Kostenpositionen oder für Akteure wie Personen, die am Entwurfsprozess beteiligt sind.
B83: P | C83: Der Objekttyp definiert die spezifischen Informationen zu einem Typ, die allen Instanzen dieses Typs gemeinsam sind.
B84: Q | C84: Enumerierter Attributwert im IFC-Schema zur normierten Klassifizierung eines Objekttyps gemäss vordefinierter Auswahlliste.
B85: R | C85: Freitext-Attribut zur zusätzlichen, projektspezifischen Typisierung eines Objekts, wenn keine passende Klassifizierung über PredefinedType existiert.
A88: 4 | B88: Klassifikationen
B90: A | C90: B | D90: C | E90: D | F90: E | G90: F | H90: G | I90: H
C91: IfcClassification | G91: IfcClassRef
B92: Klassifikationen | C92: Specification | D92: Name | E92: Source | F92: Edition | G92: Location | H92: Identification | I92: Name
B93: B | C93: Ressourcenbezeichner oder -lokator der Klassifizierung, angegeben als URI, URN oder URL.
B94: C | C94: Die Bezeichnung oder das Kürzel, unter dem die verwendete Klassifikation üblicherweise bekannt ist.
B95: D | C95: Quelle (oder Herausgeber) der Klassifikation.
B96: E | C96: Die Ausgabe oder Version des Klassifizierungssystems, aus der die Klassifizierungsbezeichnung stammt.
B97: F | C97: Ort, an dem auf die externe Quelle (Klassifizierung, Dokument oder Bibliothek) auf elektronischem Wege zugegriffen werden kann. Der elektronische Speicherort wird als URI angegeben und normalerweise in Form einer URL-Adresse bereitgestellt.
B98: G | C98: Die Identifikation liefert eine eindeutige Kennung des referenzierten Elements innerhalb der externen Quelle (Klassifikation, Dokument oder Bibliothek). Sie kann in Form von * einem Schlüssel, z. B. einer Klassifikationsbezeichnung wie NF2.3, einer UUID oder einer GUID vorliegen
B99: H | C99: Optionaler Name zur genaueren Spezifizierung der Referenz. Er kann als für Menschen lesbare Kennung dienen (die nicht unbedingt eine Entsprechung in der internen Struktur des Dokuments haben muss).
A101: 5 | B101: Merkmale
C103: Merkmale | M103: IFC 4.3.2.0 | R103: MG
B104: A | C104: B | D104: C | E104: D | F104: E | G104: F | H104: G | I104: H | J104: I | K104: J | L104: K | M104: L | N104: M | O104: N | P104: O | Q104: P | R104: Q
B105: Merkmale | C105: GUID/URI | D105: Merkmal-ID | E105: Merkmal | F105: Property | G105: Beschreibung | H105: Description (EN) | I105: DataType (Base Type) | J105: DataType (IFC) | K105: Werteliste-ID | L105: IFC 4.3.2.0 (IFC4X3_ADD2) | M105: GUID/URI | N105: IfcPropertySet (Pset) | O105: IfcQuantitySet (Qto) | P105: Benutzerdefiniertes PropertySet | Q105: Merkmalsgruppen | R105: Merkmalsgruppe (group of property)
A107: 5.1 | B107: Merkmale
B109: A | C109: B | D109: C | E109: D | F109: E | G109: F | H109: G | I109: H | J109: I | K109: J
B110: Merkmal | C110: GUID/URI | D110: Merkmal-ID | E110: Merkmal | F110: Property | G110: Beschreibung | H110: Description (EN) | I110: DataType (Base Type) | J110: DataType (IFC) | K110: Werteliste-ID
B111: B | C111: Global eindeutige, persistente Identifikatoren zur interoperablen Referenzierung von Ressourcen.
B112: C | C112: Stabiler, systeminterner Code zur eindeutigen, sprachneutralen Identifikation des Objekts. Mehrfach verwendete Objekte müssen die gleiche Objekt-ID besitzen
B113: D | C113: Fachlich definiertes Attribut zur strukturierten Beschreibung eines Objekts in einem Datenkatalog.
B114: E | C114: EN: Defined attribute used to describe an object in a structured and machine-readable way.
B115: F | C115: Textliche Erläuterung zur fachlichen Bedeutung und Anwendung eines Merkmals.
B116: G | C116: EN: Textual explanation of the meaning and intended use of a property.
B117: H | C117: Grundlegender Datentyp (z. B. STRING, REAL) zur Festlegung von Struktur und Werteformat. Hinweis: Entspricht PA030 - Attribute eines Merkmals
B118: I | C118: IFC-spezifischer Datentyp (z. B. IfcLabel, IfcReal) gemäss ISO 16739-1 zur Standardisierung.
B119: J | C119: Stabiler, systeminterner Code zur eindeutigen, sprachneutralen Identifikation der Werteliste.
A121: 5.2 | B121: IFC 4.3.2.0 (IFC4X3_ADD2)
B123: K | C123: L | D123: M | E123: N | F123: O
B124: IFC 4.3.2.0 (IFC4X3_ADD2) | C124: GUID/URI | D124: IfcPropertySet (Pset) | E124: IfcQuantitySet (Qto) | F124: Benutzerdefiniertes PropertySet
B125: L | C125: Global eindeutige, persistente Identifikatoren zur interoperablen Referenzierung von Ressourcen.
C126: Hinweis: Entspricht PA001 - Attribute eines Merkmals
B127: M | C127: Beschreibt eine Liste von Merkmalen für eine IFC-Entität. Merkmalssätze, deren Struktur und Eigenschaften fest in der IFC-Spezifikation definiert sind (z. B. Pset_WallCommon oder Pset_DoorCommon).
B128: N | C128: Beschreibt eine Liste von Mengen für eine IFC-Entität. Mengen­sätze, deren Struktur und Inhalte in der IFC-Spezifikation definiert sind (z. B. Qto_WallBaseQuantities).
B129: O | C129: Beschreibt eine Liste von Merkmalen für eine IFC-Entität. Dient dazu, projekt-, regionalspezifische oder anwendungsspezifische Merkmale zu erfassen, die nicht standardmässig in der IFC-Spezifikation enthalten sind.
A131: 5.3 | B131: Merkmalsgruppen
B133: P | C133: Q
B134: Merkmalsgruppen | C134: Merkmalsgruppe (group of property)
...

Sheet Header
A1: Data Dictionary — Core Metadata
A2: Field | B2: Value | C2: Requirement | D2: Notes / Maps to
A3: IDENTIFICATION
A4: OrganizationCode | B4: KBOB | C4: user defined name (small or capital letters), max 7 chars | D4: Short org code — lowercase, max 7 chars, appears in all derived IRIs
A5: DictionaryCode | C5: SYSTEM-GENERATED | D5: Generated from DictionaryName (EN)
A6: DictionaryName (EN) | B6: KBOB FM Data Dictionary | C6: REQUIRED | D6: Required authoring title in English — source for DictionaryCode generation
A7: DictionaryName (DE) | B7: KBOB Datenkatalog FM | C7: OPTIONAL | D7: Core authoring title in German — minimal DCAT/i14y anchor
A8: DictionaryName (FR) | B8: Catalogue de données KBOB FM | C8: OPTIONAL | D8: Optional multilingual title support
A9: DictionaryName (IT)
A10: DictionaryVersion | B10: 0.3.0 | C10: REQUIRED | D10: Semantic versioning: MAJOR.MINOR.PATCH
A11: DictionaryUri | C11: SYSTEM-GENERATED | D11: Derived from OrganizationCode and DictionaryCode; canonical base pattern https://example.com/<OrganizationCode>/<DictionaryCode>
A13: GOVERNANCE
A14: LifecycleStatus | B14: Candidate | C14: REQUIRED | D14: Governance state used to derive i14y registration status
A16: LEGEND
A17: REQUIRED: | B17: Must be filled before validation/export
A18: OPTIONAL: | B18: Fill if available

Sheet Dictionary_public
A1: Data Dictionary — Additional Metadata
A2: Field | B2: Value | C2: Requirement | D2: Notes / Maps to
A3: GOVERNANCE / PUBLISHING
A4: Owner / Publisher | C4: REQUIRED WHEN USED | D4: dct:publisher / i14y publisher mapping
A5: ContactEmail | C5: REQUIRED WHEN USED | D5: dcat:contactPoint / i14y contact
A6: Description (DE) | C6: REQUIRED WHEN USED | D6: dct:description@de
A7: Description (FR) | C7: OPTIONAL | D7: dct:description@fr
A8: Description (EN) | C8: OPTIONAL | D8: dct:description@en
A9: PrimaryLanguage | C9: REQUIRED WHEN USED | D9: Primary metadata/content language
A10: MetadataLanguages | C10: OPTIONAL | D10: Additional metadata languages; delimited list allowed
A11: ReleaseDate | C11: OPTIONAL | D11: dct:issued — format YYYY-MM-DD
A12: ModifiedDate | C12: OPTIONAL
A13: QualityAssuranceProcedure | C13: OPTIONAL
A14: QualityAssuranceProcedureUrl | C14: OPTIONAL
A16: DISCOVERY / CATALOG METADATA
A17: Keywords (DE) | C17: OPTIONAL | D17: German keywords/tags — dcat:keyword@de
A18: Keywords (FR) | C18: OPTIONAL | D18: French keywords/tags — dcat:keyword@fr
A19: Keywords (EN) | C19: OPTIONAL | D19: English keywords/tags — dcat:keyword@en
A20: AccessRights | C20: OPTIONAL | D20: Access rights / visibility statement — dct:accessRights
A21: eCH_Theme | C21: OPTIONAL | D21: Swiss eCH thematic classification / topic category
A22: SpatialCoverage | C22: OPTIONAL | D22: Geographic scope or covered territory — dct:spatial
A23: TemporalCoverage | C23: OPTIONAL | D23: Covered time period / validity period — dct:temporal
A24: DocumentationURLs | C24: OPTIONAL | D24: Supporting documentation links; delimited list allowed
A25: RelatedResourceURLs | C25: OPTIONAL | D25: Related datasets/resources links — dct:relation
A26: ApplicableLegislation | C26: OPTIONAL | D26: Applicable legal basis / legislation references
A28: LICENSING
A29: License | C29: OPTIONAL | D29: Human-readable license name — dct:license
A30: LicenseUrl | C30: OPTIONAL | D30: Resolvable license URI/URL — dct:license
A32: TECHNICAL ENDPOINTS
A33: SPARQL_Endpoint | C33: OPTIONAL | D33: SPARQL endpoint URL for published graph access
A34: TTL_Download_URL | C34: OPTIONAL | D34: Download URL for Turtle/RDF serialization — dcat:distribution
A35: JSON_Download_URL | C35: OPTIONAL | D35: Download URL for JSON/JSON-LD serialization — dcat:distribution
A36: MoreInfoUrl | C36: OPTIONAL | D36: Landing page / homepage
A38: STANDARDS ALIGNMENT
A39: ConformsTo_ISO23386 | C39: OPTIONAL | D39: dct:conformsTo — property methodology
A40: ConformsTo_ISO12006_3 | C40: OPTIONAL
A41: ConformsTo_DCAT_AP_CH | C41: OPTIONAL
A42: VersionNotes (DE) | C42: OPTIONAL
A43: VersionNotes (FR) | C43: OPTIONAL
A44: VersionNotes (EN) | C44: OPTIONAL

Sheet Classes
A1: Filter | B1: Hinweise zur Handhabung | C1: Structural categorisation | D1: Domain/Domäne/Domaine/Dominio | E1: System/System/Système/Sistema | F1: Category/Kategorie/Catégorie/Categoria | G1: Classes | H1: GUID/URI | I1: Class-ID | J1: Class-Code | K1: Class-Assignment | L1: Klassen-Zuordnung (DE) | M1: Affectation de classe (FR) | N1: Assegnazione della classe (IT) | O1: Designation (EN) | P1: Bezeichnung (DE) | Q1: Désignation (FR) | R1: Designazione (IT) | S1: Description (EN) | T1: Beschreibung (DE) | U1: Description (FR) | V1: Descrizione (IT) | W1: IFC 4.3.2.0 (IFC4X3_ADD2) | X1: IFC_URI | Y1: IfcObject Entity | Z1: IfcTypeObject Entity | AA1: PredefinedType | AB1: ObjectType | AC1: RDS | AD1: Governance | AE1: Status | AF1: Version date | AG1: Provenance (PROV) | AH1: RelatedDocuments | AI1: RelatedDocumentName (EN)
B2: Erforderlich für Excel
B3: Sprachen
B4: Referenziert / System generiert | D4: multilingual | E4: multilingual | F4: multilingual | H4: multilingual | I4: multilingual | J4: multilingual | K4: multilingual | L4: DE | M4: FR | N4: IT | O4: EN | P4: DE | Q4: FR | R4: IT | S4: EN | T4: DE | U4: FR | V4: IT | X4: multilingual | Y4: multilingual | Z4: multilingual | AA4: multilingual | AB4: multilingual | AC4: multilingual | AE4: multilingual | AF4: multilingual | AG4: multilingual | AI4: multilingual
B5: Dropdown Liste | H5: referenced | I5: system-generated | L5: system-generated | M5: system-generated | N5: system-generated | X5: referenced | Y5: referenced | Z5: referenced | AA5: referenced | AB5: referenced | AC5: referenced | AE5: referenced | AF5: referenced | AG5: referenced | AI5: referenced
B6: Validierung | K6: Rules.Class-Assignment | L6: Rules.Klassen-Zuordnung | M6: Rules.Affectation de classe | N6: Rules.Assegnazione della classe | AE6: Rules.Status
H7: https://www.kbob.admin.ch/class/grundstuck | J7: grundstuck | K7: Spatial structure | L7: =IFERROR(INDEX(Rules!$B:$B,MATCH(K8,Rules!$A:$A,0)),"") -> Räumliche Struktur | M7: =IFERROR(INDEX(Rules!$C:$C,MATCH(K8,Rules!$A:$A,0)),"") -> Structure spatiale | N7: =IFERROR(INDEX(Rules!$D:$D,MATCH(K8,Rules!$A:$A,0)),"") -> Struttura spaziale | O7: Site | P7: Grundstück | S7: KBOB FM object class for a site as a spatial unit of a developed or undeveloped plot. | T7: KBOB-FM-Objektklasse für ein Grundstück als räumliche Einheit des bebauten oder unbebauten Areals. | X7: https://identifier.buildingsmart.org/uri/buildingsmart/ifc/4.3/class/IfcSite | Y7: IfcSite | Z7: IfcSite | AE7: Candidate | AF7: 2026-06-30T12:00:00Z | AG7: KBOB | AI7: KBOB DK FM_i14y.csv
H8: https://www.kbob.admin.ch/class/gebaude | J8: gebaude | K8: Spatial structure | L8: =IFERROR(INDEX(Rules!$B:$B,MATCH(K9,Rules!$A:$A,0)),"") -> Räumliche Struktur | M8: =IFERROR(INDEX(Rules!$C:$C,MATCH(K9,Rules!$A:$A,0)),"") -> Structure spatiale | N8: =IFERROR(INDEX(Rules!$D:$D,MATCH(K9,Rules!$A:$A,0)),"") -> Struttura spaziale | O8: Building | P8: Gebäude | S8: KBOB FM object class for a building as an independent built asset. | T8: KBOB-FM-Objektklasse für ein Gebäude als eigenständiges Bauwerk. | X8: https://identifier.buildingsmart.org/uri/buildingsmart/ifc/4.3/class/IfcBuilding | Y8: IfcBuilding | Z8: IfcBuilding | AE8: Candidate | AF8: 2026-06-30T12:00:00Z | AG8: KBOB | AI8: KBOB DK FM_i14y.csv
H9: https://www.kbob.admin.ch/class/geschoss | J9: geschoss | K9: Spatial structure | L9: =IFERROR(INDEX(Rules!$B:$B,MATCH(K10,Rules!$A:$A,0)),"") -> Räumliche Struktur | M9: =IFERROR(INDEX(Rules!$C:$C,MATCH(K10,Rules!$A:$A,0)),"") -> Structure spatiale | N9: =IFERROR(INDEX(Rules!$D:$D,MATCH(K10,Rules!$A:$A,0)),"") -> Struttura spaziale | O9: Building storey | P9: Geschoss | S9: KBOB FM object class for a storey as a spatial level within a building. | T9: KBOB-FM-Objektklasse für ein Geschoss als räumliche Ebene innerhalb eines Gebäudes. | X9: https://identifier.buildingsmart.org/uri/buildingsmart/ifc/4.3/class/IfcBuildingStorey | Y9: IfcBuildingStorey | Z9: IfcBuildingStorey | AE9: Candidate | AF9: 2026-06-30T12:00:00Z | AG9: KBOB | AI9: KBOB DK FM_i14y.csv
H10: https://www.kbob.admin.ch/class/raum | J10: raum | K10: Spatial structure | L10: Räumliche Struktur | M10: Structure spatiale | N10: Struttura spaziale | O10: Room | P10: Raum | S10: KBOB FM object class for a room as a usable spatial unit within a storey. | T10: KBOB-FM-Objektklasse für einen Raum als nutzbare räumliche Einheit innerhalb eines Geschosses. | X10: https://identifier.buildingsmart.org/uri/buildingsmart/ifc/4.3/class/IfcSpace | Y10: IfcSpace | Z10: IfcSpace | AE10: Candidate | AF10: 2026-06-30T12:00:00Z | AG10: KBOB | AI10: KBOB DK FM_i14y.csv
H11: https://www.kbob.admin.ch/class/bauteil | J11: bauteil | K11: Physical elements | L11: Physische Bauteile | M11: Éléments physiques | N11: Elementi fisici | O11: Component | P11: Bauteil | S11: KBOB FM object class for a component as an identifiable element of a building or facility. | T11: KBOB-FM-Objektklasse für ein Bauteil als identifizierbares Element eines Bauwerks oder einer Anlage. | X11: https://identifier.buildingsmart.org/uri/buildingsmart/ifc/4.3/class/IfcElement | Y11: IfcElement | Z11: IfcElement | AE11: Candidate | AF11: 2026-06-30T12:00:00Z | AG11: KBOB | AI11: KBOB DK FM_i14y.csv
L12: =IFERROR(INDEX(Rules!$B:$B,MATCH(K13,Rules!$A:$A,0)),"") | M12: =IFERROR(INDEX(Rules!$C:$C,MATCH(K13,Rules!$A:$A,0)),"") | N12: =IFERROR(INDEX(Rules!$D:$D,MATCH(K13,Rules!$A:$A,0)),"")
L13: =IFERROR(INDEX(Rules!$B:$B,MATCH(K14,Rules!$A:$A,0)),"") | M13: =IFERROR(INDEX(Rules!$C:$C,MATCH(K14,Rules!$A:$A,0)),"") | N13: =IFERROR(INDEX(Rules!$D:$D,MATCH(K14,Rules!$A:$A,0)),"")
L14: =IFERROR(INDEX(Rules!$B:$B,MATCH(K15,Rules!$A:$A,0)),"") | M14: =IFERROR(INDEX(Rules!$C:$C,MATCH(K15,Rules!$A:$A,0)),"") | N14: =IFERROR(INDEX(Rules!$D:$D,MATCH(K15,Rules!$A:$A,0)),"")
L15: =IFERROR(INDEX(Rules!$B:$B,MATCH(K16,Rules!$A:$A,0)),"") | M15: =IFERROR(INDEX(Rules!$C:$C,MATCH(K16,Rules!$A:$A,0)),"") | N15: =IFERROR(INDEX(Rules!$D:$D,MATCH(K16,Rules!$A:$A,0)),"")
L16: =IFERROR(INDEX(Rules!$B:$B,MATCH(K17,Rules!$A:$A,0)),"") | M16: =IFERROR(INDEX(Rules!$C:$C,MATCH(K17,Rules!$A:$A,0)),"") | N16: =IFERROR(INDEX(Rules!$D:$D,MATCH(K17,Rules!$A:$A,0)),"")
L17: =IFERROR(INDEX(Rules!$B:$B,MATCH(K18,Rules!$A:$A,0)),"") | M17: =IFERROR(INDEX(Rules!$C:$C,MATCH(K18,Rules!$A:$A,0)),"") | N17: =IFERROR(INDEX(Rules!$D:$D,MATCH(K18,Rules!$A:$A,0)),"")
L18: =IFERROR(INDEX(Rules!$B:$B,MATCH(K19,Rules!$A:$A,0)),"") | M18: =IFERROR(INDEX(Rules!$C:$C,MATCH(K19,Rules!$A:$A,0)),"") | N18: =IFERROR(INDEX(Rules!$D:$D,MATCH(K19,Rules!$A:$A,0)),"")
L19: =IFERROR(INDEX(Rules!$B:$B,MATCH(K20,Rules!$A:$A,0)),"") | M19: =IFERROR(INDEX(Rules!$C:$C,MATCH(K20,Rules!$A:$A,0)),"") | N19: =IFERROR(INDEX(Rules!$D:$D,MATCH(K20,Rules!$A:$A,0)),"")
L20: =IFERROR(INDEX(Rules!$B:$B,MATCH(K21,Rules!$A:$A,0)),"") | M20: =IFERROR(INDEX(Rules!$C:$C,MATCH(K21,Rules!$A:$A,0)),"") | N20: =IFERROR(INDEX(Rules!$D:$D,MATCH(K21,Rules!$A:$A,0)),"")
L21: =IFERROR(INDEX(Rules!$B:$B,MATCH(K22,Rules!$A:$A,0)),"") | M21: =IFERROR(INDEX(Rules!$C:$C,MATCH(K22,Rules!$A:$A,0)),"") | N21: =IFERROR(INDEX(Rules!$D:$D,MATCH(K22,Rules!$A:$A,0)),"")
L22: =IFERROR(INDEX(Rules!$B:$B,MATCH(K23,Rules!$A:$A,0)),"") | M22: =IFERROR(INDEX(Rules!$C:$C,MATCH(K23,Rules!$A:$A,0)),"") | N22: =IFERROR(INDEX(Rules!$D:$D,MATCH(K23,Rules!$A:$A,0)),"")
L23: =IFERROR(INDEX(Rules!$B:$B,MATCH(K24,Rules!$A:$A,0)),"") | M23: =IFERROR(INDEX(Rules!$C:$C,MATCH(K24,Rules!$A:$A,0)),"") | N23: =IFERROR(INDEX(Rules!$D:$D,MATCH(K24,Rules!$A:$A,0)),"")
L24: =IFERROR(INDEX(Rules!$B:$B,MATCH(K25,Rules!$A:$A,0)),"") | M24: =IFERROR(INDEX(Rules!$C:$C,MATCH(K25,Rules!$A:$A,0)),"") | N24: =IFERROR(INDEX(Rules!$D:$D,MATCH(K25,Rules!$A:$A,0)),"")

Sheet Properties
A1: Filter | B1: Hinweise zur Handhabung | C1: Properties | D1: GUID/URI | E1: Property-ID | F1: Property-Code | G1: Property-Assignment | H1: Merkmals-Zuordnung (DE) | I1: Attribution de propriété (FR) | J1: Assegnazione della proprietà (IT) | K1: Designation (EN) | L1: Bezeichnung (DE) | M1: Désignation (FR) | N1: Designazione (IT) | O1: Description (EN) | P1: Beschreibung (DE) | Q1: Description (FR) | R1: Descrizione (IT) | S1: DataType (Base Type) | T1: DataType (IFC) | U1: EnumerationDesignation (EN) | V1: IFC 4.3.2.0 (IFC4X3_ADD2) | W1: IFC_URI | X1: IfcPropertySet (Pset) IfcQuantitySet (Qto) | Y1: Units/Einheit/Unité/Unità | Z1: QUDT URI | AA1: Unit Name (EN) | AB1: Einheit-Name (DE) | AC1: Nom de l’unité (FR) | AD1: Nome unità (IT) | AE1: Governance | AF1: Status | AG1: Version date | AH1: Provenance (PROV)
B2: Erforderlich für Excel | G2: yes
B3: Sprachen
B4: Referenziert / System generiert | D4: multilingual | E4: multilingual | F4: multilingual | H4: DE | I4: FR | J4: IT | K4: EN | L4: DE | M4: FR | N4: IT | O4: EN | P4: DE | Q4: FR | R4: IT | S4: multilingual | T4: multilingual | U4: multilingual | W4: multilingual | X4: multilingual | Y4: multilingual | Z4: multilingual | AA4: EN | AB4: DE | AC4: FR | AD4: IT | AF4: multilingual | AG4: multilingual | AH4: multilingual
B5: Dropdown Liste | D5: referenced | E5: system-generated | H5: system-generated | I5: system-generated | J5: system-generated | S5: referenced | T5: referenced | U5: referenced | W5: referenced | X5: referenced | Z5: referenced | AA5: system-generated | AB5: system-generated | AC5: system-generated | AD5: system-generated | AF5: referenced | AG5: referenced | AH5: referenced
B6: Validierung | G6: Rules.Property-Assignment | H6: Rules.Merkmals-Zuordnung | I6: Rules.Attribution de propriété | J6: Rules.Assegnazione della proprietà | S6: Rules.DataType | T6: Rules.IFC Data Type | AF6: Rules.Status
F7: guid | H7: =IFERROR(INDEX(Rules!$F:$F,MATCH(G8,Rules!$E:$E,0)),"") | I7: =IFERROR(INDEX(Rules!$G:$G,MATCH(G8,Rules!$E:$E,0)),"") | J7: =IFERROR(INDEX(Rules!$H:$H,MATCH(G8,Rules!$E:$E,0)),"") | K7: GUID | L7: GUID | O7: Property for uniquely identifying the object by means of a global unique identifier (GUID). | P7: Merkmal zur eindeutigen Identifikation des Objekts mittels Global Unique Identifier (GUID). | S7: STRING | T7: IfcLabel | W7: https://identifier.buildingsmart.org/uri/buildingsmart/ifc/4.3/prop/GlobalId | AF7: Candidate | AG7: 2026-07-31T12:00:00Z | AH7: KBOB
F8: grundstueck-id | H8: =IFERROR(INDEX(Rules!$F:$F,MATCH(G9,Rules!$E:$E,0)),"") | I8: =IFERROR(INDEX(Rules!$G:$G,MATCH(G9,Rules!$E:$E,0)),"") | J8: =IFERROR(INDEX(Rules!$H:$H,MATCH(G9,Rules!$E:$E,0)),"") | K8: Site ID | L8: Grundstück ID | O8: Property for uniquely identifying sites. | P8: Merkmal zur eindeutigen Identifikation von Grundstücken. | S8: STRING | T8: IfcLabel | W8: https://identifier.buildingsmart.org/uri/buildingsmart/ifc/4.3/prop/LandID | X8: https://identifier.buildingsmart.org/uri/buildingsmart/ifc/4.3/class/Pset_LandRegistration | AF8: Candidate | AG8: 2026-07-31T12:00:00Z | AH8: KBOB
F9: wirtschaftseinheit-id | H9: =IFERROR(INDEX(Rules!$F:$F,MATCH(G10,Rules!$E:$E,0)),"") | I9: =IFERROR(INDEX(Rules!$G:$G,MATCH(G10,Rules!$E:$E,0)),"") | J9: =IFERROR(INDEX(Rules!$H:$H,MATCH(G10,Rules!$E:$E,0)),"") | K9: Business unit ID | L9: Wirtschaftseinheit ID | O9: Property for uniquely identifying economic units. | P9: Merkmal zur eindeutigen Identifikation von Wirtschaftseinheiten. | S9: STRING | T9: IfcLabel | W9: https://identifier.buildingsmart.org/uri/buildingsmart/ifc/4.3/prop/LandTitleID | X9: https://identifier.buildingsmart.org/uri/buildingsmart/ifc/4.3/class/Pset_LandRegistration | AF9: Candidate | AG9: 2026-07-31T12:00:00Z | AH9: KBOB
F10: ort | H10: =IFERROR(INDEX(Rules!$F:$F,MATCH(G11,Rules!$E:$E,0)),"") | I10: =IFERROR(INDEX(Rules!$G:$G,MATCH(G11,Rules!$E:$E,0)),"") | J10: =IFERROR(INDEX(Rules!$H:$H,MATCH(G11,Rules!$E:$E,0)),"") | K10: City | L10: Ort | O10: Property for specifying the location. | P10: Merkmal zur Angabe von dem Ort. | S10: STRING | T10: IfcLabel | W10: https://identifier.buildingsmart.org/uri/buildingsmart/ifc/4.3/prop/Town | X10: https://identifier.buildingsmart.org/uri/buildingsmart/ifc/4.3/class/Pset_Address | AF10: Candidate | AG10: 2026-07-31T12:00:00Z | AH10: KBOB
F11: grundstueckbezeichnung | H11: =IFERROR(INDEX(Rules!$F:$F,MATCH(G12,Rules!$E:$E,0)),"") | I11: =IFERROR(INDEX(Rules!$G:$G,MATCH(G12,Rules!$E:$E,0)),"") | J11: =IFERROR(INDEX(Rules!$H:$H,MATCH(G12,Rules!$E:$E,0)),"") | K11: Site designation | L11: Grundstückbezeichnung | O11: Property for specifying the site designation. | P11: Merkmal zur Angabe von der Grundstückbezeichnung. | S11: STRING | T11: IfcLabel | W11: https://identifier.buildingsmart.org/uri/buildingsmart/ifc/4.3/prop/Name | AF11: Candidate | AG11: 2026-07-31T12:00:00Z | AH11: KBOB
F12: landeskurzel | H12: =IFERROR(INDEX(Rules!$F:$F,MATCH(G13,Rules!$E:$E,0)),"") | I12: =IFERROR(INDEX(Rules!$G:$G,MATCH(G13,Rules!$E:$E,0)),"") | J12: =IFERROR(INDEX(Rules!$H:$H,MATCH(G13,Rules!$E:$E,0)),"") | K12: Country code | L12: Landeskürzel | O12: Property for specifying the country code. | P12: Merkmal zur Angabe von dem Landeskürzel. | S12: STRING | T12: IfcLabel | W12: https://identifier.buildingsmart.org/uri/buildingsmart/ifc/4.3/prop/Country | X12: https://identifier.buildingsmart.org/uri/buildingsmart/ifc/4.3/class/Pset_Address | AF12: Candidate | AG12: 2026-07-31T12:00:00Z | AH12: KBOB
F13: kanton | H13: =IFERROR(INDEX(Rules!$F:$F,MATCH(G14,Rules!$E:$E,0)),"") | I13: =IFERROR(INDEX(Rules!$G:$G,MATCH(G14,Rules!$E:$E,0)),"") | J13: =IFERROR(INDEX(Rules!$H:$H,MATCH(G14,Rules!$E:$E,0)),"") | K13: Canton | L13: Kanton | O13: Property for specifying the canton. | P13: Merkmal zur Angabe von dem Kanton. | S13: STRING | T13: IfcLabel | W13: https://identifier.buildingsmart.org/uri/buildingsmart/ifc/4.3/prop/Region | X13: https://identifier.buildingsmart.org/uri/buildingsmart/ifc/4.3/class/Pset_Address | AF13: Candidate | AG13: 2026-07-31T12:00:00Z | AH13: KBOB
F14: postleitzahl | H14: =IFERROR(INDEX(Rules!$F:$F,MATCH(G15,Rules!$E:$E,0)),"") | I14: =IFERROR(INDEX(Rules!$G:$G,MATCH(G15,Rules!$E:$E,0)),"") | J14: =IFERROR(INDEX(Rules!$H:$H,MATCH(G15,Rules!$E:$E,0)),"") | K14: Postcode | L14: Postleitzahl | O14: Property for specifying the postcode. | P14: Merkmal zur Angabe von der Postleitzahl. | S14: INTEGER | T14: IfcInteger | W14: https://identifier.buildingsmart.org/uri/buildingsmart/ifc/4.3/prop/PostalCode | X14: https://identifier.buildingsmart.org/uri/buildingsmart/ifc/4.3/class/Pset_Address | AF14: Candidate | AG14: 2026-07-31T12:00:00Z | AH14: KBOB
F15: politische-gemeinde | H15: =IFERROR(INDEX(Rules!$F:$F,MATCH(G16,Rules!$E:$E,0)),"") | I15: =IFERROR(INDEX(Rules!$G:$G,MATCH(G16,Rules!$E:$E,0)),"") | J15: =IFERROR(INDEX(Rules!$H:$H,MATCH(G16,Rules!$E:$E,0)),"") | K15: Political municipality | L15: Politische Gemeinde | O15: Property for specifying the political municipality | P15: Merkmal zur Angabe von der politischen Gemeinde. | S15: STRING | T15: IfcLabel | X15: https://identifier.buildingsmart.org/uri/buildingsmart/ifc/4.3/class/Pset_Address | AF15: Candidate | AG15: 2026-07-31T12:00:00Z | AH15: KBOB
F16: gis-parzellennummer | H16: =IFERROR(INDEX(Rules!$F:$F,MATCH(G17,Rules!$E:$E,0)),"") | I16: =IFERROR(INDEX(Rules!$G:$G,MATCH(G17,Rules!$E:$E,0)),"") | J16: =IFERROR(INDEX(Rules!$H:$H,MATCH(G17,Rules!$E:$E,0)),"") | K16: GIS parcel number | L16: GIS-Parzellennummer | O16: Property for specifying the GIS parcel number. | P16: Merkmal zur Angabe von der GIS-Parzellennummer. | S16: STRING | T16: IfcLabel | X16: https://identifier.buildingsmart.org/uri/buildingsmart/ifc/4.3/class/Pset_LandRegistration | AF16: Candidate | AG16: 2026-07-31T12:00:00Z | AH16: KBOB
F17: grundstucksflache | H17: =IFERROR(INDEX(Rules!$F:$F,MATCH(G19,Rules!$E:$E,0)),"") | I17: =IFERROR(INDEX(Rules!$G:$G,MATCH(G19,Rules!$E:$E,0)),"") | J17: =IFERROR(INDEX(Rules!$H:$H,MATCH(G19,Rules!$E:$E,0)),"") | K17: Site area | L17: Grundstücksfläche | O17: Property for specifying the site area. | P17: Merkmal zur Angabe der Grundstücksfläche. | S17: REAL | T17: IfcAreaMeasure | W17: https://identifier.buildingsmart.org/uri/buildingsmart/ifc/4.3/prop/GrossArea | X17: https://identifier.buildingsmart.org/uri/buildingsmart/ifc/4.3/class/Qto_SiteBaseQuantities | Y17: m² | Z17: http://qudt.org/vocab/unit/M2 | AF17: Candidate | AG17: 2026-07-31T12:00:00Z | AH17: KBOB
F18: eigentumer | H18: =IFERROR(INDEX(Rules!$F:$F,MATCH(G32,Rules!$E:$E,0)),"") | I18: =IFERROR(INDEX(Rules!$G:$G,MATCH(G32,Rules!$E:$E,0)),"") | J18: =IFERROR(INDEX(Rules!$H:$H,MATCH(G32,Rules!$E:$E,0)),"") | K18: Owner | L18: Eigentümer | O18: Property for specifying the owner. | P18: Merkmal zur Angabe von dem Eigentümer. | S18: STRING | T18: IfcLabel | W18: https://identifier.buildingsmart.org/uri/buildingsmart/ifc/4.3/class/IfcOccupantOWNER | X18: https://identifier.buildingsmart.org/uri/buildingsmart/ifc/4.3/class/Pset_Address | AF18: Candidate | AG18: 2026-07-31T12:00:00Z | AH18: KBOB
F19: dienstbarkeiten-id | H19: =IFERROR(INDEX(Rules!$F:$F,MATCH(G20,Rules!$E:$E,0)),"") | I19: =IFERROR(INDEX(Rules!$G:$G,MATCH(G20,Rules!$E:$E,0)),"") | J19: =IFERROR(INDEX(Rules!$H:$H,MATCH(G20,Rules!$E:$E,0)),"") | K19: Easement ID | L19: Dienstbarkeiten ID | O19: Property for uniquely identifying easements. | P19: Merkmal zur eindeutigen Identifikation von Dienstbarkeiten. | S19: STRING | T19: IfcLabel | X19: https://identifier.buildingsmart.org/uri/buildingsmart/ifc/4.3/class/Pset_LandRegistration | AF19: Candidate | AG19: 2026-07-31T12:00:00Z | AH19: KBOB
F20: dienstbarkeitenname | H20: =IFERROR(INDEX(Rules!$F:$F,MATCH(G21,Rules!$E:$E,0)),"") | I20: =IFERROR(INDEX(Rules!$G:$G,MATCH(G21,Rules!$E:$E,0)),"") | J20: =IFERROR(INDEX(Rules!$H:$H,MATCH(G21,Rules!$E:$E,0)),"") | K20: Easement name | L20: Dienstbarkeitenname | O20: Property for specifying the easement name. | P20: Merkmal zur Angabe von dem Namen der Dienstbarkeit. | S20: STRING | T20: IfcLabel | X20: https://identifier.buildingsmart.org/uri/buildingsmart/ifc/4.3/class/Pset_LandRegistration | AF20: Candidate | AG20: 2026-07-31T12:00:00Z | AH20: KBOB
F21: gebaude-id | H21: =IFERROR(INDEX(Rules!$F:$F,MATCH(G22,Rules!$E:$E,0)),"") | I21: =IFERROR(INDEX(Rules!$G:$G,MATCH(G22,Rules!$E:$E,0)),"") | J21: =IFERROR(INDEX(Rules!$H:$H,MATCH(G22,Rules!$E:$E,0)),"") | K21: Building ID | L21: Gebäude ID | O21: Property for uniquely identifying the building. | P21: Merkmal zur eindeutigen Identifikation des Gebäudes. | S21: STRING | T21: IfcLabel | W21: https://identifier.buildingsmart.org/uri/buildingsmart/ifc/4.3/prop/BuildingID | X21: https://identifier.buildingsmart.org/uri/buildingsmart/ifc/4.3/class/Pset_BuildingCommon | AF21: Candidate | AG21: 2026-07-31T12:00:00Z | AH21: KBOB
F22: objekt-id | H22: =IFERROR(INDEX(Rules!$F:$F,MATCH(G23,Rules!$E:$E,0)),"") | I22: =IFERROR(INDEX(Rules!$G:$G,MATCH(G23,Rules!$E:$E,0)),"") | J22: =IFERROR(INDEX(Rules!$H:$H,MATCH(G23,Rules!$E:$E,0)),"") | K22: Property ID | L22: Objekt ID | O22: Property for uniquely identifying the property. | P22: Merkmal zur eindeutigen Identifikation von Objekten. | S22: STRING | T22: IfcLabel | W22: https://identifier.buildingsmart.org/uri/buildingsmart/ifc/4.3/prop/BuildingID | X22: https://identifier.buildingsmart.org/uri/buildingsmart/ifc/4.3/class/Pset_BuildingCommon | AF22: Candidate | AG22: 2026-07-31T12:00:00Z | AH22: KBOB
F23: gebaudebezeichnung | H23: =IFERROR(INDEX(Rules!$F:$F,MATCH(G24,Rules!$E:$E,0)),"") | I23: =IFERROR(INDEX(Rules!$G:$G,MATCH(G24,Rules!$E:$E,0)),"") | J23: =IFERROR(INDEX(Rules!$H:$H,MATCH(G24,Rules!$E:$E,0)),"") | K23: Building designation | L23: Gebäudebezeichnung | O23: Property for specifying the building designation. | P23: Merkmal zur Angabe von der Gebäudebezeichnung. | S23: STRING | T23: IfcLabel | W23: https://identifier.buildingsmart.org/uri/buildingsmart/ifc/4.3/prop/Name | AF23: Candidate | AG23: 2026-07-31T12:00:00Z | AH23: KBOB
F24: objekttyp | H24: =IFERROR(INDEX(Rules!$F:$F,MATCH(G25,Rules!$E:$E,0)),"") | I24: =IFERROR(INDEX(Rules!$G:$G,MATCH(G25,Rules!$E:$E,0)),"") | J24: =IFERROR(INDEX(Rules!$H:$H,MATCH(G25,Rules!$E:$E,0)),"") | K24: Property type | L24: Objekttyp | O24: Property for specifying the property type. | P24: Merkmal zur Angabe von dem Objekttyp. | S24: STRING | T24: IfcLabel | AF24: Candidate | AG24: 2026-07-31T12:00:00Z | AH24: KBOB
F25: strasse-hausnummer | H25: =IFERROR(INDEX(Rules!$F:$F,MATCH(G26,Rules!$E:$E,0)),"") | I25: =IFERROR(INDEX(Rules!$G:$G,MATCH(G26,Rules!$E:$E,0)),"") | J25: =IFERROR(INDEX(Rules!$H:$H,MATCH(G26,Rules!$E:$E,0)),"") | K25: Address line | L25: Strasse Hausnummer | O25: Property for specifying the address line. | P25: Merkmal zur Angabe von Strasse und Hausnummer. | S25: STRING | T25: IfcLabel | W25: https://identifier.buildingsmart.org/uri/buildingsmart/ifc/4.3/prop/AddressLines | X25: https://identifier.buildingsmart.org/uri/buildingsmart/ifc/4.3/class/Pset_Address | AF25: Candidate | AG25: 2026-07-31T12:00:00Z | AH25: KBOB
F26: gefahrdungsstufe | H26: =IFERROR(INDEX(Rules!$F:$F,MATCH(G27,Rules!$E:$E,0)),"") | I26: =IFERROR(INDEX(Rules!$G:$G,MATCH(G27,Rules!$E:$E,0)),"") | J26: =IFERROR(INDEX(Rules!$H:$H,MATCH(G27,Rules!$E:$E,0)),"") | K26: Hazard level | L26: Gefährdungsstufe | O26: Property for specifying the hazard level. | P26: Merkmal zur Angabe von der Gefährdungsstufe. | S26: STRING | T26: IfcLabel | W26: https://identifier.buildingsmart.org/uri/buildingsmart/ifc/4.3/prop/RiskType | X26: https://identifier.buildingsmart.org/uri/buildingsmart/ifc/4.3/class/Pset_Risk | AF26: Candidate | AG26: 2026-07-31T12:00:00Z | AH26: KBOB
F27: kostentrager | H27: =IFERROR(INDEX(Rules!$F:$F,MATCH(#REF!,Rules!$E:$E,0)),"") | I27: =IFERROR(INDEX(Rules!$G:$G,MATCH(#REF!,Rules!$E:$E,0)),"") | J27: =IFERROR(INDEX(Rules!$H:$H,MATCH(#REF!,Rules!$E:$E,0)),"") | K27: Cost centre | L27: Kostenträger | O27: Property for specifying the cost centre. | P27: Merkmal zur Angabe von dem Kostenträger. | S27: STRING | T27: IfcLabel | AF27: Candidate | AG27: 2026-07-31T12:00:00Z | AH27: KBOB
F28: gebaudegrundflache | H28: =IFERROR(INDEX(Rules!$F:$F,MATCH(G29,Rules!$E:$E,0)),"") | I28: =IFERROR(INDEX(Rules!$G:$G,MATCH(G29,Rules!$E:$E,0)),"") | J28: =IFERROR(INDEX(Rules!$H:$H,MATCH(G29,Rules!$E:$E,0)),"") | K28: Building footprint area | L28: Gebäudegrundfläche | O28: Property for specifying the building footprint area. | P28: Merkmal zur Angabe der Gebäudegrundfläche. | S28: REAL | T28: IfcAreaMeasure | W28: https://identifier.buildingsmart.org/uri/buildingsmart/ifc/4.3/prop/GrossFloorArea | X28: https://identifier.buildingsmart.org/uri/buildingsmart/ifc/4.3/class/Qto_BuildingBaseQuantities | Y28: m² | Z28: http://qudt.org/vocab/unit/M2 | AF28: Candidate | AG28: 2026-07-31T12:00:00Z | AH28: KBOB
F29: gebaudevolumen | H29: =IFERROR(INDEX(Rules!$F:$F,MATCH(G30,Rules!$E:$E,0)),"") | I29: =IFERROR(INDEX(Rules!$G:$G,MATCH(G30,Rules!$E:$E,0)),"") | J29: =IFERROR(INDEX(Rules!$H:$H,MATCH(G30,Rules!$E:$E,0)),"") | K29: Gross building volume | L29: Gebäudevolumen | O29: Property for specifying the the gross building volume. | P29: Merkmal zur Angabe der dem Gebäudevolumen. | S29: REAL | T29: IfcReal | W29: https://identifier.buildingsmart.org/uri/buildingsmart/ifc/4.3/prop/GrossVolume | X29: https://identifier.buildingsmart.org/uri/buildingsmart/ifc/4.3/class/Qto_BodyGeometryValidation | Y29: m³ | Z29: http://qudt.org/vocab/unit/M3 | AF29: Candidate | AG29: 2026-07-31T12:00:00Z | AH29: KBOB
F30: nummer-gebaudeversicherung | H30: =IFERROR(INDEX(Rules!$F:$F,MATCH(G31,Rules!$E:$E,0)),"") | I30: =IFERROR(INDEX(Rules!$G:$G,MATCH(G31,Rules!$E:$E,0)),"") | J30: =IFERROR(INDEX(Rules!$H:$H,MATCH(G31,Rules!$E:$E,0)),"") | K30: Building insurance reference | L30: Nummer Gebäudeversicherung | O30: Property for specifying the building insurance reference. | P30: Merkmal zur Angabe von der Nummer der Gebäudeversicherung. | S30: STRING | T30: IfcLabel | W30: https://identifier.buildingsmart.org/uri/buildingsmart/ifc/4.3/prop/AssetInsuranceType | X30: https://identifier.buildingsmart.org/uri/buildingsmart/ifc/4.3/class/Pset_Asset | AF30: Candidate | AG30: 2026-07-31T12:00:00Z | AH30: KBOB
F31: baujahr | H31: =IFERROR(INDEX(Rules!$F:$F,MATCH(G18,Rules!$E:$E,0)),"") | I31: =IFERROR(INDEX(Rules!$G:$G,MATCH(G18,Rules!$E:$E,0)),"") | J31: =IFERROR(INDEX(Rules!$H:$H,MATCH(G18,Rules!$E:$E,0)),"") | K31: Year of construction | L31: Baujahr | O31: Property for specifying the year of construction. | P31: Merkmal zur Angabe von dem Baujahr. | S31: INTEGER | T31: IfcInteger | W31: https://identifier.buildingsmart.org/uri/buildingsmart/ifc/4.3/prop/YearOfConstruction | X31: https://identifier.buildingsmart.org/uri/buildingsmart/ifc/4.3/class/Pset_BuildingCommon | AF31: Candidate | AG31: 2026-07-31T12:00:00Z | AH31: KBOB
F32: medienbezug-elektrisch | H32: =IFERROR(INDEX(Rules!$F:$F,MATCH(G33,Rules!$E:$E,0)),"") | I32: =IFERROR(INDEX(Rules!$G:$G,MATCH(G33,Rules!$E:$E,0)),"") | J32: =IFERROR(INDEX(Rules!$H:$H,MATCH(G33,Rules!$E:$E,0)),"") | K32: Electricity supply connection | L32: Medienbezug Elektrisch | O32: Property for specifying the electrical supply connection. | P32: Merkmal zur Angabe von dem elektrischen Medienbezug. | S32: BOOLEAN | T32: IfcLabel | AF32: Candidate | AG32: 2026-07-31T12:00:00Z | AH32: KBOB
F33: medienbezug-wasser | H33: =IFERROR(INDEX(Rules!$F:$F,MATCH(G34,Rules!$E:$E,0)),"") | I33: =IFERROR(INDEX(Rules!$G:$G,MATCH(G34,Rules!$E:$E,0)),"") | J33: =IFERROR(INDEX(Rules!$H:$H,MATCH(G34,Rules!$E:$E,0)),"") | K33: Water supply connection | L33: Medienbezug Wasser | O33: Property for specifying the water supply connection. | P33: Merkmal zur Angabe von dem Wasserbezug. | S33: BOOLEAN | T33: IfcLabel | AF33: Candidate | AG33: 2026-07-31T12:00:00Z | AH33: KBOB
F34: medienbezug-heizwaerme | H34: =IFERROR(INDEX(Rules!$F:$F,MATCH(G35,Rules!$E:$E,0)),"") | I34: =IFERROR(INDEX(Rules!$G:$G,MATCH(G35,Rules!$E:$E,0)),"") | J34: =IFERROR(INDEX(Rules!$H:$H,MATCH(G35,Rules!$E:$E,0)),"") | K34: Heating supply connection | L34: Medienbezug Heizwärme | O34: Property for specifying the heating supply connection. | P34: Merkmal zur Angabe von dem Heizungsbezug. | S34: BOOLEAN | T34: IfcLabel | AF34: Candidate | AG34: 2026-07-31T12:00:00Z | AH34: KBOB
F35: nutzungsart-aussen | H35: =IFERROR(INDEX(Rules!$F:$F,MATCH(G36,Rules!$E:$E,0)),"") | I35: =IFERROR(INDEX(Rules!$G:$G,MATCH(G36,Rules!$E:$E,0)),"") | J35: =IFERROR(INDEX(Rules!$H:$H,MATCH(G36,Rules!$E:$E,0)),"") | K35: External area use | L35: Nutzungsart aussen | O35: Property for specifying the external area use. | P35: Merkmal zur Angabe von der Nutzungsart im Aussenbereich. | S35: STRING | T35: IfcLabel | W35: https://identifier.buildingsmart.org/uri/buildingsmart/ifc/4.3/prop/MarketCategory | X35: https://identifier.buildingsmart.org/uri/buildingsmart/ifc/4.3/class/Pset_BuildingUse | AF35: Candidate | AG35: 2026-07-31T12:00:00Z | AH35: KBOB
F36: gebaudeklasse | H36: =IFERROR(INDEX(Rules!$F:$F,MATCH(G37,Rules!$E:$E,0)),"") | I36: =IFERROR(INDEX(Rules!$G:$G,MATCH(G37,Rules!$E:$E,0)),"") | J36: =IFERROR(INDEX(Rules!$H:$H,MATCH(G37,Rules!$E:$E,0)),"") | K36: Building use class | L36: Gebäudeklasse | O36: Property for specifying the building use class. | P36: Merkmal zur Angabe von der Gebäudeklasse. | S36: STRING | T36: IfcLabel | W36: https://identifier.buildingsmart.org/uri/buildingsmart/ifc/4.3/prop/OccupancyType | X36: https://identifier.buildingsmart.org/uri/buildingsmart/ifc/4.3/class/Pset_SpaceOccupancyRequirements | AF36: Candidate | AG36: 2026-07-31T12:00:00Z | AH36: KBOB
F37: gebaudelabel | H37: =IFERROR(INDEX(Rules!$F:$F,MATCH(#REF!,Rules!$E:$E,0)),"") | I37: =IFERROR(INDEX(Rules!$G:$G,MATCH(#REF!,Rules!$E:$E,0)),"") | J37: =IFERROR(INDEX(Rules!$H:$H,MATCH(#REF!,Rules!$E:$E,0)),"") | K37: Building label | L37: Gebäudelabel | O37: Property for specifying the building label. | P37: Merkmal zur Angabe von dem Gebäudelabel. | S37: STRING | T37: IfcLabel | AF37: Candidate | AG37: 2026-07-31T12:00:00Z | AH37: KBOB
F38: denkmalstatus | H38: =IFERROR(INDEX(Rules!$F:$F,MATCH(G39,Rules!$E:$E,0)),"") | I38: =IFERROR(INDEX(Rules!$G:$G,MATCH(G39,Rules!$E:$E,0)),"") | J38: =IFERROR(INDEX(Rules!$H:$H,MATCH(G39,Rules!$E:$E,0)),"") | K38: Heritage status | L38: Denkmalstatus | O38: Property for specifying the heritage status. | P38: Merkmal zur Angabe von dem Denkmalstatus. | S38: BOOLEAN | T38: IfcBoolean | W38: https://identifier.buildingsmart.org/uri/buildingsmart/ifc/4.3/prop/IsLandmarked | X38: https://identifier.buildingsmart.org/uri/buildingsmart/ifc/4.3/class/Pset_BuildingCommon | AF38: Candidate | AG38: 2026-07-31T12:00:00Z | AH38: KBOB
F39: erdbebenbauwerksklasse | H39: =IFERROR(INDEX(Rules!$F:$F,MATCH(G40,Rules!$E:$E,0)),"") | I39: =IFERROR(INDEX(Rules!$G:$G,MATCH(G40,Rules!$E:$E,0)),"") | J39: =IFERROR(INDEX(Rules!$H:$H,MATCH(G40,Rules!$E:$E,0)),"") | K39: Seismic risk class | L39: Erdbebenbauwerksklasse | O39: Property for specifying the seismic risk class. | P39: Merkmal zur Angabe von der Erdbebenbauwerksklasse. | S39: STRING | T39: IfcLabel | X39: https://identifier.buildingsmart.org/uri/buildingsmart/ifc/4.3/class/Pset_EnvironmentalCondition | AF39: Candidate | AG39: 2026-07-31T12:00:00Z | AH39: KBOB
F40: schutzzone | H40: =IFERROR(INDEX(Rules!$F:$F,MATCH(G41,Rules!$E:$E,0)),"") | I40: =IFERROR(INDEX(Rules!$G:$G,MATCH(G41,Rules!$E:$E,0)),"") | J40: =IFERROR(INDEX(Rules!$H:$H,MATCH(G41,Rules!$E:$E,0)),"") | K40: Protection zone | L40: Schutzzone | O40: Property for specifying the protection zone. | P40: Merkmal zur Angabe von der Schutzzone. | S40: BOOLEAN | T40: IfcBoolean | X40: https://identifier.buildingsmart.org/uri/buildingsmart/ifc/4.3/class/Pset_SpatialZoneCommon | AF40: Candidate | AG40: 2026-07-31T12:00:00Z | AH40: KBOB
F41: umgebungsflache-id | H41: =IFERROR(INDEX(Rules!$F:$F,MATCH(G42,Rules!$E:$E,0)),"") | I41: =IFERROR(INDEX(Rules!$G:$G,MATCH(G42,Rules!$E:$E,0)),"") | J41: =IFERROR(INDEX(Rules!$H:$H,MATCH(G42,Rules!$E:$E,0)),"") | K41: Surrounding area ID | L41: Umgebungsfläche ID | O41: Property for uniquely identifying external area. | P41: Merkmal zur eindeutigen Identifikation von Umgebungsflächen. | S41: STRING | T41: IfcLabel | W41: https://identifier.buildingsmart.org/uri/buildingsmart/ifc/4.3/prop/LandID | X41: https://identifier.buildingsmart.org/uri/buildingsmart/ifc/4.3/class/Pset_LandRegistration | AF41: Candidate | AG41: 2026-07-31T12:00:00Z | AH41: KBOB
F42: umgebungsflachennummer | H42: =IFERROR(INDEX(Rules!$F:$F,MATCH(G43,Rules!$E:$E,0)),"") | I42: =IFERROR(INDEX(Rules!$G:$G,MATCH(G43,Rules!$E:$E,0)),"") | J42: =IFERROR(INDEX(Rules!$H:$H,MATCH(G43,Rules!$E:$E,0)),"") | K42: Surrounding area number | L42: Umgebungsflächennummer | O42: Property for specifying the external area number. | P42: Merkmal zur Angabe von der Umgebungsflächennummer. | S42: STRING | T42: IfcLabel | W42: https://identifier.buildingsmart.org/uri/buildingsmart/ifc/4.3/prop/LandID | X42: https://identifier.buildingsmart.org/uri/buildingsmart/ifc/4.3/class/Pset_LandRegistration | AF42: Candidate | AG42: 2026-07-31T12:00:00Z | AH42: KBOB
F43: geschoss-id | H43: =IFERROR(INDEX(Rules!$F:$F,MATCH(G44,Rules!$E:$E,0)),"") | I43: =IFERROR(INDEX(Rules!$G:$G,MATCH(G44,Rules!$E:$E,0)),"") | J43: =IFERROR(INDEX(Rules!$H:$H,MATCH(G44,Rules!$E:$E,0)),"") | K43: Building storey ID | L43: Geschoss ID | O43: Property for uniquely identifying storeys. | P43: Merkmal zur eindeutigen Identifikation von Geschossen. | S43: STRING | T43: IfcLabel | AF43: Candidate | AG43: 2026-07-31T12:00:00Z | AH43: KBOB
F44: geschossbezeichnung | H44: =IFERROR(INDEX(Rules!$F:$F,MATCH(G45,Rules!$E:$E,0)),"") | I44: =IFERROR(INDEX(Rules!$G:$G,MATCH(G45,Rules!$E:$E,0)),"") | J44: =IFERROR(INDEX(Rules!$H:$H,MATCH(G45,Rules!$E:$E,0)),"") | K44: Building storey designation | L44: Geschossbezeichnung | O44: Property for specifying the storey designation. | P44: Merkmal zur Angabe von der Geschossbezeichnung. | S44: STRING | T44: IfcLabel | W44: https://identifier.buildingsmart.org/uri/buildingsmart/ifc/4.3/prop/Name | AF44: Candidate | AG44: 2026-07-31T12:00:00Z | AH44: KBOB
F45: geschossvolumen | H45: =IFERROR(INDEX(Rules!$F:$F,MATCH(G46,Rules!$E:$E,0)),"") | I45: =IFERROR(INDEX(Rules!$G:$G,MATCH(G46,Rules!$E:$E,0)),"") | J45: =IFERROR(INDEX(Rules!$H:$H,MATCH(G46,Rules!$E:$E,0)),"") | K45: Building storey volume | L45: Geschossvolumen | O45: Property for specifying the the storey volume. | P45: Merkmal zur Angabe der dem Geschossvolumen. | S45: REAL | T45: IfcVolumeMeasure | W45: https://identifier.buildingsmart.org/uri/buildingsmart/ifc/4.3/prop/GrossVolume | X45: https://identifier.buildingsmart.org/uri/buildingsmart/ifc/4.3/class/Qto_BodyGeometryValidation | Y45: m³ | Z45: http://qudt.org/vocab/unit/M3 | AF45: Candidate | AG45: 2026-07-31T12:00:00Z | AH45: KBOB
F46: geschosshohe | H46: =IFERROR(INDEX(Rules!$F:$F,MATCH(G47,Rules!$E:$E,0)),"") | I46: =IFERROR(INDEX(Rules!$G:$G,MATCH(G47,Rules!$E:$E,0)),"") | J46: =IFERROR(INDEX(Rules!$H:$H,MATCH(G47,Rules!$E:$E,0)),"") | K46: Building storey height | L46: Geschosshöhe | O46: Property for specifying the the storey height. | P46: Merkmal zur Angabe der der Geschosshöhe. | S46: REAL | T46: IfcLengthMeasure | W46: https://identifier.buildingsmart.org/uri/buildingsmart/ifc/4.3/prop/NetHeight | X46: https://identifier.buildingsmart.org/uri/buildingsmart/ifc/4.3/class/Qto_BuildingStoreyBaseQuantities | Y46: m | AF46: Candidate | AG46: 2026-07-31T12:00:00Z | AH46: KBOB
F47: geschossflache | H47: =IFERROR(INDEX(Rules!$F:$F,MATCH(G48,Rules!$E:$E,0)),"") | I47: =IFERROR(INDEX(Rules!$G:$G,MATCH(G48,Rules!$E:$E,0)),"") | J47: =IFERROR(INDEX(Rules!$H:$H,MATCH(G48,Rules!$E:$E,0)),"") | K47: Building storey area | L47: Geschossfläche | O47: Property for specifying the the storey area. | P47: Merkmal zur Angabe der der Geschossfläche. | S47: REAL | T47: IfcAreaMeasure | W47: https://identifier.buildingsmart.org/uri/buildingsmart/ifc/4.3/prop/GrossFloorArea | X47: https://identifier.buildingsmart.org/uri/buildingsmart/ifc/4.3/class/Qto_BuildingStoreyBaseQuantities | Y47: m² | Z47: http://qudt.org/vocab/unit/M2 | AF47: Candidate | AG47: 2026-07-31T12:00:00Z | AH47: KBOB
F48: aussengeschossflache | H48: =IFERROR(INDEX(Rules!$F:$F,MATCH(#REF!,Rules!$E:$E,0)),"") | I48: =IFERROR(INDEX(Rules!$G:$G,MATCH(#REF!,Rules!$E:$E,0)),"") | J48: =IFERROR(INDEX(Rules!$H:$H,MATCH(#REF!,Rules!$E:$E,0)),"") | K48: External building storey area | L48: Aussengeschossfläche | O48: Property for specifying the the external storey area. | P48: Merkmal zur Angabe der der Aussengeschossfläche. | S48: REAL | T48: IfcAreaMeasure | W48: https://identifier.buildingsmart.org/uri/buildingsmart/ifc/4.3/prop/GrossFloorArea | X48: https://identifier.buildingsmart.org/uri/buildingsmart/ifc/4.3/class/Qto_BuildingStoreyBaseQuantities | Y48: m² | Z48: http://qudt.org/vocab/unit/M2 | AF48: Candidate | AG48: 2026-07-31T12:00:00Z | AH48: KBOB
F49: oberirdisch | H49: =IFERROR(INDEX(Rules!$F:$F,MATCH(G50,Rules!$E:$E,0)),"") | I49: =IFERROR(INDEX(Rules!$G:$G,MATCH(G50,Rules!$E:$E,0)),"") | J49: =IFERROR(INDEX(Rules!$H:$H,MATCH(G50,Rules!$E:$E,0)),"") | K49: Above ground | L49: Oberirdisch | O49: Property for specifying whether the storey is above ground. | P49: Merkmal zur Angabe, ob das Geschoss oberirdisch liegt. | S49: BOOLEAN | T49: IfcBoolean | W49: https://identifier.buildingsmart.org/uri/buildingsmart/ifc/4.3/prop/AboveGround | X49: https://identifier.buildingsmart.org/uri/buildingsmart/ifc/4.3/class/Pset_BuildingStoreyCommon | AF49: Candidate | AG49: 2026-07-31T12:00:00Z | AH49: KBOB
F50: raum-id | H50: =IFERROR(INDEX(Rules!$F:$F,MATCH(G51,Rules!$E:$E,0)),"") | I50: =IFERROR(INDEX(Rules!$G:$G,MATCH(G51,Rules!$E:$E,0)),"") | J50: =IFERROR(INDEX(Rules!$H:$H,MATCH(G51,Rules!$E:$E,0)),"") | K50: Room ID | L50: Raum ID | O50: Property for uniquely identifying rooms. | P50: Merkmal zur eindeutigen Identifikation von Räumen. | S50: STRING | T50: IfcLabel | AF50: Candidate | AG50: 2026-07-31T12:00:00Z | AH50: KBOB
F51: raumnummer-betrieb | H51: =IFERROR(INDEX(Rules!$F:$F,MATCH(G52,Rules!$E:$E,0)),"") | I51: =IFERROR(INDEX(Rules!$G:$G,MATCH(G52,Rules!$E:$E,0)),"") | J51: =IFERROR(INDEX(Rules!$H:$H,MATCH(G52,Rules!$E:$E,0)),"") | K51: Operational room number | L51: Raumnummer Betrieb | O51: Property for specifying the operational room number. | P51: Merkmal zur Angabe von der betrieblichen Raumnummer. | S51: STRING | T51: IfcLabel | AF51: Candidate | AG51: 2026-07-31T12:00:00Z | AH51: KBOB
F52: raumbezeichnung | H52: =IFERROR(INDEX(Rules!$F:$F,MATCH(G53,Rules!$E:$E,0)),"") | I52: =IFERROR(INDEX(Rules!$G:$G,MATCH(G53,Rules!$E:$E,0)),"") | J52: =IFERROR(INDEX(Rules!$H:$H,MATCH(G53,Rules!$E:$E,0)),"") | K52: Room designation | L52: Raumbezeichnung | O52: Property for specifying the room designation. | P52: Merkmal zur Angabe von der Raumbezeichnung. | S52: STRING | T52: IfcLabel | W52: https://identifier.buildingsmart.org/uri/buildingsmart/ifc/4.3/prop/LongName | AF52: Candidate | AG52: 2026-07-31T12:00:00Z | AH52: KBOB
F53: raumtyp | H53: =IFERROR(INDEX(Rules!$F:$F,MATCH(G54,Rules!$E:$E,0)),"") | I53: =IFERROR(INDEX(Rules!$G:$G,MATCH(G54,Rules!$E:$E,0)),"") | J53: =IFERROR(INDEX(Rules!$H:$H,MATCH(G54,Rules!$E:$E,0)),"") | K53: Room type | L53: Raumtyp | O53: Property for specifying the room type. | P53: Merkmal zur Angabe von dem Raumtyp. | S53: STRING | T53: IfcLabel | W53: https://identifier.buildingsmart.org/uri/buildingsmart/ifc/4.3/prop/OccupancyType | X53: https://identifier.buildingsmart.org/uri/buildingsmart/ifc/4.3/class/Pset_SpaceOccupancyRequirements | AF53: Candidate | AG53: 2026-07-31T12:00:00Z | AH53: KBOB
F54: reinigungsgruppe | H54: =IFERROR(INDEX(Rules!$F:$F,MATCH(G55,Rules!$E:$E,0)),"") | I54: =IFERROR(INDEX(Rules!$G:$G,MATCH(G55,Rules!$E:$E,0)),"") | J54: =IFERROR(INDEX(Rules!$H:$H,MATCH(G55,Rules!$E:$E,0)),"") | K54: Cleaning group | L54: Reinigungsgruppe | O54: Property for specifying the cleaning group. | P54: Merkmal zur Angabe von der Reinigungsgruppe. | S54: STRING | T54: IfcLabel | AF54: Candidate | AG54: 2026-07-31T12:00:00Z | AH54: KBOB
F55: flachenart-sia-416 | H55: =IFERROR(INDEX(Rules!$F:$F,MATCH(G56,Rules!$E:$E,0)),"") | I55: =IFERROR(INDEX(Rules!$G:$G,MATCH(G56,Rules!$E:$E,0)),"") | J55: =IFERROR(INDEX(Rules!$H:$H,MATCH(G56,Rules!$E:$E,0)),"") | K55: SIA 416 area category | L55: Flächenart SIA 416 | O55: Property for specifying the area type according to SIA 416. | P55: Merkmal zur Angabe von der Flächenart nach SIA 416. | S55: STRING | T55: IfcLabel | AF55: Candidate | AG55: 2026-07-31T12:00:00Z | AH55: KBOB
F56: flachenart-d0165 | H56: =IFERROR(INDEX(Rules!$F:$F,MATCH(G57,Rules!$E:$E,0)),"") | I56: =IFERROR(INDEX(Rules!$G:$G,MATCH(G57,Rules!$E:$E,0)),"") | J56: =IFERROR(INDEX(Rules!$H:$H,MATCH(G57,Rules!$E:$E,0)),"") | K56: d0165 area category | L56: Flächenart d0165 | O56: Property for specifying the area type according to d0165. | P56: Merkmal zur Angabe von der Flächenart nach d0165. | S56: STRING | T56: IfcLabel | AF56: Candidate | AG56: 2026-07-31T12:00:00Z | AH56: KBOB
F57: raumvolumen-netto | H57: =IFERROR(INDEX(Rules!$F:$F,MATCH(G58,Rules!$E:$E,0)),"") | I57: =IFERROR(INDEX(Rules!$G:$G,MATCH(G58,Rules!$E:$E,0)),"") | J57: =IFERROR(INDEX(Rules!$H:$H,MATCH(G58,Rules!$E:$E,0)),"") | K57: Net room volume | L57: Raumvolumen Netto | O57: Property for specifying the the net room volume. | P57: Merkmal zur Angabe der dem Netto-Raumvolumen. | S57: REAL | T57: IfcVolumeMeasure | W57: https://identifier.buildingsmart.org/uri/buildingsmart/ifc/4.3/prop/NetVolume | X57: https://identifier.buildingsmart.org/uri/buildingsmart/ifc/4.3/class/Qto_BodyGeometryValidation | Y57: m³ | Z57: http://qudt.org/vocab/unit/M3 | AF57: Candidate | AG57: 2026-07-31T12:00:00Z | AH57: KBOB
F58: nutzhohe | H58: =IFERROR(INDEX(Rules!$F:$F,MATCH(G59,Rules!$E:$E,0)),"") | I58: =IFERROR(INDEX(Rules!$G:$G,MATCH(G59,Rules!$E:$E,0)),"") | J58: =IFERROR(INDEX(Rules!$H:$H,MATCH(G59,Rules!$E:$E,0)),"") | K58: Usable height | L58: Nutzhöhe | O58: Property for specifying the the usable height. | P58: Merkmal zur Angabe der der Nutzhöhe. | S58: REAL | T58: IfcLengthMeasure | W58: https://identifier.buildingsmart.org/uri/buildingsmart/ifc/4.3/prop/NetHeight | X58: https://identifier.buildingsmart.org/uri/buildingsmart/ifc/4.3/class/Qto_BuildingStoreyBaseQuantities | Y58: m | AF58: Candidate | AG58: 2026-07-31T12:00:00Z | AH58: KBOB
F59: lichte-raumhohe | H59: =IFERROR(INDEX(Rules!$F:$F,MATCH(G60,Rules!$E:$E,0)),"") | I59: =IFERROR(INDEX(Rules!$G:$G,MATCH(G60,Rules!$E:$E,0)),"") | J59: =IFERROR(INDEX(Rules!$H:$H,MATCH(G60,Rules!$E:$E,0)),"") | K59: Clear room height | L59: Lichte Raumhöhe | O59: Property for specifying the the clear room height. | P59: Merkmal zur Angabe der der lichten Raumhöhe. | S59: REAL | T59: IfcLengthMeasure | W59: https://identifier.buildingsmart.org/uri/buildingsmart/ifc/4.3/prop/ClearHeight | X59: https://identifier.buildingsmart.org/uri/buildingsmart/ifc/4.3/class/Pset_TransportElementElevator | Y59: m | AF59: Candidate | AG59: 2026-07-31T12:00:00Z | AH59: KBOB
F60: raumflache-brutto | H60: =IFERROR(INDEX(Rules!$F:$F,MATCH(G61,Rules!$E:$E,0)),"") | I60: =IFERROR(INDEX(Rules!$G:$G,MATCH(G61,Rules!$E:$E,0)),"") | J60: =IFERROR(INDEX(Rules!$H:$H,MATCH(G61,Rules!$E:$E,0)),"") | K60: Gross room area | L60: Raumfläche Brutto | O60: Property for specifying the the gross room area. | P60: Merkmal zur Angabe der der Brutto-Raumfläche. | S60: REAL | T60: IfcAreaMeasure | W60: https://identifier.buildingsmart.org/uri/buildingsmart/ifc/4.3/prop/GrossFloorArea | X60: https://identifier.buildingsmart.org/uri/buildingsmart/ifc/4.3/class/Qto_SpaceBaseQuantities | Y60: m² | Z60: http://qudt.org/vocab/unit/M2 | AF60: Candidate | AG60: 2026-07-31T12:00:00Z | AH60: KBOB
F61: raumflache-netto | H61: =IFERROR(INDEX(Rules!$F:$F,MATCH(G62,Rules!$E:$E,0)),"") | I61: =IFERROR(INDEX(Rules!$G:$G,MATCH(G62,Rules!$E:$E,0)),"") | J61: =IFERROR(INDEX(Rules!$H:$H,MATCH(G62,Rules!$E:$E,0)),"") | K61: Net room area | L61: Raumfläche Netto | O61: Property for specifying the the net room area. | P61: Merkmal zur Angabe der der Netto-Raumfläche. | S61: REAL | T61: IfcAreaMeasure | W61: https://identifier.buildingsmart.org/uri/buildingsmart/ifc/4.3/prop/NetFloorArea | X61: https://identifier.buildingsmart.org/uri/buildingsmart/ifc/4.3/class/Qto_SpaceBaseQuantities | Y61: m² | Z61: http://qudt.org/vocab/unit/M2 | AF61: Candidate | AG61: 2026-07-31T12:00:00Z | AH61: KBOB
F62: flachenlast | H62: =IFERROR(INDEX(Rules!$F:$F,MATCH(G63,Rules!$E:$E,0)),"") | I62: =IFERROR(INDEX(Rules!$G:$G,MATCH(G63,Rules!$E:$E,0)),"") | J62: =IFERROR(INDEX(Rules!$H:$H,MATCH(G63,Rules!$E:$E,0)),"") | K62: Area load | L62: Flächenlast | O62: Property for specifying the the area load. | P62: Merkmal zur Angabe der der Flächenlast. | S62: REAL | T62: IfcReal | W62: https://identifier.buildingsmart.org/uri/buildingsmart/ifc/4.3/prop/LoadBearingCapacity | X62: https://identifier.buildingsmart.org/uri/buildingsmart/ifc/4.3/class/Qto_SpaceBaseQuantities | Y62: kN/m² | AF62: Candidate | AG62: 2026-07-31T12:00:00Z | AH62: KBOB
F63: punktlast | H63: =IFERROR(INDEX(Rules!$F:$F,MATCH(G64,Rules!$E:$E,0)),"") | I63: =IFERROR(INDEX(Rules!$G:$G,MATCH(G64,Rules!$E:$E,0)),"") | J63: =IFERROR(INDEX(Rules!$H:$H,MATCH(G64,Rules!$E:$E,0)),"") | K63: Point load | L63: Punktlast | O63: Property for specifying the the point load. | P63: Merkmal zur Angabe der der Punktlast. | S63: REAL | T63: IfcReal | X63: https://identifier.buildingsmart.org/uri/buildingsmart/ifc/4.3/class/Qto_SpaceBaseQuantities | Y63: kN | Z63: http://qudt.org/vocab/unit/KiloN | AF63: Candidate | AG63: 2026-07-31T12:00:00Z | AH63: KBOB
F64: personenbelegung-geplant | H64: =IFERROR(INDEX(Rules!$F:$F,MATCH(G65,Rules!$E:$E,0)),"") | I64: =IFERROR(INDEX(Rules!$G:$G,MATCH(G65,Rules!$E:$E,0)),"") | J64: =IFERROR(INDEX(Rules!$H:$H,MATCH(G65,Rules!$E:$E,0)),"") | K64: Design occupancy | L64: Personenbelegung Geplant | O64: Property for specifying the the design occupancy. | P64: Merkmal zur Angabe der der geplanten Personenbelegung. | S64: INTEGER | T64: IfcInteger | X64: https://identifier.buildingsmart.org/uri/buildingsmart/ifc/4.3/class/Pset_SpaceOccupancyRequirements | AF64: Candidate | AG64: 2026-07-31T12:00:00Z | AH64: KBOB
F65: personenbelegung-ist | H65: =IFERROR(INDEX(Rules!$F:$F,MATCH(G66,Rules!$E:$E,0)),"") | I65: =IFERROR(INDEX(Rules!$G:$G,MATCH(G66,Rules!$E:$E,0)),"") | J65: =IFERROR(INDEX(Rules!$H:$H,MATCH(G66,Rules!$E:$E,0)),"") | K65: Actual occupancy | L65: Personenbelegung Ist | O65: Property for specifying the the actual occupancy. | P65: Merkmal zur Angabe der der tatsächlichen Personenbelegung. | S65: INTEGER | T65: IfcInteger | W65: https://identifier.buildingsmart.org/uri/buildingsmart/ifc/4.3/prop/OccupancyNumber | X65: https://identifier.buildingsmart.org/uri/buildingsmart/ifc/4.3/class/Pset_SpaceOccupancyRequirements | AF65: Candidate | AG65: 2026-07-31T12:00:00Z | AH65: KBOB
F66: energiebezugsflache | H66: =IFERROR(INDEX(Rules!$F:$F,MATCH(G67,Rules!$E:$E,0)),"") | I66: =IFERROR(INDEX(Rules!$G:$G,MATCH(G67,Rules!$E:$E,0)),"") | J66: =IFERROR(INDEX(Rules!$H:$H,MATCH(G67,Rules!$E:$E,0)),"") | K66: Energy reference area | L66: Energiebezugsfläche | O66: Property for specifying the the energy reference area. | P66: Merkmal zur Angabe der der Energiebezugsfläche. | S66: REAL | T66: IfcAreaMeasure | X66: https://identifier.buildingsmart.org/uri/buildingsmart/ifc/4.3/class/Pset_SpaceCommon | AF66: Candidate | AG66: 2026-07-31T12:00:00Z | AH66: KBOB
F67: temperatur | H67: =IFERROR(INDEX(Rules!$F:$F,MATCH(G68,Rules!$E:$E,0)),"") | I67: =IFERROR(INDEX(Rules!$G:$G,MATCH(G68,Rules!$E:$E,0)),"") | J67: =IFERROR(INDEX(Rules!$H:$H,MATCH(G68,Rules!$E:$E,0)),"") | K67: Temperature | L67: Temperatur | O67: Property for specifying the the temperature. | P67: Merkmal zur Angabe der der Temperatur. | S67: REAL | T67: IfcThermalTransmittanceMeasure | W67: https://identifier.buildingsmart.org/uri/buildingsmart/ifc/4.3/prop/ReferenceEnvironmentTemperature | X67: https://identifier.buildingsmart.org/uri/buildingsmart/ifc/4.3/class/Pset_EnvironmentalCondition | Y67: °C | AF67: Candidate | AG67: 2026-07-31T12:00:00Z | AH67: KBOB
F68: fluchtweg | H68: =IFERROR(INDEX(Rules!$F:$F,MATCH(G69,Rules!$E:$E,0)),"") | I68: =IFERROR(INDEX(Rules!$G:$G,MATCH(G69,Rules!$E:$E,0)),"") | J68: =IFERROR(INDEX(Rules!$H:$H,MATCH(G69,Rules!$E:$E,0)),"") | K68: Escape route | L68: Fluchtweg | O68: Property for specifying whether the room forms a part of an escape route. | P68: Merkmal zur Angabe von dem Fluchtweg. | S68: BOOLEAN | T68: IfcBoolean | X68: https://identifier.buildingsmart.org/uri/buildingsmart/ifc/4.3/class/Pset_SpaceCommon | AF68: Candidate | AG68: 2026-07-31T12:00:00Z | AH68: KBOB
F69: fensterflache | H69: =IFERROR(INDEX(Rules!$F:$F,MATCH(G70,Rules!$E:$E,0)),"") | I69: =IFERROR(INDEX(Rules!$G:$G,MATCH(G70,Rules!$E:$E,0)),"") | J69: =IFERROR(INDEX(Rules!$H:$H,MATCH(G70,Rules!$E:$E,0)),"") | K69: Window area | L69: Fensterfläche | O69: Property for specifying the the window area. | P69: Merkmal zur Angabe der der Fensterfläche. | S69: REAL | T69: IfcAreaMeasure | W69: https://identifier.buildingsmart.org/uri/buildingsmart/ifc/4.3/prop/GlazingAreaFraction | X69: https://identifier.buildingsmart.org/uri/buildingsmart/ifc/4.3/class/Pset_WindowCommon | Y69: m² | Z69: http://qudt.org/vocab/unit/M2 | AF69: Candidate | AG69: 2026-07-31T12:00:00Z | AH69: KBOB
F70: fenster-offenbar | H70: =IFERROR(INDEX(Rules!$F:$F,MATCH(G71,Rules!$E:$E,0)),"") | I70: =IFERROR(INDEX(Rules!$G:$G,MATCH(G71,Rules!$E:$E,0)),"") | J70: =IFERROR(INDEX(Rules!$H:$H,MATCH(G71,Rules!$E:$E,0)),"") | K70: Openable window | L70: Fenster Öffenbar | O70: Property for specifying whether the window can be opened. | P70: Merkmal zur Angabe, ob das Fenster geöffnet werden kann. | S70: BOOLEAN | T70: IfcBoolean | X70: https://identifier.buildingsmart.org/uri/buildingsmart/ifc/4.3/class/Pset_WindowCommon | AF70: Candidate | AG70: 2026-07-31T12:00:00Z | AH70: KBOB
F71: raumnutzer | H71: =IFERROR(INDEX(Rules!$F:$F,MATCH(G72,Rules!$E:$E,0)),"") | I71: =IFERROR(INDEX(Rules!$G:$G,MATCH(G72,Rules!$E:$E,0)),"") | J71: =IFERROR(INDEX(Rules!$H:$H,MATCH(G72,Rules!$E:$E,0)),"") | K71: Room user | L71: Raumnutzer | O71: Property for specifying the room user. | P71: Merkmal zur Angabe von dem Raumnutzer. | S71: STRING | T71: IfcLabel | X71: https://identifier.buildingsmart.org/uri/buildingsmart/ifc/4.3/class/Pset_SpaceOccupancyRequirements | AF71: Candidate | AG71: 2026-07-31T12:00:00Z | AH71: KBOB
F72: bodenbelag | H72: =IFERROR(INDEX(Rules!$F:$F,MATCH(G73,Rules!$E:$E,0)),"") | I72: =IFERROR(INDEX(Rules!$G:$G,MATCH(G73,Rules!$E:$E,0)),"") | J72: =IFERROR(INDEX(Rules!$H:$H,MATCH(G73,Rules!$E:$E,0)),"") | K72: Floor covering | L72: Bodenbelag | O72: Property for specifying the floor covering. | P72: Merkmal zur Angabe von dem Bodenbelag. | S72: STRING | T72: IfcLabel | W72: https://identifier.buildingsmart.org/uri/buildingsmart/ifc/4.3/prop/FloorCovering | X72: https://identifier.buildingsmart.org/uri/buildingsmart/ifc/4.3/class/Pset_SpaceCoveringRequirements | AF72: Candidate | AG72: 2026-07-31T12:00:00Z | AH72: KBOB
F73: deckenmaterial | H73: =IFERROR(INDEX(Rules!$F:$F,MATCH(G74,Rules!$E:$E,0)),"") | I73: =IFERROR(INDEX(Rules!$G:$G,MATCH(G74,Rules!$E:$E,0)),"") | J73: =IFERROR(INDEX(Rules!$H:$H,MATCH(G74,Rules!$E:$E,0)),"") | K73: Ceiling material | L73: Deckenmaterial | O73: Property for specifying the ceiling material. | P73: Merkmal zur Angabe von dem Deckenmaterial. | S73: STRING | T73: IfcLabel | W73: https://identifier.buildingsmart.org/uri/buildingsmart/ifc/4.3/prop/CeilingCovering | X73: https://identifier.buildingsmart.org/uri/buildingsmart/ifc/4.3/class/Pset_SpaceCoveringRequirements | AF73: Candidate | AG73: 2026-07-31T12:00:00Z | AH73: KBOB
F74: wandbelag | H74: =IFERROR(INDEX(Rules!$F:$F,MATCH(G75,Rules!$E:$E,0)),"") | I74: =IFERROR(INDEX(Rules!$G:$G,MATCH(G75,Rules!$E:$E,0)),"") | J74: =IFERROR(INDEX(Rules!$H:$H,MATCH(G75,Rules!$E:$E,0)),"") | K74: Wall covering | L74: Wandbelag | O74: Property for specifying the wall covering. | P74: Merkmal zur Angabe von dem Wandbelag. | S74: STRING | T74: IfcLabel | W74: https://identifier.buildingsmart.org/uri/buildingsmart/ifc/4.3/prop/WallCovering | X74: https://identifier.buildingsmart.org/uri/buildingsmart/ifc/4.3/class/Pset_SpaceCoveringRequirements | AF74: Candidate | AG74: 2026-07-31T12:00:00Z | AH74: KBOB
F75: luftwechselrate | H75: =IFERROR(INDEX(Rules!$F:$F,MATCH(G77,Rules!$E:$E,0)),"") | I75: =IFERROR(INDEX(Rules!$G:$G,MATCH(G77,Rules!$E:$E,0)),"") | J75: =IFERROR(INDEX(Rules!$H:$H,MATCH(G77,Rules!$E:$E,0)),"") | K75: Air change rate | L75: Luftwechselrate | O75: Property for specifying the the air change rate. | P75: Merkmal zur Angabe der der Luftwechselrate. | S75: REAL | T75: IfcReal | W75: https://identifier.buildingsmart.org/uri/buildingsmart/ifc/4.3/prop/MechanicalVentilationRate | X75: https://identifier.buildingsmart.org/uri/buildingsmart/ifc/4.3/class/Pset_SpaceHVACDesign | Y75: h⁻¹ | AF75: Candidate | AG75: 2026-07-31T12:00:00Z | AH75: KBOB
F76: luftfeuchtigkeit | H76: =IFERROR(INDEX(Rules!$F:$F,MATCH(G77,Rules!$E:$E,0)),"") | I76: =IFERROR(INDEX(Rules!$G:$G,MATCH(G77,Rules!$E:$E,0)),"") | J76: =IFERROR(INDEX(Rules!$H:$H,MATCH(G77,Rules!$E:$E,0)),"") | K76: Humidity | L76: Luftfeuchtigkeit | O76: Property for specifying the the relative humidity. | P76: Merkmal zur Angabe der der Luftfeuchtigkeit. | S76: REAL | T76: IfcReal | W76: https://identifier.buildingsmart.org/uri/buildingsmart/ifc/4.3/prop/ReferenceAirRelativeHumidity | X76: https://identifier.buildingsmart.org/uri/buildingsmart/ifc/4.3/class/Pset_EnvironmentalCondition | Y76: % | Z76: http://qudt.org/vocab/unit/PERCENT | AF76: Candidate | AG76: 2026-07-31T12:00:00Z | AH76: KBOB
F77: sonnenschutz | H77: =IFERROR(INDEX(Rules!$F:$F,MATCH(G79,Rules!$E:$E,0)),"") | I77: =IFERROR(INDEX(Rules!$G:$G,MATCH(G79,Rules!$E:$E,0)),"") | J77: =IFERROR(INDEX(Rules!$H:$H,MATCH(G79,Rules!$E:$E,0)),"") | K77: Solar shading | L77: Sonnenschutz | O77: Property for specifying whether the room has the solar shading. | P77: Merkmal zur Angabe von dem Sonnenschutz. | S77: BOOLEAN | T77: IfcBoolean | AF77: Candidate | AG77: 2026-07-31T12:00:00Z | AH77: KBOB
F78: beheizt | K78: Heated | L78: Beheizt | O78: Property for specifying whether the room is heated. | P78: Merkmal zur Angabe, ob der Raum beheizt wird. | S78: BOOLEAN | T78: IfcBoolean | X78: https://identifier.buildingsmart.org/uri/buildingsmart/ifc/4.3/class/Pset_SpaceCommon | AF78: Candidate | AG78: 2026-07-31T12:00:00Z | AH78: KBOB
F79: beluftung | H79: =IFERROR(INDEX(Rules!$F:$F,MATCH(#REF!,Rules!$E:$E,0)),"") | I79: =IFERROR(INDEX(Rules!$G:$G,MATCH(#REF!,Rules!$E:$E,0)),"") | J79: =IFERROR(INDEX(Rules!$H:$H,MATCH(#REF!,Rules!$E:$E,0)),"") | K79: Ventilation | L79: Belüftet | O79: Property for specifying whether the room is ventilated. | P79: Merkmal zur Angabe, ob der Raum befüftet wird. | S79: BOOLEAN | T79: IfcBoolean | X79: https://identifier.buildingsmart.org/uri/buildingsmart/ifc/4.3/class/Pset_SpaceCommon | AF79: Candidate | AG79: 2026-07-31T12:00:00Z | AH79: KBOB
F80: befeuchtet | H80: =IFERROR(INDEX(Rules!$F:$F,MATCH(G81,Rules!$E:$E,0)),"") | I80: =IFERROR(INDEX(Rules!$G:$G,MATCH(G81,Rules!$E:$E,0)),"") | J80: =IFERROR(INDEX(Rules!$H:$H,MATCH(G81,Rules!$E:$E,0)),"") | K80: Humidified | L80: Befeuchtet | O80: Property for specifying whether the room is humidified. | P80: Merkmal zur Angabe, ob der Raum befeuchtet wird. | S80: BOOLEAN | T80: IfcBoolean | X80: https://identifier.buildingsmart.org/uri/buildingsmart/ifc/4.3/class/Pset_SpaceCommon | AF80: Candidate | AG80: 2026-07-31T12:00:00Z | AH80: KBOB
F81: entfeuchtet | H81: =IFERROR(INDEX(Rules!$F:$F,MATCH(#REF!,Rules!$E:$E,0)),"") | I81: =IFERROR(INDEX(Rules!$G:$G,MATCH(#REF!,Rules!$E:$E,0)),"") | J81: =IFERROR(INDEX(Rules!$H:$H,MATCH(#REF!,Rules!$E:$E,0)),"") | K81: Dehumidified | L81: Entfeuchtet | O81: Property for specifying whether the room is dehumidified. | P81: Merkmal zur Angabe, ob der Raum entfeuchtet wird. | S81: BOOLEAN | T81: IfcBoolean | X81: https://identifier.buildingsmart.org/uri/buildingsmart/ifc/4.3/class/Pset_SpaceCommon | AF81: Candidate | AG81: 2026-07-31T12:00:00Z | AH81: KBOB
F82: gekühlt | K82: Cooled | L82: Gekühlt | O82: Property for specifying whether the room is cooled. | P82: Merkmal zur Angabe, ob der Raum gekühlt wird. | S82: BOOLEAN | T82: IfcBoolean | X82: https://identifier.buildingsmart.org/uri/buildingsmart/ifc/4.3/class/Pset_SpaceCommon | AF82: Candidate | AG82: 2026-07-31T12:00:00Z | AH82: KBOB
F83: klimatisiert | H83: =IFERROR(INDEX(Rules!$F:$F,MATCH(#REF!,Rules!$E:$E,0)),"") | I83: =IFERROR(INDEX(Rules!$G:$G,MATCH(#REF!,Rules!$E:$E,0)),"") | J83: =IFERROR(INDEX(Rules!$H:$H,MATCH(#REF!,Rules!$E:$E,0)),"") | K83: Air-conditioned | L83: Klimatisiert | O83: Property for specifying whether the room is air-conditioned. | P83: Merkmal zur Angabe, ob der Raum klimatisiert ist. | S83: BOOLEAN | T83: IfcBoolean | X83: https://identifier.buildingsmart.org/uri/buildingsmart/ifc/4.3/class/Pset_SpaceCommon | AF83: Candidate | AG83: 2026-07-31T12:00:00Z | AH83: KBOB
F84: sanitäre-anlagen | K84: Sanitary facilities | L84: Sanitäre Anlagen | O84: Property for specifying whether the room is equipped with sanitary facilities. | P84: Merkmal zur Angabe, ob der Raum mit sanitären Anlagen ausgestattet ist. | S84: BOOLEAN | T84: IfcBoolean | X84: https://identifier.buildingsmart.org/uri/buildingsmart/ifc/4.3/class/Pset_SpaceCommon | AF84: Candidate | AG84: 2026-07-31T12:00:00Z | AH84: KBOB
F85: vermietbarkeit | H85: =IFERROR(INDEX(Rules!$F:$F,MATCH(G87,Rules!$E:$E,0)),"") | I85: =IFERROR(INDEX(Rules!$G:$G,MATCH(G87,Rules!$E:$E,0)),"") | J85: =IFERROR(INDEX(Rules!$H:$H,MATCH(G87,Rules!$E:$E,0)),"") | K85: Lettable status | L85: Vermietbarkeit | O85: Property for specifying whether the room is lettable. | P85: Merkmal zur Angabe, ob der Raum oder das Objekt vermietbar ist. | S85: BOOLEAN | T85: IfcBoolean | X85: https://identifier.buildingsmart.org/uri/buildingsmart/ifc/4.3/class/Pset_SpaceOccupancyRequirements | AF85: Candidate | AG85: 2026-07-31T12:00:00Z | AH85: KBOB
F86: doppelboden | H86: =IFERROR(INDEX(Rules!$F:$F,MATCH(G87,Rules!$E:$E,0)),"") | I86: =IFERROR(INDEX(Rules!$G:$G,MATCH(G87,Rules!$E:$E,0)),"") | J86: =IFERROR(INDEX(Rules!$H:$H,MATCH(G87,Rules!$E:$E,0)),"") | K86: Raised access floor | L86: Doppelboden | O86: Property for specifying whether the room has the raised floor. | P86: Merkmal zur Angabe von dem Doppelboden. | S86: BOOLEAN | T86: IfcBoolean | X86: https://identifier.buildingsmart.org/uri/buildingsmart/ifc/4.3/class/Pset_SpaceCommon | AF86: Candidate | AG86: 2026-07-31T12:00:00Z | AH86: KBOB
F87: bauteil-id | H87: =IFERROR(INDEX(Rules!$F:$F,MATCH(G88,Rules!$E:$E,0)),"") | I87: =IFERROR(INDEX(Rules!$G:$G,MATCH(G88,Rules!$E:$E,0)),"") | J87: =IFERROR(INDEX(Rules!$H:$H,MATCH(G88,Rules!$E:$E,0)),"") | K87: Component ID | L87: Bauteil ID | O87: Property for uniquely identifying components. | P87: Merkmal zur eindeutigen Identifikation von Bauteilen. | S87: STRING | T87: IfcLabel | AF87: Candidate | AG87: 2026-07-31T12:00:00Z | AH87: KBOB
F88: aks | H88: =IFERROR(INDEX(Rules!$F:$F,MATCH(G89,Rules!$E:$E,0)),"") | I88: =IFERROR(INDEX(Rules!$G:$G,MATCH(G89,Rules!$E:$E,0)),"") | J88: =IFERROR(INDEX(Rules!$H:$H,MATCH(G89,Rules!$E:$E,0)),"") | K88: Asset Identification Code | L88: Anlagenkennzeichnungssystem | O88: Property for specifying the asset identification code. | P88: Merkmal zur Angabe von dem Anlagenkennzeichnungssystem-Code. | S88: STRING | T88: IfcLabel | W88: https://identifier.buildingsmart.org/uri/buildingsmart/ifc/4.3/prop/AssetIdentifier | X88: https://identifier.buildingsmart.org/uri/buildingsmart/ifc/4.3/class/Pset_ConstructionOccurence | AF88: Candidate | AG88: 2026-07-31T12:00:00Z | AH88: KBOB
F89: antrieb | H89: =IFERROR(INDEX(Rules!$F:$F,MATCH(G90,Rules!$E:$E,0)),"") | I89: =IFERROR(INDEX(Rules!$G:$G,MATCH(G90,Rules!$E:$E,0)),"") | J89: =IFERROR(INDEX(Rules!$H:$H,MATCH(G90,Rules!$E:$E,0)),"") | K89: Drive | L89: Antrieb | O89: Property for specifying the drive. | P89: Merkmal zur Angabe von dem Antrieb. | S89: BOOLEAN | T89: IfcBoolean | W89: https://identifier.buildingsmart.org/uri/buildingsmart/ifc/4.3/prop/HasDrive | AF89: Candidate | AG89: 2026-07-31T12:00:00Z | AH89: KBOB
F90: artikelnummer | H90: =IFERROR(INDEX(Rules!$F:$F,MATCH(G91,Rules!$E:$E,0)),"") | I90: =IFERROR(INDEX(Rules!$G:$G,MATCH(G91,Rules!$E:$E,0)),"") | J90: =IFERROR(INDEX(Rules!$H:$H,MATCH(G91,Rules!$E:$E,0)),"") | K90: Article number | L90: Artikelnummer | O90: Property for specifying the article number. | P90: Merkmal zur Angabe von der Artikelnummer. | S90: STRING | T90: IfcLabel | W90: https://identifier.buildingsmart.org/uri/buildingsmart/ifc/4.3/prop/ArticleNumber | X90: https://identifier.buildingsmart.org/uri/buildingsmart/ifc/4.3/class/Pset_ManufacturerTypeInformation | AF90: Candidate | AG90: 2026-07-31T12:00:00Z | AH90: KBOB
F91: bauteilart | H91: =IFERROR(INDEX(Rules!$F:$F,MATCH(G92,Rules!$E:$E,0)),"") | I91: =IFERROR(INDEX(Rules!$G:$G,MATCH(G92,Rules!$E:$E,0)),"") | J91: =IFERROR(INDEX(Rules!$H:$H,MATCH(G92,Rules!$E:$E,0)),"") | K91: Component category | L91: Bauteilart | O91: Property for specifying the component category. | P91: Merkmal zur Angabe von der Bauteilart. | S91: STRING | T91: IfcLabel | W91: https://identifier.buildingsmart.org/uri/buildingsmart/ifc/4.3/prop/ObjectType | AF91: Candidate | AG91: 2026-07-31T12:00:00Z | AH91: KBOB
F92: bauteiltyp | H92: =IFERROR(INDEX(Rules!$F:$F,MATCH(G93,Rules!$E:$E,0)),"") | I92: =IFERROR(INDEX(Rules!$G:$G,MATCH(G93,Rules!$E:$E,0)),"") | J92: =IFERROR(INDEX(Rules!$H:$H,MATCH(G93,Rules!$E:$E,0)),"") | K92: Component type | L92: Bauteiltyp | O92: Property for specifying the component type. | P92: Merkmal zur Angabe von dem Bauteiltyp. | S92: STRING | T92: IfcLabel | W92: https://identifier.buildingsmart.org/uri/buildingsmart/ifc/4.3/prop/ModelReference | X92: https://identifier.buildingsmart.org/uri/buildingsmart/ifc/4.3/class/Pset_ManufacturerTypeInformation | AF92: Candidate | AG92: 2026-07-31T12:00:00Z | AH92: KBOB
F93: bauteilname | H93: =IFERROR(INDEX(Rules!$F:$F,MATCH(G94,Rules!$E:$E,0)),"") | I93: =IFERROR(INDEX(Rules!$G:$G,MATCH(G94,Rules!$E:$E,0)),"") | J93: =IFERROR(INDEX(Rules!$H:$H,MATCH(G94,Rules!$E:$E,0)),"") | K93: Component name | L93: Bauteilname | O93: Property for specifying the component name. | P93: Merkmal zur Angabe von dem Bauteilnamen. | S93: STRING | T93: IfcLabel | W93: https://identifier.buildingsmart.org/uri/buildingsmart/ifc/4.3/prop/Name | AF93: Candidate | AG93: 2026-07-31T12:00:00Z | AH93: KBOB
F94: hersteller | H94: =IFERROR(INDEX(Rules!$F:$F,MATCH(G95,Rules!$E:$E,0)),"") | I94: =IFERROR(INDEX(Rules!$G:$G,MATCH(G95,Rules!$E:$E,0)),"") | J94: =IFERROR(INDEX(Rules!$H:$H,MATCH(G95,Rules!$E:$E,0)),"") | K94: Manufacturer | L94: Hersteller | O94: Property for specifying the manufacturer. | P94: Merkmal zur Angabe von dem Hersteller. | S94: STRING | T94: IfcLabel | W94: https://identifier.buildingsmart.org/uri/buildingsmart/ifc/4.3/prop/Manufacturer | X94: https://identifier.buildingsmart.org/uri/buildingsmart/ifc/4.3/class/Pset_ManufacturerTypeInformation | AF94: Candidate | AG94: 2026-07-31T12:00:00Z | AH94: KBOB
F95: produkt-id | H95: =IFERROR(INDEX(Rules!$F:$F,MATCH(G96,Rules!$E:$E,0)),"") | I95: =IFERROR(INDEX(Rules!$G:$G,MATCH(G96,Rules!$E:$E,0)),"") | J95: =IFERROR(INDEX(Rules!$H:$H,MATCH(G96,Rules!$E:$E,0)),"") | K95: Product ID | L95: Produkt ID | O95: Property for uniquely identifying products. | P95: Merkmal zur eindeutigen Identifikation von Produkten. | S95: STRING | T95: IfcLabel | X95: https://identifier.buildingsmart.org/uri/buildingsmart/ifc/4.3/class/Pset_ManufacturerTypeInformation | AF95: Candidate | AG95: 2026-07-31T12:00:00Z | AH95: KBOB
F96: material | H96: =IFERROR(INDEX(Rules!$F:$F,MATCH(G97,Rules!$E:$E,0)),"") | I96: =IFERROR(INDEX(Rules!$G:$G,MATCH(G97,Rules!$E:$E,0)),"") | J96: =IFERROR(INDEX(Rules!$H:$H,MATCH(G97,Rules!$E:$E,0)),"") | K96: Material | L96: Material | O96: Property for specifying the material. | P96: Merkmal zur Angabe von dem Material. | S96: STRING | T96: IfcLabel | AF96: Candidate | AG96: 2026-07-31T12:00:00Z | AH96: KBOB
F97: seriennummer | H97: =IFERROR(INDEX(Rules!$F:$F,MATCH(G98,Rules!$E:$E,0)),"") | I97: =IFERROR(INDEX(Rules!$G:$G,MATCH(G98,Rules!$E:$E,0)),"") | J97: =IFERROR(INDEX(Rules!$H:$H,MATCH(G98,Rules!$E:$E,0)),"") | K97: Serial number | L97: Seriennummer | O97: Property for specifying the serial number. | P97: Merkmal zur Angabe von der Seriennummer. | S97: STRING | T97: IfcLabel | W97: https://identifier.buildingsmart.org/uri/buildingsmart/ifc/4.3/prop/SerialNumber | X97: https://identifier.buildingsmart.org/uri/buildingsmart/ifc/4.3/class/Pset_ManufacturerOccurrence | AF97: Candidate | AG97: 2026-07-31T12:00:00Z | AH97: KBOB
F98: anlagenzustand | H98: =IFERROR(INDEX(Rules!$F:$F,MATCH(G99,Rules!$E:$E,0)),"") | I98: =IFERROR(INDEX(Rules!$G:$G,MATCH(G99,Rules!$E:$E,0)),"") | J98: =IFERROR(INDEX(Rules!$H:$H,MATCH(G99,Rules!$E:$E,0)),"") | K98: Asset condition rating | L98: Anlagenzustand | O98: Property for specifying the asset condition rating. | P98: Merkmal zur Angabe von dem Anlagenzustand. | S98: STRING | T98: IfcLabel | W98: https://identifier.buildingsmart.org/uri/buildingsmart/ifc/4.3/prop/Status | AF98: Candidate | AG98: 2026-07-31T12:00:00Z | AH98: KBOB
F99: anschaffungskosten | H99: =IFERROR(INDEX(Rules!$F:$F,MATCH(G100,Rules!$E:$E,0)),"") | I99: =IFERROR(INDEX(Rules!$G:$G,MATCH(G100,Rules!$E:$E,0)),"") | J99: =IFERROR(INDEX(Rules!$H:$H,MATCH(G100,Rules!$E:$E,0)),"") | K99: Acquisition cost | L99: Anschaffungskosten | O99: Property for specifying the the acquisition cost. | P99: Merkmal zur Angabe der den Anschaffungskosten. | S99: REAL | T99: IfcReal | AF99: Candidate | AG99: 2026-07-31T12:00:00Z | AH99: KBOB
F100: brandschutzklasse | H100: =IFERROR(INDEX(Rules!$F:$F,MATCH(G101,Rules!$E:$E,0)),"") | I100: =IFERROR(INDEX(Rules!$G:$G,MATCH(G101,Rules!$E:$E,0)),"") | J100: =IFERROR(INDEX(Rules!$H:$H,MATCH(G101,Rules!$E:$E,0)),"") | K100: Fire protection class | L100: Brandschutzklasse | O100: Property for specifying the fire protection class. | P100: Merkmal zur Angabe von der Brandschutzklasse. | S100: STRING | T100: IfcLabel | W100: https://identifier.buildingsmart.org/uri/buildingsmart/ifc/4.3/prop/FireRating | AF100: Candidate | AG100: 2026-07-31T12:00:00Z | AH100: KBOB
...

Sheet Values
A1: Filter | B1: Hinweise zur Handhabung | C1: Enumerations | D1: GUID/URI | E1: Enumeration-ID | F1: Enumeration-Code | G1: Designation (EN) | H1: Bezeichnung (DE) | I1: Désignation (FR) | J1: Designazione (IT) | K1: Enumeration (EN) | L1: Werteliste (DE) | M1: Liste de valeurs (FR) | N1: Lista valori (IT) | O1: Units/Einheit/Unité/Unità | P1: Governance | Q1: Status | R1: Version date | S1: Provenance (PROV)
B2: Erforderlich für Excel
B3: Sprachen
B4: Referenziert / System generiert | D4: multilingual | E4: multilingual | F4: multilingual | G4: EN | H4: DE | I4: FR | J4: IT | K4: EN | L4: DE | M4: FR | N4: IT | O4: multilingual | Q4: multilingual | R4: multilingual | S4: multilingual
B5: Dropdown Liste | D5: system-generated | E5: system-generated | Q5: referenced | R5: referenced | S5: referenced
B6: Validierung | Q6: Rules.Status
G7: Canton | H7: Kanton | K7: ["Zürich", "Bern", "Luzern", "Uri", "Schwyz", "Obwalden", "Nidwalden", "Glarus", "Zug", "Freiburg", "Solothurn", "Basel-Stadt", "Basel-Landschaft", "Schaffhausen", "Appenzell Ausserrhoden", "Appenzell Innerrhoden", "St. Gallen", "Graubünden", "Aargau", "Thurgau", "Tessin", "Waadt", "Wallis", "Neuenburg", "Genf", "Jura"] | L7: ["Zürich", "Bern", "Luzern", "Uri", "Schwyz", "Obwalden", "Nidwalden", "Glarus", "Zug", "Freiburg", "Solothurn", "Basel-Stadt", "Basel-Landschaft", "Schaffhausen", "Appenzell Ausserrhoden", "Appenzell Innerrhoden", "St. Gallen", "Graubünden", "Aargau", "Thurgau", "Tessin", "Waadt", "Wallis", "Neuenburg", "Genf", "Jura"] | Q7: Preview | R7: 2026-07-31T12:00:00Z | S7: KBOB
G8: SIA 416 area category | H8: Flächenart SIA 416 | K8: ["1.2", "1.2.1", "1.2.2", 2, "2.1.1.1", "2.1.1.2", "2.1.2", "2.1.3", 3, "3.1.1", "3.1.2", "3.1.3", "AIRSPACE", "ROOF", 1, 2, 3, 4] | L8: ["1_GSF", "1.1_GGF", "1.2_UF", "1.2.1_BUF", "1.2.2_UUF", "2_GF", "2.1.1.1_HNF", "2.1.1.2_NNF", "2.1.2_VF", "2.1.3_FF", "3_AGF", "3.1_ANGF", "3.1.1_ANF", "3.1.2_AVF", "3.1.3_AFF", "5_GV", "AIRSPACE_LUFTRAUM", "ROOF_DACH"] | Q8: Preview | R8: 2026-07-31T12:00:00Z | S8: KBOB
G9: d0165 area category | H9: Flächenart d0165 | K9: [1.1, 1.2, 1.3, 1.4, 1.5, 1.6, 2.1, 2.2, 2.3, 2.4, 2.5, 2.6, 2.7, 2.8, 3.1, 3.2, 3.3, 3.4, 3.5, 3.6, 3.7, 3.8, 3.9, 4.1, 4.2, 4.3, 4.4, 4.5, 4.6, 5.1, 5.2, 5.3, 5.4, 5.5, 5.6, 5.7, 5.8, 5.9, 6.1, 6.2, 6.3, 6.4, 6.5, 6.6, 6.7, 6.8, 7.1, 7.2, 7.3, 7.4, 7.5, 7.6, 7.7, 8.1, 8.2, 8.3, 8.4, 8.5, 8.6, 8.7, 8.8, 8.9, 9.1, 9.2, 9.3, 9.4, 10.1] | L9: ["1.1_Wohnräume", "1.2_Gemeinschaftsräume", "1.3_Pausenräume", "1.4_Warteräume", "1.5_Speiseräume", "1.6_Hafträume", "2.1_Büroräume", "2.2_Grossraumbüros", "2.3_Besprechungsräume", "2.4_Konstruktionsräume", "2.5_Schalterräume", "2.6_Bedienungsräume", "2.7_Aufsichtsräume", "2.8_Bürotechnikräume", "3.1_Werkhallen", "3.2_Werkstätten", "3.3_Technologische Labors", "3.4_Physikalische/physikaltechnische/elektrotechnische Labors", "3.5_Chemische/bakteriologische/morphologische Labors", "3.6_Räume für Tierhaltung", "3.7_Räume für Pflanzenzucht", "3.8_Küchen", "3.9_Sonderarbeitsräume", "4.1_Lagerräume", "4.2_Archive/Sammlungsräume", "4.3_Kühlräume", "4.4_Annahme- und Ausgaberäume", "4.5_Verkaufsräume", "4.6_Ausstellungsräume", "5.1_Unterrichtsräume mit festem Gestühl", "5.2_Allgemein Unterrichts- und Übungsräume ohne festes Gestühl", "5.3_Besondere Unterrichts- und Übungsräume ohne festes Gestühl", "5.4_Bibliotheksräume", "5.5_Sporträume", "5.6_Versammlungsräume", "5.7_Bühnen-/Studioräume", "5.8_Schauräume", "5.9_Sakralräume", "6.1_Räume mit allgemeiner medizinischen Ausstattung", "6.2_Räume mit besonderer medizinischen Ausstattung", "6.3_Räume für operative Eingriffe/Endoskopien/Entbindungen", "6.4_Räume für Strahlendiagnostik", "6.5_Räume für Strahlentherapie", "6.6_Räume für Physiotherapie und Rehabilitation", "6.7_Bettenräume mit allgemeiner Ausstattung", "6.8_Bettenräume mit besonderer Ausstattung", "7.1_Sanitärräume", "7.2_Garderoben", "7.3_Abstellräume", "7.4_Fahrzeugabstellflächen", "7.5_Fahrgastflächen", "7.6_Räume für zentrale Technik", "7.7_Schutzräum", "8.1_Abwasseraufbereitung u. -beseitigung", "8.2_Wasserversorgung", "8.3_Heizung und Brauchwassererwärmung", "8.4_Gase und Flüssigkeiten", "8.5_Elektrische Stromversorgung", "8.6_Fernmeldetechnik", "8.7_Raumlufttechnische Anlagen", "8.8_Aufzugs- und Förderanlagen", "8.9_Sonstige betriebstechnische Anlagen", "9.1_Flure/Hallen", "9.2_Treppen", "9.3_Schächte für Förderanlagen", "9.4_Fahrzeugsverkehrsflächen", "10.1_aussenliegende Fahrzeugabstellflächen"] | Q9: Preview | R9: 2026-07-31T12:00:00Z | S9: KBOB
G10: eBKP-H code | H10: eBKP-H | K10: ["A01.01", "A01.02", "A01.03", "A01.04", "A02.01", "A02.02", "A02.03", "A02.04", "A02.05", "A02.06", "A02.07", "B01.01", "B01.02", "B01.03", "B01.04", "B02.01", "B02.02", "B02.03", "B02.04", "B02.05", "B02.06", "B02.07", "B02.08", "B03.01", "B03.02", "B03.03", "B03.04", "B03.05", "B04.01", "B04.02", "B04.03", "B04.04", "B04.05", "B04.06", "B04.07", "B04.08", "B05.01", "B05.02", "B05.03", "B06.01", "B06.02", "B06.03", "B06.04", "B06.05", "B06.06", "B07.01", "B07.02", "B07.03", "B07.04", "B08.01", "B08.02", "B08.03", "B08.04", "B09.01", "B09.02", "B09.03", "C01.01", "C01.02", "C01.03", "C01.04", "C01.05", "C02.01", "C02.02", "C03.01", "C03.02", "C04.01", "C04.02", "C04.03", "C04.04", "C04.05", "C04.06", "C04.07", "C04.08", "C05.01", "C05.02", "D01.01", "D01.02", "D01.03", "D01.04", "D01.05", "D01.06", "D01.07", "D01.08", "D01.09", "D01.10", "D01.11", "D02.01", "D02.02", "D02.03", "D02.04", "D02.05", "D02.06", "D02.07", "D03.01", "D03.02", "D03.03", "D03.04", "D04.01", "D04.02", "D04.03", "D04.04", "D04.05", "D04.06", "D04.07", "D05.01", "D05.02", "D05.03", "D05.04", "D05.05", "D05.06", "D06.01", "D06.02", "D06.03", "D06.04", "D06.05", "D06.06", "D07.01", "D07.02", "D07.03", "D07.04", "D07.05", "D07.06", "D08.01", "D08.02", "D08.03", "D08.04", "D08.05", "D08.06", "D09.01", "D09.02", "D09.03", "D09.04", "D09.05", "D10.01", "D10.02", "D10.03", "D10.04", "D10.05", "D11.01", "D11.02", "D11.03", "D11.04", "D11.05", "D12.01", "D12.02", "D12.03", "D12.04", "D12.05", "D12.06", "E01.01", "E01.02", "E01.03", "E02.01", "E02.02", "E02.03", "E02.04", "E02.05", "E02.06", "E03.01", "E03.02", "E03.03", "E03.04", "E03.05", "F01.01", "F01.02", "F01.03", "F01.04", "F02.01", "F02.02", "F02.03", "G01.01", "G01.02", "G01.03", "G01.04", "G01.05", "G01.06", "G02.01", "G02.02", "G03.01", "G03.02", "G04.01", "G04.02", "G05.01", "G05.02", "G05.03", "G05.04", "G05.05", "G05.06", "G05.07", "G06.01", "G06.02", "G06.03", "G06.04", "H01.01", "H01.02", "H01.03", "H01.04", "H01.05", "H02.01", "H02.02", "H02.03", "H02.04", "H02.05", "H03.01", "H03.02", "H03.03", "H03.04", "H03.05", "H04.01", "H04.02", "H04.03", "H04.04", "H04.05", "H05.01", "H05.02", "H05.03", "H05.04", "H05.05", "H05.06", "H05.07", "H05.08", "H05.09", "H05.10", "H05.11", "H05.12", "H06.01", "H06.02", "H06.03", "H06.04", "H07.01", "H07.02", "H07.03", "H07.04", "H08.01", "H08.02", "H08.03", "H08.04", "H09.01", "H09.02", "H09.03", "H09.04", "H09.05", "H09.06", "H09.07", "H09.08", "H09.09", "I01.01", "I01.02", "I02.01", "I02.02", "I02.03", "I02.04", "I02.05", "I02.06", "I02.07", "I02.08", "I03.01", "I03.02", "I03.03", "I03.04", "I03.05", "I03.06", "I03.07", "I03.08", "I03.09", "I04.01", "I04.02", "I04.03", "I04.04", "I05.01", "I05.02", "I05.03", "I05.04", "I05.05", "I05.06", "I05.07", "I05.08", "I06.01", "I06.02", "I06.03", "I06.04", "J01.01", "J01.02", "J01.03", "J01.04", "J02.01", "J02.02", "J02.03", "J03.01", "J03.02", "J04.01", "J04.02", "V01.01", "V01.02", "V01.03", "V01.04", "V01.05", "V01.06", "V01.07", "V02.01", "V02.02", "V03.01", "V03.02", "V03.03", "V03.04", "V03.05", "V03.06", "V03.07", "W01.01", "W01.02", "W02.01", "W02.02", "W02.03", "W03.01", "W03.02", "W04.01", "W04.02", "W04.03", "W05.01", "W06.01", "W06.02", "W06.03", "W06.04", "W07.01", "W07.02", "Y01.01", "Y02.01", "Z01.01"] | L10: ["A01.01", "A01.02", "A01.03", "A01.04", "A02.01", "A02.02", "A02.03", "A02.04", "A02.05", "A02.06", "A02.07", "B01.01", "B01.02", "B01.03", "B01.04", "B02.01", "B02.02", "B02.03", "B02.04", "B02.05", "B02.06", "B02.07", "B02.08", "B03.01", "B03.02", "B03.03", "B03.04", "B03.05", "B04.01", "B04.02", "B04.03", "B04.04", "B04.05", "B04.06", "B04.07", "B04.08", "B05.01", "B05.02", "B05.03", "B06.01", "B06.02", "B06.03", "B06.04", "B06.05", "B06.06", "B07.01", "B07.02", "B07.03", "B07.04", "B08.01", "B08.02", "B08.03", "B08.04", "B09.01", "B09.02", "B09.03", "C01.01", "C01.02", "C01.03", "C01.04", "C01.05", "C02.01", "C02.02", "C03.01", "C03.02", "C04.01", "C04.02", "C04.03", "C04.04", "C04.05", "C04.06", "C04.07", "C04.08", "C05.01", "C05.02", "D01.01", "D01.02", "D01.03", "D01.04", "D01.05", "D01.06", "D01.07", "D01.08", "D01.09", "D01.10", "D01.11", "D02.01", "D02.02", "D02.03", "D02.04", "D02.05", "D02.06", "D02.07", "D03.01", "D03.02", "D03.03", "D03.04", "D04.01", "D04.02", "D04.03", "D04.04", "D04.05", "D04.06", "D04.07", "D05.01", "D05.02", "D05.03", "D05.04", "D05.05", "D05.06", "D06.01", "D06.02", "D06.03", "D06.04", "D06.05", "D06.06", "D07.01", "D07.02", "D07.03", "D07.04", "D07.05", "D07.06", "D08.01", "D08.02", "D08.03", "D08.04", "D08.05", "D08.06", "D09.01", "D09.02", "D09.03", "D09.04", "D09.05", "D10.01", "D10.02", "D10.03", "D10.04", "D10.05", "D11.01", "D11.02", "D11.03", "D11.04", "D11.05", "D12.01", "D12.02", "D12.03", "D12.04", "D12.05", "D12.06", "E01.01", "E01.02", "E01.03", "E02.01", "E02.02", "E02.03", "E02.04", "E02.05", "E02.06", "E03.01", "E03.02", "E03.03", "E03.04", "E03.05", "F01.01", "F01.02", "F01.03", "F01.04", "F02.01", "F02.02", "F02.03", "G01.01", "G01.02", "G01.03", "G01.04", "G01.05", "G01.06", "G02.01", "G02.02", "G03.01", "G03.02", "G04.01", "G04.02", "G05.01", "G05.02", "G05.03", "G05.04", "G05.05", "G05.06", "G05.07", "G06.01", "G06.02", "G06.03", "G06.04", "H01.01", "H01.02", "H01.03", "H01.04", "H01.05", "H02.01", "H02.02", "H02.03", "H02.04", "H02.05", "H03.01", "H03.02", "H03.03", "H03.04", "H03.05", "H04.01", "H04.02", "H04.03", "H04.04", "H04.05", "H05.01", "H05.02", "H05.03", "H05.04", "H05.05", "H05.06", "H05.07", "H05.08", "H05.09", "H05.10", "H05.11", "H05.12", "H06.01", "H06.02", "H06.03", "H06.04", "H07.01", "H07.02", "H07.03", "H07.04", "H08.01", "H08.02", "H08.03", "H08.04", "H09.01", "H09.02", "H09.03", "H09.04", "H09.05", "H09.06", "H09.07", "H09.08", "H09.09", "I01.01", "I01.02", "I02.01", "I02.02", "I02.03", "I02.04", "I02.05", "I02.06", "I02.07", "I02.08", "I03.01", "I03.02", "I03.03", "I03.04", "I03.05", "I03.06", "I03.07", "I03.08", "I03.09", "I04.01", "I04.02", "I04.03", "I04.04", "I05.01", "I05.02", "I05.03", "I05.04", "I05.05", "I05.06", "I05.07", "I05.08", "I06.01", "I06.02", "I06.03", "I06.04", "J01.01", "J01.02", "J01.03", "J01.04", "J02.01", "J02.02", "J02.03", "J03.01", "J03.02", "J04.01", "J04.02", "V01.01", "V01.02", "V01.03", "V01.04", "V01.05", "V01.06", "V01.07", "V02.01", "V02.02", "V03.01", "V03.02", "V03.03", "V03.04", "V03.05", "V03.06", "V03.07", "W01.01", "W01.02", "W02.01", "W02.02", "W02.03", "W03.01", "W03.02", "W04.01", "W04.02", "W04.03", "W05.01", "W06.01", "W06.02", "W06.03", "W06.04", "W07.01", "W07.02", "Y01.01", "Y02.01", "Z01.01"] | Q10: Preview | R10: 2026-07-31T12:00:00Z | S10: KBOB
G11: Electricity supply connection | H11: Medienbezug Elektrisch | K11: ["true", "false"] | L11: ["true", "false"] | Q11: Preview | R11: 2026-07-31T12:00:00Z | S11: KBOB
G12: Water supply connection | H12: Medienbezug Wasser | K12: ["true", "false"] | L12: ["true", "false"] | Q12: Preview | R12: 2026-07-31T12:00:00Z | S12: KBOB
G13: Heating supply connection | H13: Medienbezug Heizwärme | K13: ["true", "false"] | L13: ["true", "false"] | Q13: Preview | R13: 2026-07-31T12:00:00Z | S13: KBOB
G14: Heritage status | H14: Denkmalstatus | K14: ["true", "false"] | L14: ["true", "false"] | Q14: Preview | R14: 2026-07-31T12:00:00Z | S14: KBOB
G15: Protection zone | H15: Schutzzone | K15: ["true", "false"] | L15: ["true", "false"] | Q15: Preview | R15: 2026-07-31T12:00:00Z | S15: KBOB
G16: Above ground | H16: Oberirdisch | K16: ["true", "false"] | L16: ["true", "false"] | Q16: Preview | R16: 2026-07-31T12:00:00Z | S16: KBOB
G17: Escape route | H17: Fluchtweg | K17: ["true", "false"] | L17: ["true", "false"] | Q17: Preview | R17: 2026-07-31T12:00:00Z | S17: KBOB
G18: Openable window | H18: Fenster Öffenbar | K18: ["true", "false"] | L18: ["true", "false"] | Q18: Preview | R18: 2026-07-31T12:00:00Z | S18: KBOB
G19: Solar shading | H19: Sonnenschutz | K19: ["true", "false"] | L19: ["true", "false"] | Q19: Preview | R19: 2026-07-31T12:00:00Z | S19: KBOB
G20: Ventilation | H20: Belüftet | K20: ["true", "false"] | L20: ["true", "false"]
G21: Heated | H21: Beheizt | K21: ["true", "false"] | L21: ["true", "false"] | Q21: Preview | R21: 2026-07-31T12:00:00Z | S21: KBOB
G22: Humidified | H22: Befeuchtet | K22: ["true", "false"] | L22: ["true", "false"] | Q22: Preview | R22: 2026-07-31T12:00:00Z | S22: KBOB
G23: Dehumidified | H23: Entfeuchtet | K23: ["true", "false"] | L23: ["true", "false"] | Q23: Preview | R23: 2026-07-31T12:00:00Z | S23: KBOB
G24: Cooled | H24: Gekühlt | K24: ["true", "false"] | L24: ["true", "false"] | Q24: Preview | R24: 2026-07-31T12:00:00Z | S24: KBOB
G25: Air-conditioned | H25: Klimatisiert | K25: ["true", "false"] | L25: ["true", "false"] | Q25: Preview | R25: 2026-07-31T12:00:00Z | S25: KBOB
G26: Sanitary facilities | H26: Sanitäre Anlagen | K26: ["true", "false"] | L26: ["true", "false"] | Q26: Preview | R26: 2026-07-31T12:00:00Z | S26: KBOB
G27: Lettable status | H27: Vermietbarkeit | K27: ["true", "false"] | L27: ["true", "false"] | Q27: Preview | R27: 2026-07-31T12:00:00Z | S27: KBOB
G28: Raised access floor | H28: Doppelboden | K28: ["true", "false"] | L28: ["true", "false"] | Q28: Preview | R28: 2026-07-31T12:00:00Z | S28: KBOB
G29: Escape route function | H29: Fluchtwegfunktion | K29: ["true", "false"] | L29: ["true", "false"] | Q29: Preview | R29: 2026-07-31T12:00:00Z | S29: KBOB
G30: Drive | H30: Antrieb | K30: ["true", "false"] | L30: ["true", "false"] | Q30: Preview | R30: 2026-07-31T12:00:00Z | S30: KBOB

Sheet Documents
A1: Filter | B1: Hinweise zur Handhabung | C1: Documents | D1: GUID/URI | E1: Document-ID | F1: Document-Code | G1: DocumentName (EN) | H1: Bezeichnung (DE) | I1: Désignation (FR) | J1: Designazione (IT) | K1: Security level/Sicherheitsstufe/Niveau de sécurité/Livello di sicurezza | L1: Accessibility/Zugänglichkeit/Accessibilité/Accessibilità | M1: Revision | N1: DocumentOwner | O1: Governance | P1: Status | Q1: Version date | R1: Provenance (PROV)
B2: Erforderlich für Excel
B3: Sprachen
B4: Referenziert / System generiert | D4: multilingual | E4: multilingual | F4: multilingual | G4: EN | H4: DE | I4: FR | J4: IT | K4: multilingual | L4: multilingual | M4: multilingual | N4: multilingual | P4: multilingual | Q4: multilingual | R4: multilingual
B5: Dropdown Liste | E5: system-generated | G5: referenced | M5: referenced | N5: referenced | P5: referenced | Q5: referenced | R5: referenced
B6: Validierung | K6: Rules.ISG - Informationssicherheitsgesetz | L6: Rules.FAIR Prinzipien | P6: Rules.Status
G7: SN 504 416 - Areas and volumes of buildings | H7: SN 504 416 -Flächen und Volumen von Gebäuden | K7: nicht klassifiziert | L7: Zugänglich kostenpflichtig | M7: 2003 | N7: SIA | P7: Candidate | Q7: 2026-07-31T12:00:00Z | R7: KBOB

Sheet GroupOfProperties
A1: Filter | B1: Hinweise zur Handhabung | C1: Group of Properties | D1: GoP-ID | E1: GoP-Code | F1: Designation (EN) | G1: Description (EN) | H1: Beschreibung (DE) | I1: Description (FR) | J1: Descrizione (IT) | K1: Governance | L1: Status | M1: Version date | N1: Provenance (PROV)
B2: Erforderlich für Excel
B3: Sprachen
B4: Referenziert / System generiert | D4: multilingual | E4: multilingual | F4: EN | G4: EN | H4: DE | I4: FR | J4: IT | L4: multilingual | M4: multilingual | N4: multilingual
B5: Dropdown Liste | D5: system-generated | L5: referenced | M5: referenced | N5: referenced
B6: Validierung | L6: Rules.Status
E7: KBOB_Identifikation | F7: KBOB_Identification | G7: PropertySetName KBOB_Identifikation | H7: PropertySetName KBOB_Identification | L7: Candidate | M7: 2026-07-31T12:00:00Z | N7: KBOB
E8: KBOB_Verortung | F8: KBOB_Location | G8: PropertySetName KBOB_Verortung | H8: PropertySetName KBOB_Location | L8: Candidate | M8: 2026-07-31T12:00:00Z | N8: KBOB
E9: KBOB_Klassifikation | F9: KBOB_Classification | G9: PropertySetName KBOB_Klassifikation | H9: PropertySetName KBOB_Classification | L9: Candidate | M9: 2026-07-31T12:00:00Z | N9: KBOB
E10: KBOB_Nutzung | F10: KBOB_Usage | G10: PropertySetName KBOB_Nutzung | H10: PropertySetName KBOB_Usage | L10: Candidate | M10: 2026-07-31T12:00:00Z | N10: KBOB
E11: KBOB_Compliance | F11: KBOB_Compliance | G11: PropertySetName KBOB_Compliance | H11: PropertySetName KBOB_Compliance | L11: Candidate | M11: 2026-07-31T12:00:00Z | N11: KBOB
E12: KBOB_Geometrie | F12: KBOB_Geometry | G12: PropertySetName KBOB_Geometrie | H12: PropertySetName KBOB_Geometry | L12: Candidate | M12: 2026-07-31T12:00:00Z | N12: KBOB
E13: KBOB_Betrieb | F13: KBOB_Operations | G13: PropertySetName KBOB_Betrieb | H13: PropertySetName KBOB_Operations | L13: Candidate | M13: 2026-07-31T12:00:00Z | N13: KBOB
E14: KBOB_Technik | F14: KBOB_Technical | G14: PropertySetName KBOB_Technik | H14: PropertySetName KBOB_Technical | L14: Candidate | M14: 2026-07-31T12:00:00Z | N14: KBOB
E15: KBOB_Wartung | F15: KBOB_Maintenance | G15: PropertySetName KBOB_Wartung | H15: PropertySetName KBOB_Maintenance | L15: Candidate | M15: 2026-07-31T12:00:00Z | N15: KBOB
E16: KBOB_Material | F16: KBOB_Material | G16: PropertySetName KBOB_Material | H16: PropertySetName KBOB_Material | L16: Candidate | M16: 2026-07-31T12:00:00Z | N16: KBOB

Sheet Data_Template
C1: GoP | E1: Properties | DH1: Documents | DN1: LOIN | DS1: Governance
C2: GoP - Designation/Bezeichnung/Désignation/Designazione | E2: Property - Designation/Bezeichnung/Désignation/Designazione | F2: GUID | G2: Grundstück ID | H2: Wirtschaftseinheit ID | I2: Ort | J2: Grundstückbezeichnung | K2: Landeskürzel | L2: Kanton | M2: Postleitzahl | N2: Politische Gemeinde | O2: GIS-Parzellennummer | P2: Grundstücksfläche | Q2: Eigentümer | R2: Dienstbarkeiten ID | S2: Dienstbarkeitenname | T2: Gebäude ID | U2: Objekt ID | V2: Gebäudebezeichnung | W2: Objekttyp | X2: Strasse Hausnummer | Y2: Gefährdungsstufe | Z2: Kostenträger | AA2: Gebäudegrundfläche | AB2: Gebäudevolumen | AC2: Nummer Gebäudeversicherung | AD2: Baujahr | AE2: Medienbezug Elektrisch | AF2: Medienbezug Wasser | AG2: Medienbezug Heizung | AH2: Nutzungsart aussen | AI2: Gebäudeklasse | AJ2: Gebäudelabel | AK2: Denkmalstatus | AL2: Erdbebenbauwerksklasse | AM2: Schutzzone | AN2: Umgebungsfläche ID | AO2: Umgebungsflächennummer | AP2: Geschoss ID | AQ2: Geschossbezeichnung | AR2: Geschossvolumen | AS2: Geschosshöhe | AT2: Geschossfläche | AU2: Aussengeschossfläche | AV2: Oberirdisch | AW2: Raum ID | AX2: Raumnummer Betrieb | AY2: Raumbezeichnung | AZ2: Raumtyp | BA2: Reinigungsgruppe | BB2: Flächenart SIA 416 | BC2: Flächenart d0165 | BD2: Raumvolumen Netto | BE2: Nutzhöhe | BF2: Lichte Raumhöhe | BG2: Raumfläche Brutto | BH2: Raumfläche Netto | BI2: Flächenlast | BJ2: Punktlast | BK2: Personenbelegung Geplant | BL2: Personenbelegung Ist | BM2: Energiebezugsfläche | BN2: Temperatur | BO2: Fluchtweg | BP2: Fensterfläche | BQ2: Fenster Öffenbar | BR2: Raumnutzer | BS2: Bodenbelag | BT2: Deckenmaterial | BU2: Wandbelag | BV2: Luftwechselrate | BW2: Luftfeuchtigkeit | BX2: Sonnenschutz | BY2: Beheizt | BZ2: Belüftet | CA2: Befeuchtet | CB2: Entfeuchtet | CC2: Gekühlt | CD2: Klimatisiert | CE2: Sanitäre Anlagen | CF2: Vermietbarkeit | CG2: Doppelboden | CH2: Bauteil ID | CI2: Anlagenkennzeichnungssystem | CJ2: Antriebsart | CK2: Artikelnummer | CL2: Bauteilart | CM2: Bauteiltyp | CN2: Bauteilname | CO2: Hersteller | CP2: Produkt ID | CQ2: Material | CR2: Seriennummer | CS2: Anlagenzustand | CT2: Anschaffungskosten | CU2: Brandschutzklasse | CV2: eBKP-H | CW2: Einbruchschutzklasse | CX2: Fluchtwegfunktion | CY2: Lebensdauer | CZ2: Türsteuerung | DA2: Wartungsvertrag | DB2: Wartungsintervall | DC2: Abnahmedatum | DD2: Inbetriebnahme | DE2: Nutzlast | DF2: Fensterart | DG2: Schliessart | DH2: Document - Designation/Bezeichnung/Désignation/Designazione | DI2: SN 504 416 -Flächen und Volumen von Gebäuden | DN2: LOIN | DO2: LOIN_Milestone | DP2: LOIN_Role | DQ2: LOIN_UseCase | DS2: Governance | DT2: Status | DU2: Version date | DV2: Provenance (PROV)
A3: Classes
A4: Class - Designation/Bezeichnung/Désignation/Designazione | DT4: Rules.Status
A5: Grundstück | C5: KBOB_Identifikation | F5: x | G5: x | H5: x | J5: x | O5: x | R5: x | S5: x | DT5: Candidate | DU5: 2026-07-31T12:00:00Z | DV5: KBOB
A6: Grundstück | C6: KBOB_Verortung | I6: x | K6: x | L6: x | M6: x | N6: x | DT6: Candidate | DU6: 2026-07-31T12:00:00Z | DV6: KBOB
A7: Grundstück | C7: KBOB_Nutzung | Q7: x | DT7: Candidate | DU7: 2026-07-31T12:00:00Z | DV7: KBOB
A8: Grundstück | C8: KBOB_Geometrie | P8: x | DI8: x | DT8: Candidate | DU8: 2026-07-31T12:00:00Z | DV8: KBOB
DT9: Candidate | DU9: 2026-07-31T12:00:00Z | DV9: KBOB
A10: Gebäude | C10: KBOB_Identifikation | F10: x | T10: x | U10: x | V10: x | X10: x | AC10: x | AJ10: x | AN10: x | AO10: x | DT10: Candidate | DU10: 2026-07-31T12:00:00Z | DV10: KBOB
A11: Gebäude | C11: KBOB_Klassifikation | W11: x | Y11: x | Z11: x | AH11: x | AI11: x | DT11: Candidate | DU11: 2026-07-31T12:00:00Z | DV11: KBOB
A12: Gebäude | C12: KBOB_Nutzung | Q12: x | DT12: Candidate | DU12: 2026-07-31T12:00:00Z | DV12: KBOB
A13: Gebäude | C13: KBOB_Compliance | AK13: x | AL13: x | AM13: x | DT13: Candidate | DU13: 2026-07-31T12:00:00Z | DV13: KBOB
A14: Gebäude | C14: KBOB_Geometrie | AA14: x | AB14: x | DI14: x | DT14: Candidate | DU14: 2026-07-31T12:00:00Z | DV14: KBOB
A15: Gebäude | C15: KBOB_Betrieb | AD15: x | DT15: Candidate | DU15: 2026-07-31T12:00:00Z | DV15: KBOB
A16: Gebäude | C16: KBOB_Technik | AE16: x | AF16: x | AG16: x | DT16: Candidate | DU16: 2026-07-31T12:00:00Z | DV16: KBOB
DT17: Candidate | DU17: 2026-07-31T12:00:00Z | DV17: KBOB
A18: Geschoss | C18: KBOB_Identifikation | F18: x | AP18: x | AQ18: x | DT18: Candidate | DU18: 2026-07-31T12:00:00Z | DV18: KBOB
A19: Geschoss | C19: KBOB_Klassifikation | AV19: x | DT19: Candidate | DU19: 2026-07-31T12:00:00Z | DV19: KBOB
A20: Geschoss | C20: KBOB_Geometrie | AR20: x | AS20: x | AT20: x | AU20: x | DI20: x | DT20: Candidate | DU20: 2026-07-31T12:00:00Z | DV20: KBOB
DT21: Candidate | DU21: 2026-07-31T12:00:00Z | DV21: KBOB
A22: Raum | C22: KBOB_Identifikation | F22: x | AP22: x | AW22: x | AX22: x | AY22: x | CH22: x | DT22: Candidate | DU22: 2026-07-31T12:00:00Z | DV22: KBOB
A23: Raum | C23: KBOB_Klassifikation | AZ23: x | BO23: x | DT23: Candidate | DU23: 2026-07-31T12:00:00Z | DV23: KBOB
A24: Raum | C24: KBOB_Nutzung | BA24: x | BK24: x | BL24: x | BR24: x | CF24: x | DT24: Candidate | DU24: 2026-07-31T12:00:00Z | DV24: KBOB
A25: Raum | C25: KBOB_Geometrie | BB25: x | BC25: x | BD25: x | BE25: x | BF25: x | BG25: x | BH25: x | BI25: x | BJ25: x | BM25: x | BP25: x | DI25: x | DT25: Candidate | DU25: 2026-07-31T12:00:00Z | DV25: KBOB
A26: Raum | C26: KBOB_Technik | BN26: x | BQ26: x | BV26: x | BW26: x | BX26: x | BY26: x | BZ26: x | CA26: x | CB26: x | CC26: x | CD26: x | CE26: x | CG26: x | DT26: Candidate | DU26: 2026-07-31T12:00:00Z | DV26: KBOB
A27: Raum | C27: KBOB_Material | BS27: x | BT27: x | BU27: x | DT27: Candidate | DU27: 2026-07-31T12:00:00Z | DV27: KBOB
DT28: Candidate | DU28: 2026-07-31T12:00:00Z | DV28: KBOB
A29: Bauteil | C29: KBOB_Identifikation | F29: x | CH29: x | CI29: x | CK29: x | CN29: x | CO29: x | CP29: x | CR29: x | DT29: Candidate | DU29: 2026-07-31T12:00:00Z | DV29: KBOB
A30: Bauteil | C30: KBOB_Klassifikation | CL30: x | CM30: x | CV30: x | DF30: x | DG30: x | DT30: Candidate | DU30: 2026-07-31T12:00:00Z | DV30: KBOB
A31: Bauteil | C31: KBOB_Nutzung | Q31: x | DT31: Candidate | DU31: 2026-07-31T12:00:00Z | DV31: KBOB
A32: Bauteil | C32: KBOB_Compliance | CU32: x | CW32: x | DT32: Candidate | DU32: 2026-07-31T12:00:00Z | DV32: KBOB
A33: Bauteil | C33: KBOB_Geometrie | DE33: x | DT33: Candidate | DU33: 2026-07-31T12:00:00Z | DV33: KBOB
A34: Bauteil | C34: KBOB_Technik | CJ34: x | CX34: x | CZ34: x | DT34: Candidate | DU34: 2026-07-31T12:00:00Z | DV34: KBOB
A35: Bauteil | C35: KBOB_Wartung | CS35: x | CT35: x | CY35: x | DA35: x | DB35: x | DC35: x | DD35: x | DT35: Candidate | DU35: 2026-07-31T12:00:00Z | DV35: KBOB
A36: Bauteil | C36: KBOB_Material | CQ36: x | DT36: Candidate | DU36: 2026-07-31T12:00:00Z | DV36: KBOB

Sheet Gelöschte Bauteile
B1: D | C1: 05 | D1: . | E1: 01 | F1: . | G1: 004 | H1: . | I1: nnn | L1: Schalldämpfer | N1: 242.2 | O1: - | P1: - | Q1: - | R1: x | U1: x | V1: Rohrzubehör | Y1: Apparat HLKS | Z1: IfcDuctSilencerType | AA1: ROUND/RECTANGULAR | AD1: 200 | AE1: 200 | AF1: 300 | AG1: 300 | AH1: 300 | AI1: 300 | AV1: x | BE1: =IF(COUNTIF(AJ1:BD1,"x")>0,"x","") -> x
B2: D | C2: 05 | D2: . | E2: 01 | F2: . | G2: 004 | H2: . | I2: nnn | L2: Dacheinfassung | N2: 242.2 | O2: - | P2: - | Q2: - | R2: x | U2: x | V2: Rohrzubehör | Y2: Installationszubehör | Z2: IfcCoveringType | AA2: ROOFING | AD2: 200 | AE2: 200 | AF2: 300 | AG2: 300 | AH2: 300 | AI2: 300 | AV2: x | BE2: =IF(COUNTIF(AJ2:BD2,"x")>0,"x","") -> x
B3: D | C3: 05 | D3: . | E3: 01 | F3: . | G3: 004 | H3: . | I3: nnn | L3: Revisionsstück | N3: 242.2 | O3: - | P3: - | Q3: - | R3: x | U3: x | V3: Rohrformteile | Z3: IfcPipeSegmentType | AA3: SPOOL | AD3: 200 | AE3: 200 | AF3: 300 | AG3: 300 | AH3: 300 | AI3: 300 | AV3: x | BE3: =IF(COUNTIF(AJ3:BD3,"x")>0,"x","") -> x
B4: D | C4: 05 | D4: . | E4: 01 | F4: . | G4: 004 | H4: . | I4: nnn | L4: Messstutzen | N4: 242.2 | O4: - | P4: - | Q4: - | R4: x | U4: x | V4: Rohrformteile | Z4: IfcPipeFittingType | AA4: ENTRY | AD4: 200 | AE4: 200 | AF4: 300 | AG4: 300 | AH4: 300 | AI4: 300 | AV4: x | BE4: =IF(COUNTIF(AJ4:BD4,"x")>0,"x","") -> x
B5: D | C5: 05 | D5: . | E5: 01 | F5: . | G5: 004 | H5: . | I5: nnn | L5: Abscheider | N5: 242.2 | O5: - | P5: - | Q5: - | R5: x | U5: x | V5: Rohrzubehör | Y5: Armatur HLKS | Z5: IfcValveType | AA5: DRAWOFFCOCK | AD5: 200 | AE5: 200 | AF5: 300 | AG5: 300 | AH5: 300 | AI5: 300 | AV5: x | BE5: =IF(COUNTIF(AJ5:BD5,"x")>0,"x","") -> x
B6: D | C6: 05 | D6: . | E6: 01 | F6: . | G6: 004 | H6: . | I6: nnn | L6: Isolierstück | N6: 242.2 | O6: - | P6: - | Q6: - | R6: x | U6: x | V6: Rohrformteile | Z6: IfcPipeSegmentType | AA6: SPOOL | AD6: 200 | AE6: 200 | AF6: 300 | AG6: 300 | AH6: 300 | AI6: 300 | AV6: x | BE6: =IF(COUNTIF(AJ6:BD6,"x")>0,"x","") -> x
B7: D | C7: 05 | D7: . | E7: 01 | F7: . | G7: 004 | H7: . | I7: nnn | L7: Kontrolldeckel | N7: 242.2 | O7: - | P7: - | Q7: - | R7: x | U7: x | V7: Rohrzubehör | AV7: x | BE7: =IF(COUNTIF(AJ7:BD7,"x")>0,"x","") -> x
B8: D | C8: 05 | D8: . | E8: 01 | F8: . | G8: 004 | H8: . | I8: nnn | L8: Schlammsammler | N8: 242.2 | O8: - | P8: - | Q8: - | R8: x | U8: x | V8: Rohrzubehör | Y8: Apparat HLKS | Z8: IfcFilterType | AA8: WATERFILTER | AD8: 200 | AE8: 200 | AF8: 300 | AG8: 300 | AH8: 300 | AI8: 300 | AV8: x | BE8: =IF(COUNTIF(AJ8:BD8,"x")>0,"x","") -> x
B9: D | C9: 05 | D9: . | E9: 01 | F9: . | G9: 004 | H9: . | I9: nnn | L9: Storzkupplung | N9: 242.2 | O9: - | P9: - | Q9: - | R9: x | U9: x | V9: Rohrformteile | Z9: IfcPipeFittingType | AA9: CONNECTOR | AD9: 200 | AE9: 200 | AF9: 300 | AG9: 300 | AH9: 300 | AI9: 300 | AV9: x | BE9: =IF(COUNTIF(AJ9:BD9,"x")>0,"x","") -> x
B10: D | C10: 05 | D10: . | E10: 02 | F10: . | G10: 009 | H10: . | I10: nnn | L10: Wärmeübertrager | N10: 242.0 | O10: - | P10: - | Q10: - | R10: x | U10: x | V10: HLS-Bauteile | Y10: Apparat HLKS | Z10: IfcHeatExchanger | AA10: - | AD10: 200 | AE10: 200 | AF10: 300 | AG10: 300 | AH10: 300 | AI10: 300 | AV10: x | BE10: =IF(COUNTIF(AJ10:BD10,"x")>0,"x","") -> x
B11: D | C11: 05 | D11: . | E11: 02 | F11: . | G11: 009 | H11: . | I11: nnn | L11: Wassermangelsicherung | N11: 242.2 | O11: - | P11: - | Q11: - | R11: x | U11: x | V11: HLS-Bauteile | Y11: Schaltung & Steuerung HLKSE | Z11: IfcFlowController | AA11: - | AD11: 200 | AE11: 200 | AF11: 300 | AG11: 300 | AH11: 300 | AI11: 300 | AV11: x | BE11: =IF(COUNTIF(AJ11:BD11,"x")>0,"x","") -> x

Sheet Rules
A1: Class-Assignment | B1: Klassen-Zuordnung | C1: Affectation de classe | D1: Assegnazione della classe | E1: Property-Assignment | F1: Merkmals-Zuordnung | G1: Attribution de propriété | H1: Assegnazione della proprietà | I1: DataType | J1: IFC Data Type | K1: Status | L1: ISG - Informationssicherheitsgesetz | M1: FAIR Prinzipien | N1: LifecycleStatus
A2: Systems / Installations | B2: Systeme / Anlagen | C2: Systèmes / installations | D2: Sistemi / installazioni | E2: not defined | F2: nicht definiert | G2: non défini | H2: non definito | I2: BOOLEAN | J2: nicht definiert | K2: Preview | L2: nicht klassifiziert | M2: Zugänglich kostenpflichtig | N2: Preview
A3: Physical elements | B3: Physische Bauteile | C3: Éléments physiques | D3: Elementi fisici | E3: Identification and classification | F3: Identifikation und Klassifikation | G3: Identification et classification | H3: Identificazione e classificazione | I3: CHARACTER | J3: IfcBoolean | K3: Active | L3: intern | M3: Zugänglich unentgeltlich | N3: Active
A4: Spatial structure | B4: Räumliche Struktur | C4: Structure spatiale | D4: Struttura spaziale | E4: Manufacturer and product information | F4: Hersteller- und Produktinformationen | G4: Informations sur le fabricant et le produit | H4: Informazioni sul produttore e sul prodotto | I4: INTEGER | J4: IfcDate | K4: Inactive | L4: sensitiv | M4: Nicht zugänglich - kostenpflichtig | N4: Inactive
A5: Logical zones & groups | B5: Logische Zonen & Gruppen | C5: Zones logiques et groupes | D5: Zone logiche e gruppi | E5: Geometric characteristics | F5: Geometrische Eigenschaften | G5: Caractéristiques géométriques | H5: Caratteristiche geometriche | I5: REAL | J5: IfcDateTime | K5: Deprecated | L5: geheim | M5: Nicht zugänglich - unentgeltlich | N5: Deprecated
A6: Geometric references & grids | B6: Geometrische Referenzen & Raster | C6: Références géométriques et grilles | D6: Riferimenti geometrici e griglie | E6: Physical characteristics | F6: Physikalische Eigenschaften | G6: Caractéristiques physiques | H6: Caratteristiche fisiche | I6: STRING | J6: IfcDuration | K6: Retired | N6: Retired
A7: Actors | B7: Akteure | C7: Acteurs | D7: Attori | E7: Material and construction | F7: Material und Aufbau | G7: Matériau et constitution | H7: Materiale e struttura | I7: TIME | J7: IfcGloballyUniqueId | K7: Candidate | N7: Candidate
A8: Resources | B8: Ressourcen | C8: Ressources | D8: Risorse | E8: Operating conditions and limits | F8: Betriebsbedingungen und Grenzwerte | G8: Conditions de fonctionnement et limites | H8: Condizioni operative e limiti | I8: DATETIME | J8: IfcIdentifier | K8: Recorded | N8: Recorded
A9: Processes & tasks | B9: Prozesse & Aufgaben | C9: Processus et tâches | D9: Processi e compiti | E9: Performance characteristics | F9: Leistungs- und Funktionskennwerte | G9: Caractéristiques de performance et de fonctionnement | H9: Caratteristiche prestazionali e funzionali | J9: IfcInteger | K9: Superseded | N9: Superseded
E10: Hydraulic / flow characteristics | F10: Hydraulische / strömungstechnische Kennwerte | G10: Caractéristiques hydrauliques / d’écoulement | H10: Caratteristiche idrauliche / di flusso | J10: IfcLabel | K10: Incomplete | N10: Incomplete
E11: Thermal characteristics | F11: Thermische Kennwerte | G11: Caractéristiques thermiques | H11: Caratteristiche termiche | J11: IfcLengthMeasure
E12: Electrical characteristics | F12: Elektrische Kennwerte | G12: Caractéristiques électriques | H12: Caratteristiche elettriche | J12: IfcLocalTime
E13: Measurement, control and sensing | F13: Mess-, Steuer- und Regelungsdaten | G13: Caractéristiques de mesure, de commande et de détection | H13: Caratteristiche di misurazione, controllo e rilevamento | J13: IfcLogical
E14: Connection and interface characteristics | F14: Anschluss- und Schnittstelleninformationen | G14: Caractéristiques de raccordement et d’interface | H14: Caratteristiche di collegamento e interfaccia | J14: IfcNormalisedRatioMeasure
E15: Safety and protection characteristics | F15: Sicherheits- und Schutzmerkmale | G15: Caractéristiques de sécurité et de protection | H15: Caratteristiche di sicurezza e protezione | J15: IfcPositiveInteger
E16: Installation and delivery information | F16: Montage-, Einbau- und Lieferinformationen | G16: Informations de montage, d’installation et de livraison | H16: Informazioni di montaggio, installazione e fornitura | J16: IfcPositiveLengthMeasure
E17: Reference and documentation information | F17: Referenz- und Dokumentationsinformationen | G17: Informations de référence et de documentation | H17: Informazioni di riferimento e documentazione | J17: IfcPositiveRatioMeasure
J18: IfcPositiveTimeMeasure
J19: IfcRatioMeasure
J20: IfcReal
J21: IfcText
J22: IfcThermalTransmittanceMeasure
J23: IfcTime
J24: IfcURIReference
